Workbook

Sheet crono ejemplo
A1: N° | B1: Actividad | C1: Fecha | E1: Aspectos generales de planificación | N1: Impacto Real (%) | O1: Avance Real (%) | Q1: Área | AE1: % Completado Tarea | AF1: Valor Ganado | AG1: Valor Ganado (%) | AH1: Valor Ganado Acum (%)
E2: Dias | F2: HH | G2: % Impacto | H2: % Avance | I2: Esfuerzo (HH) | L2: Costo (UF) | Q2: Jefe de Proyecto | V2: Documentación | Y2: Investigación | AB2: Desarrollo
C3: Inicio | D3: Termino | I3: Unit. | J3: Acum. | K3: % De uso | L3: Unit. | M3: Acum. | P3: % De uso | Q3: % dedic | R3: HH esfuerzo | S3: Rol | T3: Valor HH (UF) | U3: Costo (UF) | V3: % dedic | W3: HH esfuerzo | X3: Costo (UF) | Y3: % dedic | Z3: HH esfuerzo | AA3: Costo (UF) | AB3: % dedic | AC3: HH esfuerzo | AD3: Costo (UF)
A4: 1 | B4: Fase de Inicio | C4: 44656 | D4: 44670 | E4: =_xludf.DAYs(D4,C4)+1 -> #NAME? | F4: =SUM(F5,F7) -> 26 | G4: =SUM(G5,G7) -> 0.029511918 | I4: =SUM(I5,I7) -> #REF! | J4: =I4 -> #REF! | K4: =SUM(K5,K7) -> #REF! | L4: =SUM(L5,L7) -> #REF! | M4: =L4 -> #REF! | P4: =M4/$M$93 -> #REF!
A5: 1.1 | B5: Relevamiento inicial del Proyecto | C5: 44656 | D5: 44656 | E5: =_xludf.DAYs(D5,C5)+1 -> #NAME? | F5: =SUM(F6) -> 1 | G5: =G6 -> 0.0011350738 | I5: =SUM(I6) -> #REF! | J5: =J6 -> #REF! | K5: =SUM(J6) -> #REF! | L5: =L6 -> #REF! | M5: =L5 -> #REF! | P5: =SUM(P6) -> #REF!
A6: 1.1.1 | B6: Definición de Roles | C6: 44656 | D6: 44656 | E6: =_xludf.DAYs(D6,C6)+1 -> #NAME? | F6: 1 | G6: =F6/F105 -> 0.0011350738 | H6: =G6 -> 0.0011350738 | I6: =SUM(R6,W6,Z6,AC6) -> #REF! | J6: =I6 -> #REF! | K6: =J6/$J$104 -> #REF! | L6: =SUM(U6,X6,AA6,AD6) -> #REF! | M6: =L6 -> #REF! | N6: =G6*AE6 -> 0 | O6: =N6 -> 0 | P6: =M6/$M$93 -> #REF! | Q6: =R6/F6 -> 1 | R6: 1 | S6: L | T6: =IF(S6="L",0.68,IF(S6="JP",0.57,IF(S6="JI",0.57,IF(S6="JD",0.57,IF(S6="P",0.24,IF(S6="I",0.12,IF(S6="D",0.13))))))) -> 0.68 | U6: =T6*R6 -> 0.68 | V6: =W6/F6 -> #REF! | W6: ='CD R Documentación'!O7+'CD R Documentación'!T7+'CD R Documentación'!Y7+'CD R Documentación'!AD7+'CD R Documentación'!AI7+'CD R Documentación'!AN7+#REF! -> #REF! | X6: ='CD R Documentación'!R7+'CD R Documentación'!W7+'CD R Documentación'!AB7+'CD R Documentación'!AG7+'CD R Documentación'!AL7+'CD R Documentación'!AQ7+#REF! -> #REF! | Y6: =Z6/F6 -> 0 | Z6: ='CD R Investigación'!P7+'CD R Investigación'!U7+'CD R Investigación'!Z7+'CD R Investigación'!AE7+'CD R Investigación'!AJ7+'CD R Investigación'!AO7+'CD R Investigación'!AT7+'CD R Investigación'!AY7 -> 0 | AA6: ='CD R Investigación'!S7+'CD R Investigación'!X7+'CD R Investigación'!AC7+'CD R Investigación'!AH7+'CD R Investigación'!AM7+'CD R Investigación'!AR7+'CD R Investigación'!AW7+'CD R Investigación'!BB7 -> 0 | AB6: =AC6/F6 -> #REF! | AC6: ='CD R Desarrollo'!P7+'CD R Desarrollo'!U7+'CD R Desarrollo'!Z7+'CD R Desarrollo'!AE7+'CD R Desarrollo'!AJ7+'CD R Desarrollo'!AO7+#REF!+#REF! -> #REF! | AD6: ='CD R Desarrollo'!S7+'CD R Desarrollo'!X7+'CD R Desarrollo'!AC7+'CD R Desarrollo'!AH7+'CD R Desarrollo'!AM7+'CD R Desarrollo'!AR7+#REF!+#REF! -> #REF! | AE6: 0 | AF6: ='PL Cronograma detallado'!L40*AE6 -> 0 | AG6: =AF6/'PL Cronograma detallado'!M257 -> #DIV/0! | AH6: =AG6 -> #DIV/0!
A7: 1.2 | B7: Gestión del Alcance | C7: 44656 | D7: 44662 | E7: =_xludf.DAYs(D7,C7)+1 -> #NAME? | F7: =SUM(F8:F19) -> 25 | G7: =SUM(G8:G19) -> 0.028376844 | H7: =SUM(H6,G7) -> 0.029511918 | I7: =SUM(I8:I19) -> #REF! | J7: =SUM(I7,J5) -> #REF! | K7: =SUM(K8:K16) -> #REF! | L7: =SUM(L8:L19) -> #REF! | M7: =SUM(L7,M5) -> #REF! | P7: =M7/$M$93 -> #REF!
A8: 1.2.1 | B8: Organización de grupos de Trabajo | C8: 44657 | D8: 44657 | E8: =_xludf.DAYs(D8,C8)+1 -> #NAME? | F8: 1 | G8: =F8/F$105 -> 0.0011350738 | H8: =SUM(H6,G8) -> 0.0022701476 | I8: =SUM(R8,W8,Z8,AC8) -> #REF! | J8: =SUM(I8,J6) -> #REF! | K8: =J8/$J$104 -> #REF! | L8: =SUM(U8,X8,AA8,AD8) -> #REF! | M8: =SUM(L8,M6) -> #REF! | N8: =G8*AE8 -> 0.0011350738 | O8: =SUM(N8,O6) -> 0.0011350738 | P8: =M8/$M$93 -> #REF! | Q8: =R8/F8 -> 1 | R8: 1 | S8: L | T8: =IF(S8="L",0.68,IF(S8="JP",0.57,IF(S8="JI",0.57,IF(S8="JD",0.57,IF(S8="P",0.24,IF(S8="I",0.12,IF(S8="D",0.13))))))) -> 0.68 | U8: =T8*R8 -> 0.68 | V8: =W8/F8 -> #REF! | W8: ='CD R Documentación'!O9+'CD R Documentación'!T9+'CD R Documentación'!Y9+'CD R Documentación'!AD9+'CD R Documentación'!AI9+'CD R Documentación'!AN9+#REF! -> #REF! | X8: ='CD R Documentación'!R9+'CD R Documentación'!W9+'CD R Documentación'!AB9+'CD R Documentación'!AG9+'CD R Documentación'!AL9+'CD R Documentación'!AQ9+#REF! -> #REF! | Y8: =Z8/F8 -> 3 | Z8: ='CD R Investigación'!P9+'CD R Investigación'!U9+'CD R Investigación'!Z9+'CD R Investigación'!AE9+'CD R Investigación'!AJ9+'CD R Investigación'!AO9+'CD R Investigación'!AT9+'CD R Investigación'!AY9 -> 3 | AA8: ='CD R Investigación'!S9+'CD R Investigación'!X9+'CD R Investigación'!AC9+'CD R Investigación'!AH9+'CD R Investigación'!AM9+'CD R Investigación'!AR9+'CD R Investigación'!AW9+'CD R Investigación'!BB9 -> 1.32 | AB8: =AC8/F8 -> #REF! | AC8: ='CD R Desarrollo'!P9+'CD R Desarrollo'!U9+'CD R Desarrollo'!Z9+'CD R Desarrollo'!AE9+'CD R Desarrollo'!AJ9+'CD R Desarrollo'!AO9+#REF!+#REF! -> #REF! | AD8: ='CD R Desarrollo'!S9+'CD R Desarrollo'!X9+'CD R Desarrollo'!AC9+'CD R Desarrollo'!AH9+'CD R Desarrollo'!AM9+'CD R Desarrollo'!AR9+#REF!+#REF! -> #REF! | AE8: 1 | AF8: ='PL Cronograma detallado'!L42*AE8 -> 9.67 | AG8: =AF8/'PL Cronograma detallado'!M$257 -> #DIV/0! | AH8: =AG8+AH6 -> #DIV/0!
A9: 1.2.2 | B9: Definición de Enfoques y Justificación | C9: 44657 | D9: 44658 | E9: =_xludf.DAYs(D9,C9)+1 -> #NAME? | F9: 2 | G9: =F9/F$105 -> 0.0022701476 | H9: =SUM(H8,G9) -> 0.0045402951 | I9: =SUM(R9,W9,Z9,AC9) -> #REF! | J9: =SUM(I9,J8) -> #REF! | K9: =J9/$J$104 -> #REF! | L9: =SUM(U9,X9,AA9,AD9) -> #REF! | M9: =SUM(L9,M8) -> #REF! | N9: =G9*AE9 -> 0.0022701476 | O9: =SUM(N9,O8) -> 0.0034052213 | P9: =M9/$M$93 -> #REF! | Q9: =R9/F9 -> 0.5 | R9: 1 | S9: L | T9: =IF(S9="L",0.68,IF(S9="JP",0.57,IF(S9="JI",0.57,IF(S9="JD",0.57,IF(S9="P",0.24,IF(S9="I",0.12,IF(S9="D",0.13))))))) -> 0.68 | U9: =T9*R9 -> 0.68 | V9: =W9/F9 -> #REF! | W9: ='CD R Documentación'!O10+'CD R Documentación'!T10+'CD R Documentación'!Y10+'CD R Documentación'!AD10+'CD R Documentación'!AI10+'CD R Documentación'!AN10+#REF! -> #REF! | X9: ='CD R Documentación'!R10+'CD R Documentación'!W10+'CD R Documentación'!AB10+'CD R Documentación'!AG10+'CD R Documentación'!AL10+'CD R Documentación'!AQ10+#REF! -> #REF! | Y9: =Z9/F9 -> 0 | Z9: ='CD R Investigación'!P10+'CD R Investigación'!U10+'CD R Investigación'!Z10+'CD R Investigación'!AE10+'CD R Investigación'!AJ10+'CD R Investigación'!AO10+'CD R Investigación'!AT10+'CD R Investigación'!AY10 -> 0 | AA9: ='CD R Investigación'!S10+'CD R Investigación'!X10+'CD R Investigación'!AC10+'CD R Investigación'!AH10+'CD R Investigación'!AM10+'CD R Investigación'!AR10+'CD R Investigación'!AW10+'CD R Investigación'!BB10 -> 0 | AB9: =AC9/F9 -> #REF! | AC9: ='CD R Desarrollo'!P10+'CD R Desarrollo'!U10+'CD R Desarrollo'!Z10+'CD R Desarrollo'!AE10+'CD R Desarrollo'!AJ10+'CD R Desarrollo'!AO10+#REF!+#REF! -> #REF! | AD9: ='CD R Desarrollo'!S10+'CD R Desarrollo'!X10+'CD R Desarrollo'!AC10+'CD R Desarrollo'!AH10+'CD R Desarrollo'!AM10+'CD R Desarrollo'!AR10+#REF!+#REF! -> #REF! | AE9: 1 | AF9: ='PL Cronograma detallado'!L58*AE9 -> 49.43 | AG9: =AF9/'PL Cronograma detallado'!M$257 -> #DIV/0! | AH9: =AG9+AH8 -> #DIV/0!
A10: 1.2.3 | B10: Establecer Alcances y Limitaciones | C10: 44657 | D10: 44658 | E10: =_xludf.DAYs(D10,C10)+1 -> #NAME? | F10: 2 | G10: =F10/F$105 -> 0.0022701476 | H10: =SUM(H9,G10) -> 0.0068104427 | I10: =SUM(R10,W10,Z10,AC10) -> #REF! | J10: =SUM(I10,J9) -> #REF! | K10: =J10/$J$104 -> #REF! | L10: =SUM(U10,X10,AA10,AD10) -> #REF! | M10: =SUM(L10,M9) -> #REF! | N10: =G10*AE10 -> 0.0022701476 | O10: =SUM(N10,O9) -> 0.0056753689 | P10: =M10/$M$93 -> #REF! | Q10: =R10/F10 -> 0.5 | R10: 1 | S10: L | T10: =IF(S10="L",0.68,IF(S10="JP",0.57,IF(S10="JI",0.57,IF(S10="JD",0.57,IF(S10="P",0.24,IF(S10="I",0.12,IF(S10="D",0.13))))))) -> 0.68 | U10: =T10*R10 -> 0.68 | V10: =W10/F10 -> #REF! | W10: ='CD R Documentación'!O11+'CD R Documentación'!T11+'CD R Documentación'!Y11+'CD R Documentación'!AD11+'CD R Documentación'!AI11+'CD R Documentación'!AN11+#REF! -> #REF! | X10: ='CD R Documentación'!R11+'CD R Documentación'!W11+'CD R Documentación'!AB11+'CD R Documentación'!AG11+'CD R Documentación'!AL11+'CD R Documentación'!AQ11+#REF! -> #REF! | Y10: =Z10/F10 -> 1.5 | Z10: ='CD R Investigación'!P11+'CD R Investigación'!U11+'CD R Investigación'!Z11+'CD R Investigación'!AE11+'CD R Investigación'!AJ11+'CD R Investigación'!AO11+'CD R Investigación'!AT11+'CD R Investigación'!AY11 -> 3 | AA10: ='CD R Investigación'!S11+'CD R Investigación'!X11+'CD R Investigación'!AC11+'CD R Investigación'!AH11+'CD R Investigación'!AM11+'CD R Investigación'!AR11+'CD R Investigación'!AW11+'CD R Investigación'!BB11 -> 1.32 | AB10: =AC10/F10 -> #REF! | AC10: ='CD R Desarrollo'!P11+'CD R Desarrollo'!U11+'CD R Desarrollo'!Z11+'CD R Desarrollo'!AE11+'CD R Desarrollo'!AJ11+'CD R Desarrollo'!AO11+#REF!+#REF! -> #REF! | AD10: ='CD R Desarrollo'!S11+'CD R Desarrollo'!X11+'CD R Desarrollo'!AC11+'CD R Desarrollo'!AH11+'CD R Desarrollo'!AM11+'CD R Desarrollo'!AR11+#REF!+#REF! -> #REF! | AE10: 1 | AF10: ='PL Cronograma detallado'!L59*AE10 -> 34.27 | AG10: =AF10/'PL Cronograma detallado'!M$257 -> #DIV/0! | AH10: =AG10+AH9 -> #DIV/0!
A11: 1.2.4 | B11: Definir Metodologias | C11: 44657 | D11: 44660 | E11: =_xludf.DAYs(D11,C11)+1 -> #NAME? | F11: 2 | G11: =F11/F$105 -> 0.0022701476 | H11: =SUM(H10,G11) -> 0.0090805902 | I11: =SUM(R11,W11,Z11,AC11) -> #REF! | J11: =SUM(I11,J10) -> #REF! | K11: =J11/$J$104 -> #REF! | L11: =SUM(U11,X11,AA11,AD11) -> #REF! | M11: =SUM(L11,M10) -> #REF! | N11: =G11*AE11 -> 0.0022701476 | O11: =SUM(N11,O10) -> 0.0079455165 | P11: =M11/$M$93 -> #REF! | Q11: =R11/F11 -> 0.5 | R11: 1 | S11: L | T11: =IF(S11="L",0.68,IF(S11="JP",0.57,IF(S11="JI",0.57,IF(S11="JD",0.57,IF(S11="P",0.24,IF(S11="I",0.12,IF(S11="D",0.13))))))) -> 0.68 | U11: =T11*R11 -> 0.68 | V11: =W11/F11 -> #REF! | W11: ='CD R Documentación'!O12+'CD R Documentación'!T12+'CD R Documentación'!Y12+'CD R Documentación'!AD12+'CD R Documentación'!AI12+'CD R Documentación'!AN12+#REF! -> #REF! | X11: ='CD R Documentación'!R12+'CD R Documentación'!W12+'CD R Documentación'!AB12+'CD R Documentación'!AG12+'CD R Documentación'!AL12+'CD R Documentación'!AQ12+#REF! -> #REF! | Y11: =Z11/F11 -> 1 | Z11: ='CD R Investigación'!P12+'CD R Investigación'!U12+'CD R Investigación'!Z12+'CD R Investigación'!AE12+'CD R Investigación'!AJ12+'CD R Investigación'!AO12+'CD R Investigación'!AT12+'CD R Investigación'!AY12 -> 2 | AA11: ='CD R Investigación'!S12+'CD R Investigación'!X12+'CD R Investigación'!AC12+'CD R Investigación'!AH12+'CD R Investigación'!AM12+'CD R Investigación'!AR12+'CD R Investigación'!AW12+'CD R Investigación'!BB12 -> 0.88 | AB11: =AC11/F11 -> #REF! | AC11: ='CD R Desarrollo'!P12+'CD R Desarrollo'!U12+'CD R Desarrollo'!Z12+'CD R Desarrollo'!AE12+'CD R Desarrollo'!AJ12+'CD R Desarrollo'!AO12+#REF!+#REF! -> #REF! | AD11: ='CD R Desarrollo'!S12+'CD R Desarrollo'!X12+'CD R Desarrollo'!AC12+'CD R Desarrollo'!AH12+'CD R Desarrollo'!AM12+'CD R Desarrollo'!AR12+#REF!+#REF! -> #REF! | AE11: 1 | AF11: ='PL Cronograma detallado'!L60*AE11 -> 13.81 | AG11: =AF11/'PL Cronograma detallado'!M$257 -> #DIV/0! | AH11: =AG11+AH10 -> #DIV/0!
A12: 1.2.5 | B12: Definir Plan de Hitos | C12: 44657 | D12: 44657 | E12: =_xludf.DAYs(D12,C12)+1 -> #NAME? | F12: 1 | G12: =F12/F$105 -> 0.0011350738 | H12: =SUM(H11,G12) -> 0.010215664 | I12: =SUM(R12,W12,Z12,AC12) -> #REF! | J12: =SUM(I12,J11) -> #REF! | K12: =J12/$J$104 -> #REF! | L12: =SUM(U12,X12,AA12,AD12) -> #REF! | M12: =SUM(L12,M11) -> #REF! | N12: =G12*AE12 -> 0.0011350738 | O12: =SUM(N12,O11) -> 0.0090805902 | P12: =M12/$M$93 -> #REF! | Q12: =R12/F12 -> 1 | R12: 1 | S12: L | T12: =IF(S12="L",0.68,IF(S12="JP",0.57,IF(S12="JI",0.57,IF(S12="JD",0.57,IF(S12="P",0.24,IF(S12="I",0.12,IF(S12="D",0.13))))))) -> 0.68 | U12: =T12*R12 -> 0.68 | V12: =W12/F12 -> #REF! | W12: ='CD R Documentación'!O13+'CD R Documentación'!T13+'CD R Documentación'!Y13+'CD R Documentación'!AD13+'CD R Documentación'!AI13+'CD R Documentación'!AN13+#REF! -> #REF! | X12: ='CD R Documentación'!R13+'CD R Documentación'!W13+'CD R Documentación'!AB13+'CD R Documentación'!AG13+'CD R Documentación'!AL13+'CD R Documentación'!AQ13+#REF! -> #REF! | Y12: =Z12/F12 -> 1 | Z12: ='CD R Investigación'!P13+'CD R Investigación'!U13+'CD R Investigación'!Z13+'CD R Investigación'!AE13+'CD R Investigación'!AJ13+'CD R Investigación'!AO13+'CD R Investigación'!AT13+'CD R Investigación'!AY13 -> 1 | AA12: ='CD R Investigación'!S13+'CD R Investigación'!X13+'CD R Investigación'!AC13+'CD R Investigación'!AH13+'CD R Investigación'!AM13+'CD R Investigación'!AR13+'CD R Investigación'!AW13+'CD R Investigación'!BB13 -> 0.44 | AB12: =AC12/F12 -> #REF! | AC12: ='CD R Desarrollo'!P13+'CD R Desarrollo'!U13+'CD R Desarrollo'!Z13+'CD R Desarrollo'!AE13+'CD R Desarrollo'!AJ13+'CD R Desarrollo'!AO13+#REF!+#REF! -> #REF! | AD12: ='CD R Desarrollo'!S13+'CD R Desarrollo'!X13+'CD R Desarrollo'!AC13+'CD R Desarrollo'!AH13+'CD R Desarrollo'!AM13+'CD R Desarrollo'!AR13+#REF!+#REF! -> #REF! | AE12: 1 | AF12: ='PL Cronograma detallado'!L62*AE12 -> 19.67 | AG12: =AF12/'PL Cronograma detallado'!M$257 -> #DIV/0! | AH12: =AG12+AH11 -> #DIV/0!
A13: 1.2.6 | B13: Elaborar Cronograma | C13: 44657 | D13: 44660 | E13: =_xludf.DAYs(D13,C13)+1 -> #NAME? | F13: 5 | G13: =F13/F$105 -> 0.0056753689 | H13: =SUM(H12,G13) -> 0.015891033 | I13: =SUM(R13,W13,Z13,AC13) -> #REF! | J13: =SUM(I13,J12) -> #REF! | K13: =J13/$J$104 -> #REF! | L13: =SUM(U13,X13,AA13,AD13) -> #REF! | M13: =SUM(L13,M12) -> #REF! | N13: =G13*AE13 -> 0.0056753689 | O13: =SUM(N13,O12) -> 0.014755959 | P13: =M13/$M$93 -> #REF! | Q13: =R13/F13 -> 0.2 | R13: 1 | S13: L | T13: =IF(S13="L",0.68,IF(S13="JP",0.57,IF(S13="JI",0.57,IF(S13="JD",0.57,IF(S13="P",0.24,IF(S13="I",0.12,IF(S13="D",0.13))))))) -> 0.68 | U13: =T13*R13 -> 0.68 | V13: =W13/F13 -> #REF! | W13: ='CD R Documentación'!O14+'CD R Documentación'!T14+'CD R Documentación'!Y14+'CD R Documentación'!AD14+'CD R Documentación'!AI14+'CD R Documentación'!AN14+#REF! -> #REF! | X13: ='CD R Documentación'!R14+'CD R Documentación'!W14+'CD R Documentación'!AB14+'CD R Documentación'!AG14+'CD R Documentación'!AL14+'CD R Documentación'!AQ14+#REF! -> #REF! | Y13: =Z13/F13 -> 0.8 | Z13: ='CD R Investigación'!P14+'CD R Investigación'!U14+'CD R Investigación'!Z14+'CD R Investigación'!AE14+'CD R Investigación'!AJ14+'CD R Investigación'!AO14+'CD R Investigación'!AT14+'CD R Investigación'!AY14 -> 4 | AA13: ='CD R Investigación'!S14+'CD R Investigación'!X14+'CD R Investigación'!AC14+'CD R Investigación'!AH14+'CD R Investigación'!AM14+'CD R Investigación'!AR14+'CD R Investigación'!AW14+'CD R Investigación'!BB14 -> 1.76 | AB13: =AC13/F13 -> #REF! | AC13: ='CD R Desarrollo'!P14+'CD R Desarrollo'!U14+'CD R Desarrollo'!Z14+'CD R Desarrollo'!AE14+'CD R Desarrollo'!AJ14+'CD R Desarrollo'!AO14+#REF!+#REF! -> #REF! | AD13: ='CD R Desarrollo'!S14+'CD R Desarrollo'!X14+'CD R Desarrollo'!AC14+'CD R Desarrollo'!AH14+'CD R Desarrollo'!AM14+'CD R Desarrollo'!AR14+#REF!+#REF! -> #REF! | AE13: 1 | AF13: ='PL Cronograma detallado'!L63*AE13 -> 7.65 | AG13: =AF13/'PL Cronograma detallado'!M$257 -> #DIV/0! | AH13: =AG13+AH12 -> #DIV/0!
A14: 1.2.7 | B14: Distribución del Esfuerzo | C14: 44658 | D14: 44659 | E14: =_xludf.DAYs(D14,C14)+1 -> #NAME? | F14: 4 | G14: =F14/F$105 -> 0.0045402951 | H14: =SUM(H13,G14) -> 0.020431328 | I14: =SUM(R14,W14,Z14,AC14) -> #REF! | J14: =SUM(I14,J13) -> #REF! | K14: =J14/$J$104 -> #REF! | L14: =SUM(U14,X14,AA14,AD14) -> #REF! | M14: =SUM(L14,M13) -> #REF! | N14: =G14*AE14 -> 0.0045402951 | O14: =SUM(N14,O13) -> 0.019296254 | P14: =M14/$M$93 -> #REF! | Q14: =R14/F14 -> 0.25 | R14: 1 | S14: L | T14: =IF(S14="L",0.68,IF(S14="JP",0.57,IF(S14="JI",0.57,IF(S14="JD",0.57,IF(S14="P",0.24,IF(S14="I",0.12,IF(S14="D",0.13))))))) -> 0.68 | U14: =T14*R14 -> 0.68 | V14: =W14/F14 -> #REF! | W14: ='CD R Documentación'!O15+'CD R Documentación'!T15+'CD R Documentación'!Y15+'CD R Documentación'!AD15+'CD R Documentación'!AI15+'CD R Documentación'!AN15+#REF! -> #REF! | X14: ='CD R Documentación'!R15+'CD R Documentación'!W15+'CD R Documentación'!AB15+'CD R Documentación'!AG15+'CD R Documentación'!AL15+'CD R Documentación'!AQ15+#REF! -> #REF! | Y14: =Z14/F14 -> 0.75 | Z14: ='CD R Investigación'!P15+'CD R Investigación'!U15+'CD R Investigación'!Z15+'CD R Investigación'!AE15+'CD R Investigación'!AJ15+'CD R Investigación'!AO15+'CD R Investigación'!AT15+'CD R Investigación'!AY15 -> 3 | AA14: ='CD R Investigación'!S15+'CD R Investigación'!X15+'CD R Investigación'!AC15+'CD R Investigación'!AH15+'CD R Investigación'!AM15+'CD R Investigación'!AR15+'CD R Investigación'!AW15+'CD R Investigación'!BB15 -> 1.32 | AB14: =AC14/F14 -> #REF! | AC14: ='CD R Desarrollo'!P15+'CD R Desarrollo'!U15+'CD R Desarrollo'!Z15+'CD R Desarrollo'!AE15+'CD R Desarrollo'!AJ15+'CD R Desarrollo'!AO15+#REF!+#REF! -> #REF! | AD14: ='CD R Desarrollo'!S15+'CD R Desarrollo'!X15+'CD R Desarrollo'!AC15+'CD R Desarrollo'!AH15+'CD R Desarrollo'!AM15+'CD R Desarrollo'!AR15+#REF!+#REF! -> #REF! | AE14: 1 | AF14: ='PL Cronograma detallado'!L64*AE14 -> 7.65 | AG14: =AF14/'PL Cronograma detallado'!M$257 -> #DIV/0! | AH14: =AG14+AH13 -> #DIV/0!
A15: 1.2.8 | B15: Definir Costos | C15: 44658 | D15: 44659 | E15: 1 | F15: 1 | G15: =F15/F$105 -> 0.0011350738 | H15: =SUM(H14,G15) -> 0.021566402 | I15: =SUM(R15,W15,Z15,AC15) -> #REF! | J15: =SUM(I15,J14) -> #REF! | K15: =J15/$J$104 -> #REF! | L15: =SUM(U15,X15,AA15,AD15) -> #REF! | M15: =SUM(L15,M14) -> #REF! | N15: =G15*AE15 -> 0.0011350738 | O15: =SUM(N15,O14) -> 0.020431328 | P15: =M15/$M$93 -> #REF! | Q15: =R15/F15 -> 1 | R15: 1 | S15: L | T15: =IF(S15="L",0.68,IF(S15="JP",0.57,IF(S15="JI",0.57,IF(S15="JD",0.57,IF(S15="P",0.24,IF(S15="I",0.12,IF(S15="D",0.13))))))) -> 0.68 | U15: =T15*R15 -> 0.68 | V15: =W15/F15 -> #REF! | W15: ='CD R Documentación'!O16+'CD R Documentación'!T16+'CD R Documentación'!Y16+'CD R Documentación'!AD16+'CD R Documentación'!AI16+'CD R Documentación'!AN16+#REF! -> #REF! | X15: ='CD R Documentación'!R16+'CD R Documentación'!W16+'CD R Documentación'!AB16+'CD R Documentación'!AG16+'CD R Documentación'!AL16+'CD R Documentación'!AQ16+#REF! -> #REF! | Y15: =Z15/F15 -> 2 | Z15: ='CD R Investigación'!P16+'CD R Investigación'!U16+'CD R Investigación'!Z16+'CD R Investigación'!AE16+'CD R Investigación'!AJ16+'CD R Investigación'!AO16+'CD R Investigación'!AT16+'CD R Investigación'!AY16 -> 2 | AA15: ='CD R Investigación'!S16+'CD R Investigación'!X16+'CD R Investigación'!AC16+'CD R Investigación'!AH16+'CD R Investigación'!AM16+'CD R Investigación'!AR16+'CD R Investigación'!AW16+'CD R Investigación'!BB16 -> 0.88 | AB15: =AC15/F15 -> #REF! | AC15: ='CD R Desarrollo'!P16+'CD R Desarrollo'!U16+'CD R Desarrollo'!Z16+'CD R Desarrollo'!AE16+'CD R Desarrollo'!AJ16+'CD R Desarrollo'!AO16+#REF!+#REF! -> #REF! | AD15: ='CD R Desarrollo'!S16+'CD R Desarrollo'!X16+'CD R Desarrollo'!AC16+'CD R Desarrollo'!AH16+'CD R Desarrollo'!AM16+'CD R Desarrollo'!AR16+#REF!+#REF! -> #REF! | AE15: 1 | AF15: ='PL Cronograma detallado'!L65*AE15 -> 4.37 | AG15: =AF15/'PL Cronograma detallado'!M$257 -> #DIV/0! | AH15: =AG15+AH14 -> #DIV/0!
A16: 1.2.9 | B16: Definir Criterio de Evaluación de Integrantes | C16: 44659 | D16: 44659 | E16: =_xludf.DAYs(D16,C16)+1 -> #NAME? | F16: 1 | G16: =F16/F$105 -> 0.0011350738 | H16: =SUM(H15,G16) -> 0.022701476 | I16: =SUM(R16,W16,Z16,AC16) -> #REF! | J16: =SUM(I16,J15) -> #REF! | K16: =J16/$J$104 -> #REF! | L16: =SUM(U16,X16,AA16,AD16) -> #REF! | M16: =SUM(L16,M15) -> #REF! | N16: =G16*AE16 -> 0.0011350738 | O16: =SUM(N16,O15) -> 0.021566402 | P16: =M16/$M$93 -> #REF! | Q16: =R16/F16 -> 1 | R16: 1 | S16: L | T16: =IF(S16="L",0.68,IF(S16="JP",0.57,IF(S16="JI",0.57,IF(S16="JD",0.57,IF(S16="P",0.24,IF(S16="I",0.12,IF(S16="D",0.13))))))) -> 0.68 | U16: =T16*R16 -> 0.68 | V16: =W16/F16 -> #REF! | W16: ='CD R Documentación'!O17+'CD R Documentación'!T17+'CD R Documentación'!Y17+'CD R Documentación'!AD17+'CD R Documentación'!AI17+'CD R Documentación'!AN17+#REF! -> #REF! | X16: ='CD R Documentación'!R17+'CD R Documentación'!W17+'CD R Documentación'!AB17+'CD R Documentación'!AG17+'CD R Documentación'!AL17+'CD R Documentación'!AQ17+#REF! -> #REF! | Y16: =Z16/F16 -> 2 | Z16: ='CD R Investigación'!P17+'CD R Investigación'!U17+'CD R Investigación'!Z17+'CD R Investigación'!AE17+'CD R Investigación'!AJ17+'CD R Investigación'!AO17+'CD R Investigación'!AT17+'CD R Investigación'!AY17 -> 2 | AA16: ='CD R Investigación'!S17+'CD R Investigación'!X17+'CD R Investigación'!AC17+'CD R Investigación'!AH17+'CD R Investigación'!AM17+'CD R Investigación'!AR17+'CD R Investigación'!AW17+'CD R Investigación'!BB17 -> 0.88 | AB16: =AC16/F16 -> #REF! | AC16: ='CD R Desarrollo'!P17+'CD R Desarrollo'!U17+'CD R Desarrollo'!Z17+'CD R Desarrollo'!AE17+'CD R Desarrollo'!AJ17+'CD R Desarrollo'!AO17+#REF!+#REF! -> #REF! | AD16: ='CD R Desarrollo'!S17+'CD R Desarrollo'!X17+'CD R Desarrollo'!AC17+'CD R Desarrollo'!AH17+'CD R Desarrollo'!AM17+'CD R Desarrollo'!AR17+#REF!+#REF! -> #REF! | AE16: 1 | AF16: ='PL Cronograma detallado'!L29*AE16 -> 0 | AG16: =AF16/'PL Cronograma detallado'!M$257 -> #DIV/0! | AH16: =AG16+AH15 -> #DIV/0!
A17: 1.3 | B17: Elaboración Informe Propuesta | C17: 44656 | D17: 44661 | E17: =_xludf.DAYs(D17,C17)+1 -> #NAME? | F17: 4 | G17: =F17/F$105 -> 0.0045402951 | H17: =SUM(H16,G17) -> 0.027241771 | I17: =SUM(R17,W17,Z17,AC17) -> #REF! | J17: =SUM(I17,J16) -> #REF! | K17: =J17/$J$104 -> #REF! | L17: =SUM(U17,X17,AA17,AD17) -> #REF! | M17: =SUM(L17,M16) -> #REF! | N17: =G17*AE17 -> 0.0045402951 | O17: =SUM(N17,O16) -> 0.026106697 | P17: =M17/$M$93 -> #REF! | Q17: =R17/F17 -> 0.375 | R17: 1.5 | S17: L | T17: =IF(S17="L",0.68,IF(S17="JP",0.57,IF(S17="JI",0.57,IF(S17="JD",0.57,IF(S17="P",0.24,IF(S17="I",0.12,IF(S17="D",0.13))))))) -> 0.68 | U17: =T17*R17 -> 1.02 | V17: =W17/F17 -> #REF! | W17: ='CD R Documentación'!O18+'CD R Documentación'!T18+'CD R Documentación'!Y18+'CD R Documentación'!AD18+'CD R Documentación'!AI18+'CD R Documentación'!AN18+#REF! -> #REF! | X17: ='CD R Documentación'!R18+'CD R Documentación'!W18+'CD R Documentación'!AB18+'CD R Documentación'!AG18+'CD R Documentación'!AL18+'CD R Documentación'!AQ18+#REF! -> #REF! | Y17: =Z17/F17 -> 1 | Z17: ='CD R Investigación'!P18+'CD R Investigación'!U18+'CD R Investigación'!Z18+'CD R Investigación'!AE18+'CD R Investigación'!AJ18+'CD R Investigación'!AO18+'CD R Investigación'!AT18+'CD R Investigación'!AY18 -> 4 | AA17: ='CD R Investigación'!S18+'CD R Investigación'!X18+'CD R Investigación'!AC18+'CD R Investigación'!AH18+'CD R Investigación'!AM18+'CD R Investigación'!AR18+'CD R Investigación'!AW18+'CD R Investigación'!BB18 -> 1.76 | AB17: =AC17/F17 -> #REF! | AC17: ='CD R Desarrollo'!P18+'CD R Desarrollo'!U18+'CD R Desarrollo'!Z18+'CD R Desarrollo'!AE18+'CD R Desarrollo'!AJ18+'CD R Desarrollo'!AO18+#REF!+#REF! -> #REF! | AD17: ='CD R Desarrollo'!S18+'CD R Desarrollo'!X18+'CD R Desarrollo'!AC18+'CD R Desarrollo'!AH18+'CD R Desarrollo'!AM18+'CD R Desarrollo'!AR18+#REF!+#REF! -> #REF! | AE17: 1 | AF17: =#REF!*AE17 -> #REF! | AG17: =AF17/'PL Cronograma detallado'!M$257 -> #REF! | AH17: =AG17+AH16 -> #REF!
A18: 1.3.1 | B18: Reunión de Líderes 1 | C18: 44659 | D18: 44659 | E18: =_xludf.DAYs(D18,C18)+1 -> #NAME? | F18: 1 | G18: =F18/F$105 -> 0.0011350738 | H18: =SUM(H17,G18) -> 0.028376844 | I18: =SUM(R18,W18,Z18,AC18) -> #REF! | J18: =SUM(I18,J17) -> #REF! | K18: =J18/$J$104 -> #REF! | L18: =SUM(U18,X18,AA18,AD18) -> #REF! | M18: =SUM(L18,M17) -> #REF! | N18: =G18*AE18 -> 0.0011350738 | O18: =SUM(N18,O17) -> 0.027241771 | P18: =M18/$M$93 -> #REF! | Q18: =R18/F18 -> 1 | R18: 1 | S18: L | T18: =IF(S18="L",0.68,IF(S18="JP",0.57,IF(S18="JI",0.57,IF(S18="JD",0.57,IF(S18="P",0.24,IF(S18="I",0.12,IF(S18="D",0.13))))))) -> 0.68 | U18: =T18*R18 -> 0.68 | V18: =W18/F18 -> #REF! | W18: ='CD R Documentación'!O19+'CD R Documentación'!T19+'CD R Documentación'!Y19+'CD R Documentación'!AD19+'CD R Documentación'!AI19+'CD R Documentación'!AN19+#REF! -> #REF! | X18: ='CD R Documentación'!R19+'CD R Documentación'!W19+'CD R Documentación'!AB19+'CD R Documentación'!AG19+'CD R Documentación'!AL19+'CD R Documentación'!AQ19+#REF! -> #REF! | Y18: =Z18/F18 -> 2 | Z18: ='CD R Investigación'!P19+'CD R Investigación'!U19+'CD R Investigación'!Z19+'CD R Investigación'!AE19+'CD R Investigación'!AJ19+'CD R Investigación'!AO19+'CD R Investigación'!AT19+'CD R Investigación'!AY19 -> 2 | AA18: ='CD R Investigación'!S19+'CD R Investigación'!X19+'CD R Investigación'!AC19+'CD R Investigación'!AH19+'CD R Investigación'!AM19+'CD R Investigación'!AR19+'CD R Investigación'!AW19+'CD R Investigación'!BB19 -> 0.88 | AB18: =AC18/F18 -> #REF! | AC18: ='CD R Desarrollo'!P19+'CD R Desarrollo'!U19+'CD R Desarrollo'!Z19+'CD R Desarrollo'!AE19+'CD R Desarrollo'!AJ19+'CD R Desarrollo'!AO19+#REF!+#REF! -> #REF! | AD18: ='CD R Desarrollo'!S19+'CD R Desarrollo'!X19+'CD R Desarrollo'!AC19+'CD R Desarrollo'!AH19+'CD R Desarrollo'!AM19+'CD R Desarrollo'!AR19+#REF!+#REF! -> #REF! | AE18: 1 | AF18: ='PL Cronograma detallado'!L66*AE18 -> 21.7 | AG18: =AF18/'PL Cronograma detallado'!M$257 -> #DIV/0! | AH18: =AG18+AH17 -> #DIV/0!
A19: 1.4 | B19: Entrega de Informe de Propuesta v1 | C19: 44662 | D19: 44662 | E19: =_xludf.DAYs(D19,C19)+1 -> #NAME? | F19: 1 | G19: =F19/F$105 -> 0.0011350738 | H19: =SUM(H18,G19) -> 0.029511918 | I19: =SUM(R19,W19,Z19,AC19) -> #REF! | J19: =SUM(I19,J18) -> #REF! | K19: =J19/$J$104 -> #REF! | L19: =SUM(U19,X19,AA19,AD19) -> #REF! | M19: =SUM(L19,M18) -> #REF! | N19: =G19*AE19 -> 0.0011350738 | O19: =SUM(N19,O18) -> 0.028376844 | P19: =M19/$M$93 -> #REF! | Q19: =R19/F19 -> 1 | R19: 1 | S19: L | T19: =IF(S19="L",0.68,IF(S19="JP",0.57,IF(S19="JI",0.57,IF(S19="JD",0.57,IF(S19="P",0.24,IF(S19="I",0.12,IF(S19="D",0.13))))))) -> 0.68 | U19: =T19*R19 -> 0.68 | V19: =W19/F19 -> #REF! | W19: ='CD R Documentación'!O20+'CD R Documentación'!T20+'CD R Documentación'!Y20+'CD R Documentación'!AD20+'CD R Documentación'!AI20+'CD R Documentación'!AN20+#REF! -> #REF! | X19: ='CD R Documentación'!R20+'CD R Documentación'!W20+'CD R Documentación'!AB20+'CD R Documentación'!AG20+'CD R Documentación'!AL20+'CD R Documentación'!AQ20+#REF! -> #REF! | Y19: =Z19/F19 -> 4 | Z19: ='CD R Investigación'!P20+'CD R Investigación'!U20+'CD R Investigación'!Z20+'CD R Investigación'!AE20+'CD R Investigación'!AJ20+'CD R Investigación'!AO20+'CD R Investigación'!AT20+'CD R Investigación'!AY20 -> 4 | AA19: ='CD R Investigación'!S20+'CD R Investigación'!X20+'CD R Investigación'!AC20+'CD R Investigación'!AH20+'CD R Investigación'!AM20+'CD R Investigación'!AR20+'CD R Investigación'!AW20+'CD R Investigación'!BB20 -> 1.76 | AB19: =AC19/F19 -> #REF! | AC19: ='CD R Desarrollo'!P20+'CD R Desarrollo'!U20+'CD R Desarrollo'!Z20+'CD R Desarrollo'!AE20+'CD R Desarrollo'!AJ20+'CD R Desarrollo'!AO20+#REF!+#REF! -> #REF! | AD19: ='CD R Desarrollo'!S20+'CD R Desarrollo'!X20+'CD R Desarrollo'!AC20+'CD R Desarrollo'!AH20+'CD R Desarrollo'!AM20+'CD R Desarrollo'!AR20+#REF!+#REF! -> #REF! | AE19: 1 | AF19: ='PL Cronograma detallado'!L67*AE19 -> 3.57 | AG19: =AF19/'PL Cronograma detallado'!M$257 -> #DIV/0! | AH19: =AG19+AH18 -> #DIV/0!
A20: 2 | B20: Fase de Investigación | C20: 44656 | D20: 44695 | E20: =_xludf.DAYs(D20,C20)+1 -> #NAME? | F20: =SUM(F21,F26,F37) -> 253 | G20: =SUM(G21,G26,G37) -> 0.28717367 | I20: =SUM(I21,I26,I37) -> #REF! | J20: =SUM(I20,J4) -> #REF! | K20: =J20/$J$104 -> #REF! | L20: =SUM(L21,L26,L37) -> #REF! | M20: =SUM(L20,M4) -> #REF! | P20: =M20/$M$93 -> #REF! | Q20: =R20/F20 -> 0 | U20: =T20*R20 -> 0 | X20: ='CD R Documentación'!R21+'CD R Documentación'!W21+'CD R Documentación'!AB21+'CD R Documentación'!AG21+'CD R Documentación'!AL21+'CD R Documentación'!AQ21+#REF! -> #REF! | Z20: ='CD R Investigación'!P21+'CD R Investigación'!U21+'CD R Investigación'!Z21+'CD R Investigación'!AE21+'CD R Investigación'!AJ21+'CD R Investigación'!AO21+'CD R Investigación'!AT21+'CD R Investigación'!AY21 -> 0 | AA20: ='CD R Investigación'!S21+'CD R Investigación'!X21+'CD R Investigación'!AC21+'CD R Investigación'!AH21+'CD R Investigación'!AM21+'CD R Investigación'!AR21+'CD R Investigación'!AW21+'CD R Investigación'!BB21 -> 0 | AC20: ='CD R Desarrollo'!P21+'CD R Desarrollo'!U21+'CD R Desarrollo'!Z21+'CD R Desarrollo'!AE21+'CD R Desarrollo'!AJ21+'CD R Desarrollo'!AO21+#REF!+#REF! -> #REF! | AD20: ='CD R Desarrollo'!S21+'CD R Desarrollo'!X21+'CD R Desarrollo'!AC21+'CD R Desarrollo'!AH21+'CD R Desarrollo'!AM21+'CD R Desarrollo'!AR21+#REF!+#REF! -> #REF!
A21: 2.1 | B21: Relevación de Información de Proyecto GPI 2021-II | C21: 44656 | D21: 44667 | E21: =_xludf.DAYs(D21,C21)+1 -> #NAME? | F21: =SUM(F22:F25) -> 11 | G21: =SUM(G22:G25) -> 0.012485812 | H21: =SUM(G21,H19) -> 0.04199773 | I21: =SUM(I22:I25) -> #REF! | J21: =SUM(I21,J7) -> #REF! | K21: =J21/$J$104 -> #REF! | L21: =SUM(L22:L25) -> #REF! | M21: =SUM(L21,M7) -> #REF! | P21: =M21/$M$93 -> #REF! | X21: ='CD R Documentación'!R22+'CD R Documentación'!W22+'CD R Documentación'!AB22+'CD R Documentación'!AG22+'CD R Documentación'!AL22+'CD R Documentación'!AQ22+#REF! -> #REF! | Z21: ='CD R Investigación'!P22+'CD R Investigación'!U22+'CD R Investigación'!Z22+'CD R Investigación'!AE22+'CD R Investigación'!AJ22+'CD R Investigación'!AO22+'CD R Investigación'!AT22+'CD R Investigación'!AY22 -> 0 | AA21: ='CD R Investigación'!S22+'CD R Investigación'!X22+'CD R Investigación'!AC22+'CD R Investigación'!AH22+'CD R Investigación'!AM22+'CD R Investigación'!AR22+'CD R Investigación'!AW22+'CD R Investigación'!BB22 -> 0 | AC21: ='CD R Desarrollo'!P22+'CD R Desarrollo'!U22+'CD R Desarrollo'!Z22+'CD R Desarrollo'!AE22+'CD R Desarrollo'!AJ22+'CD R Desarrollo'!AO22+#REF!+#REF! -> #REF! | AD21: ='CD R Desarrollo'!S22+'CD R Desarrollo'!X22+'CD R Desarrollo'!AC22+'CD R Desarrollo'!AH22+'CD R Desarrollo'!AM22+'CD R Desarrollo'!AR22+#REF!+#REF! -> #REF!
A22: 2.1.1 | B22: Recolección Documentación Proyecto GPI 2021-II | C22: 44657 | D22: 44657 | E22: =_xludf.DAYs(D22,C22)+1 -> #NAME? | F22: 1 | G22: =F22/F$105 -> 0.0011350738 | H22: =SUM(H19,G22) -> 0.030646992 | I22: =SUM(R22,W22,Z22,AC22) -> #REF! | J22: =SUM(I22,J19) -> #REF! | K22: =J22/$J$104 -> #REF! | L22: =SUM(U22,X22,AA22,AD22) -> #REF! | M22: =SUM(L22,M19) -> #REF! | N22: =G22*AE22 -> 0.0011350738 | O22: =SUM(N22,O19) -> 0.029511918 | P22: =M22/$M$93 -> #REF! | Q22: =R22/F22 -> 0.5 | R22: 0.5 | S22: L | T22: =IF(S22="L",0.68,IF(S22="JP",0.57,IF(S22="JI",0.57,IF(S22="JD",0.57,IF(S22="P",0.24,IF(S22="I",0.12,IF(S22="D",0.13))))))) -> 0.68 | U22: =T22*R22 -> 0.34 | V22: =W22/F22 -> #REF! | W22: ='CD R Documentación'!O23+'CD R Documentación'!T23+'CD R Documentación'!Y23+'CD R Documentación'!AD23+'CD R Documentación'!AI23+'CD R Documentación'!AN23+#REF! -> #REF! | X22: ='CD R Documentación'!R23+'CD R Documentación'!W23+'CD R Documentación'!AB23+'CD R Documentación'!AG23+'CD R Documentación'!AL23+'CD R Documentación'!AQ23+#REF! -> #REF! | Y22: =Z22/F22 -> 0 | Z22: ='CD R Investigación'!P23+'CD R Investigación'!U23+'CD R Investigación'!Z23+'CD R Investigación'!AE23+'CD R Investigación'!AJ23+'CD R Investigación'!AO23+'CD R Investigación'!AT23+'CD R Investigación'!AY23 -> 0 | AA22: ='CD R Investigación'!S23+'CD R Investigación'!X23+'CD R Investigación'!AC23+'CD R Investigación'!AH23+'CD R Investigación'!AM23+'CD R Investigación'!AR23+'CD R Investigación'!AW23+'CD R Investigación'!BB23 -> 0 | AB22: =AC22/F22 -> #REF! | AC22: ='CD R Desarrollo'!P23+'CD R Desarrollo'!U23+'CD R Desarrollo'!Z23+'CD R Desarrollo'!AE23+'CD R Desarrollo'!AJ23+'CD R Desarrollo'!AO23+#REF!+#REF! -> #REF! | AD22: ='CD R Desarrollo'!S23+'CD R Desarrollo'!X23+'CD R Desarrollo'!AC23+'CD R Desarrollo'!AH23+'CD R Desarrollo'!AM23+'CD R Desarrollo'!AR23+#REF!+#REF! -> #REF! | AE22: 1 | AF22: ='PL Cronograma detallado'!L70*AE22 -> 8.85 | AG22: =AF22/'PL Cronograma detallado'!M$257 -> #DIV/0! | AH22: =AG22+AH19 -> #DIV/0!
A23: 2.1.2 | B23: Obtención Repositorio Proyecto GPI 2021-II | C23: 44657 | D23: 44657 | E23: =_xludf.DAYs(D23,C23)+1 -> #NAME? | F23: 1 | G23: =F23/F$105 -> 0.0011350738 | H23: =SUM(H22,G23) -> 0.031782066 | I23: =SUM(R23,W23,Z23,AC23) -> #REF! | J23: =SUM(I23,J22) -> #REF! | K23: =J23/$J$104 -> #REF! | L23: =SUM(U23,X23,AA23,AD23) -> #REF! | M23: =SUM(L23,M22) -> #REF! | N23: =G23*AE23 -> 0.0011350738 | O23: =SUM(N23,O22) -> 0.030646992 | P23: =M23/$M$93 -> #REF! | Q23: =R23/F23 -> 1 | R23: 1 | S23: L | T23: =IF(S23="L",0.68,IF(S23="JP",0.57,IF(S23="JI",0.57,IF(S23="JD",0.57,IF(S23="P",0.24,IF(S23="I",0.12,IF(S23="D",0.13))))))) -> 0.68 | U23: =T23*R23 -> 0.68 | V23: =W23/F23 -> #REF! | W23: ='CD R Documentación'!O24+'CD R Documentación'!T24+'CD R Documentación'!Y24+'CD R Documentación'!AD24+'CD R Documentación'!AI24+'CD R Documentación'!AN24+#REF! -> #REF! | X23: ='CD R Documentación'!R24+'CD R Documentación'!W24+'CD R Documentación'!AB24+'CD R Documentación'!AG24+'CD R Documentación'!AL24+'CD R Documentación'!AQ24+#REF! -> #REF! | Y23: =Z23/F23 -> 0 | Z23: ='CD R Investigación'!P24+'CD R Investigación'!U24+'CD R Investigación'!Z24+'CD R Investigación'!AE24+'CD R Investigación'!AJ24+'CD R Investigación'!AO24+'CD R Investigación'!AT24+'CD R Investigación'!AY24 -> 0 | AA23: ='CD R Investigación'!S24+'CD R Investigación'!X24+'CD R Investigación'!AC24+'CD R Investigación'!AH24+'CD R Investigación'!AM24+'CD R Investigación'!AR24+'CD R Investigación'!AW24+'CD R Investigación'!BB24 -> 0 | AB23: =AC23/F23 -> #REF! | AC23: ='CD R Desarrollo'!P24+'CD R Desarrollo'!U24+'CD R Desarrollo'!Z24+'CD R Desarrollo'!AE24+'CD R Desarrollo'!AJ24+'CD R Desarrollo'!AO24+#REF!+#REF! -> #REF! | AD23: ='CD R Desarrollo'!S24+'CD R Desarrollo'!X24+'CD R Desarrollo'!AC24+'CD R Desarrollo'!AH24+'CD R Desarrollo'!AM24+'CD R Desarrollo'!AR24+#REF!+#REF! -> #REF! | AE23: 1 | AF23: ='PL Cronograma detallado'!L71*AE23 -> 3.43 | AG23: =AF23/'PL Cronograma detallado'!M$257 -> #DIV/0! | AH23: =AG23+AH22 -> #DIV/0!
A24: 2.1.3 | B24: Análisis de Documentación de Proyecto GPI 2021-II | C24: 44658 | D24: 44667 | E24: =_xludf.DAYs(D24,C24)+1 -> #NAME? | F24: 8 | G24: =F24/F$105 -> 0.0090805902 | H24: =SUM(H23,G24) -> 0.040862656 | I24: =SUM(R24,W24,Z24,AC24) -> #REF! | J24: =SUM(I24,J23) -> #REF! | K24: =J24/$J$104 -> #REF! | L24: =SUM(U24,X24,AA24,AD24) -> #REF! | M24: =SUM(L24,M23) -> #REF! | N24: =G24*AE24 -> 0.0090805902 | O24: =SUM(N24,O23) -> 0.039727582 | P24: =M24/$M$93 -> #REF! | Q24: =R24/F24 -> 0.0625 | R24: 0.5 | S24: L | T24: =IF(S24="L",0.68,IF(S24="JP",0.57,IF(S24="JI",0.57,IF(S24="JD",0.57,IF(S24="P",0.24,IF(S24="I",0.12,IF(S24="D",0.13))))))) -> 0.68 | U24: =T24*R24 -> 0.34 | V24: =W24/F24 -> #REF! | W24: ='CD R Documentación'!O25+'CD R Documentación'!T25+'CD R Documentación'!Y25+'CD R Documentación'!AD25+'CD R Documentación'!AI25+'CD R Documentación'!AN25+#REF! -> #REF! | X24: ='CD R Documentación'!R25+'CD R Documentación'!W25+'CD R Documentación'!AB25+'CD R Documentación'!AG25+'CD R Documentación'!AL25+'CD R Documentación'!AQ25+#REF! -> #REF! | Y24: =Z24/F24 -> 1 | Z24: ='CD R Investigación'!P25+'CD R Investigación'!U25+'CD R Investigación'!Z25+'CD R Investigación'!AE25+'CD R Investigación'!AJ25+'CD R Investigación'!AO25+'CD R Investigación'!AT25+'CD R Investigación'!AY25 -> 8 | AA24: ='CD R Investigación'!S25+'CD R Investigación'!X25+'CD R Investigación'!AC25+'CD R Investigación'!AH25+'CD R Investigación'!AM25+'CD R Investigación'!AR25+'CD R Investigación'!AW25+'CD R Investigación'!BB25 -> 3.52 | AB24: =AC24/F24 -> #REF! | AC24: ='CD R Desarrollo'!P25+'CD R Desarrollo'!U25+'CD R Desarrollo'!Z25+'CD R Desarrollo'!AE25+'CD R Desarrollo'!AJ25+'CD R Desarrollo'!AO25+#REF!+#REF! -> #REF! | AD24: ='CD R Desarrollo'!S25+'CD R Desarrollo'!X25+'CD R Desarrollo'!AC25+'CD R Desarrollo'!AH25+'CD R Desarrollo'!AM25+'CD R Desarrollo'!AR25+#REF!+#REF! -> #REF! | AE24: 1 | AF24: ='PL Cronograma detallado'!L72*AE24 -> 3.13 | AG24: =AF24/'PL Cronograma detallado'!M$257 -> #DIV/0! | AH24: =AG24+AH23 -> #DIV/0!
A25: 2.1.4 | B25: Reunión de Líderes 2 | C25: 44666 | D25: 44666 | E25: =_xludf.DAYs(D25,C25)+1 -> #NAME? | F25: 1 | G25: =F25/F$105 -> 0.0011350738 | H25: =SUM(H24,G25) -> 0.04199773 | I25: =SUM(R25,W25,Z25,AC25) -> #REF! | J25: =SUM(I25,J24) -> #REF! | K25: =J25/$J$104 -> #REF! | L25: =SUM(U25,X25,AA25,AD25) -> #REF! | M25: =SUM(L25,M24) -> #REF! | N25: =G25*AE25 -> 0.0011350738 | O25: =SUM(N25,O24) -> 0.040862656 | P25: =M25/$M$93 -> #REF! | Q25: =R25/F25 -> 1 | R25: 1 | S25: L | T25: =IF(S25="L",0.68,IF(S25="JP",0.57,IF(S25="JI",0.57,IF(S25="JD",0.57,IF(S25="P",0.24,IF(S25="I",0.12,IF(S25="D",0.13))))))) -> 0.68 | U25: =T25*R25 -> 0.68 | V25: =W25/F25 -> #REF! | W25: ='CD R Documentación'!O26+'CD R Documentación'!T26+'CD R Documentación'!Y26+'CD R Documentación'!AD26+'CD R Documentación'!AI26+'CD R Documentación'!AN26+#REF! -> #REF! | X25: ='CD R Documentación'!R26+'CD R Documentación'!W26+'CD R Documentación'!AB26+'CD R Documentación'!AG26+'CD R Documentación'!AL26+'CD R Documentación'!AQ26+#REF! -> #REF! | Y25: =Z25/F25 -> 0 | Z25: ='CD R Investigación'!P26+'CD R Investigación'!U26+'CD R Investigación'!Z26+'CD R Investigación'!AE26+'CD R Investigación'!AJ26+'CD R Investigación'!AO26+'CD R Investigación'!AT26+'CD R Investigación'!AY26 -> 0 | AA25: ='CD R Investigación'!S26+'CD R Investigación'!X26+'CD R Investigación'!AC26+'CD R Investigación'!AH26+'CD R Investigación'!AM26+'CD R Investigación'!AR26+'CD R Investigación'!AW26+'CD R Investigación'!BB26 -> 0 | AB25: =AC25/F25 -> #REF! | AC25: ='CD R Desarrollo'!P26+'CD R Desarrollo'!U26+'CD R Desarrollo'!Z26+'CD R Desarrollo'!AE26+'CD R Desarrollo'!AJ26+'CD R Desarrollo'!AO26+#REF!+#REF! -> #REF! | AD25: ='CD R Desarrollo'!S26+'CD R Desarrollo'!X26+'CD R Desarrollo'!AC26+'CD R Desarrollo'!AH26+'CD R Desarrollo'!AM26+'CD R Desarrollo'!AR26+#REF!+#REF! -> #REF! | AE25: 1 | AF25: ='PL Cronograma detallado'!L73*AE25 -> 2.29 | AG25: =AF25/'PL Cronograma detallado'!M$257 -> #DIV/0! | AH25: =AG25+AH24 -> #DIV/0!
A26: 2.2 | B26: Investigación Bibliométrica y Altmetric | C26: 44669 | D26: 44688 | E26: =_xludf.DAYs(D26,C26)+1 -> #NAME? | F26: =SUM(F27:F36) -> 62 | G26: =SUM(G27:G36) -> 0.070374574 | H26: =SUM(H25,G26) -> 0.1123723 | I26: =SUM(I27:I36) -> #REF! | J26: =SUM(I26,J21) -> #REF! | K26: =J26/$J$104 -> #REF! | L26: =SUM(L27:L36) -> #REF! | M26: =SUM(L26,M21) -> #REF! | P26: =M26/$M$93 -> #REF! | W26: ='CD R Documentación'!O27+'CD R Documentación'!T27+'CD R Documentación'!Y27+'CD R Documentación'!AD27+'CD R Documentación'!AI27+'CD R Documentación'!AN27+#REF! -> #REF! | X26: ='CD R Documentación'!R27+'CD R Documentación'!W27+'CD R Documentación'!AB27+'CD R Documentación'!AG27+'CD R Documentación'!AL27+'CD R Documentación'!AQ27+#REF! -> #REF! | Z26: ='CD R Investigación'!P27+'CD R Investigación'!U27+'CD R Investigación'!Z27+'CD R Investigación'!AE27+'CD R Investigación'!AJ27+'CD R Investigación'!AO27+'CD R Investigación'!AT27+'CD R Investigación'!AY27 -> 0 | AA26: ='CD R Investigación'!S27+'CD R Investigación'!X27+'CD R Investigación'!AC27+'CD R Investigación'!AH27+'CD R Investigación'!AM27+'CD R Investigación'!AR27+'CD R Investigación'!AW27+'CD R Investigación'!BB27 -> 0 | AC26: ='CD R Desarrollo'!P27+'CD R Desarrollo'!U27+'CD R Desarrollo'!Z27+'CD R Desarrollo'!AE27+'CD R Desarrollo'!AJ27+'CD R Desarrollo'!AO27+#REF!+#REF! -> #REF! | AD26: ='CD R Desarrollo'!S27+'CD R Desarrollo'!X27+'CD R Desarrollo'!AC27+'CD R Desarrollo'!AH27+'CD R Desarrollo'!AM27+'CD R Desarrollo'!AR27+#REF!+#REF! -> #REF!
A27: H1 | B27: Entrega de Informe de Propuesta vf | C27: 44670 | D27: 44670 | E27: =_xludf.DAYs(D27,C27)+1 -> #NAME? | F27: 1 | G27: =(F27/F$105) -> 0.0011350738 | H27: =SUM(H25,G27) -> 0.043132804 | I27: =SUM(R27,W27,Z27,AC27) -> #REF! | J27: =SUM(I27,J25) -> #REF! | K27: =J27/$J$104 -> #REF! | L27: =SUM(U27,X27,AA27,AD27) -> #REF! | M27: =SUM(L27,M25) -> #REF! | N27: =G27*AE27 -> 0.0011350738 | O27: =SUM(N27,O25) -> 0.04199773 | P27: =M27/$M$93 -> #REF! | Q27: =R27/F27 -> 1 | R27: 1 | S27: L | T27: =IF(S27="L",0.68,IF(S27="JP",0.57,IF(S27="JI",0.57,IF(S27="JD",0.57,IF(S27="P",0.24,IF(S27="I",0.12,IF(S27="D",0.13))))))) -> 0.68 | U27: =T27*R27 -> 0.68 | V27: =W27/F27 -> #REF! | W27: ='CD R Documentación'!O28+'CD R Documentación'!T28+'CD R Documentación'!Y28+'CD R Documentación'!AD28+'CD R Documentación'!AI28+'CD R Documentación'!AN28+#REF! -> #REF! | X27: ='CD R Documentación'!R28+'CD R Documentación'!W28+'CD R Documentación'!AB28+'CD R Documentación'!AG28+'CD R Documentación'!AL28+'CD R Documentación'!AQ28+#REF! -> #REF! | Y27: =Z27/F27 -> 0 | Z27: ='CD R Investigación'!P28+'CD R Investigación'!U28+'CD R Investigación'!Z28+'CD R Investigación'!AE28+'CD R Investigación'!AJ28+'CD R Investigación'!AO28+'CD R Investigación'!AT28+'CD R Investigación'!AY28 -> 0 | AA27: ='CD R Investigación'!S28+'CD R Investigación'!X28+'CD R Investigación'!AC28+'CD R Investigación'!AH28+'CD R Investigación'!AM28+'CD R Investigación'!AR28+'CD R Investigación'!AW28+'CD R Investigación'!BB28 -> 0 | AB27: =AC27/F27 -> #REF! | AC27: ='CD R Desarrollo'!P28+'CD R Desarrollo'!U28+'CD R Desarrollo'!Z28+'CD R Desarrollo'!AE28+'CD R Desarrollo'!AJ28+'CD R Desarrollo'!AO28+#REF!+#REF! -> #REF! | AD27: ='CD R Desarrollo'!S28+'CD R Desarrollo'!X28+'CD R Desarrollo'!AC28+'CD R Desarrollo'!AH28+'CD R Desarrollo'!AM28+'CD R Desarrollo'!AR28+#REF!+#REF! -> #REF! | AE27: 1 | AF27: ='PL Cronograma detallado'!L76*AE27 -> 7.73 | AG27: =AF27/'PL Cronograma detallado'!M$257 -> #DIV/0! | AH27: =AG27+AH25 -> #DIV/0!
A28: 2.2.1 | B28: Definición de Instrumentos de Análisis Bibliométricos | C28: 44670 | D28: 44671 | E28: =_xludf.DAYs(D28,C28)+1 -> #NAME? | F28: 2 | G28: =F28/F$105 -> 0.0022701476 | H28: =SUM(H27,G28) -> 0.045402951 | I28: =SUM(R28,W28,Z28,AC28) -> #REF! | J28: =SUM(I28,J27) -> #REF! | K28: =J28/$J$104 -> #REF! | L28: =SUM(U28,X28,AA28,AD28) -> #REF! | M28: =SUM(L28,M27) -> #REF! | N28: =G28*AE28 -> 0.0022701476 | O28: =SUM(N28,O27) -> 0.044267877 | P28: =M28/$M$93 -> #REF! | Q28: =R28/F28 -> 0 | R28: 0 | S28: L | T28: =IF(S28="L",0.68,IF(S28="JP",0.57,IF(S28="JI",0.57,IF(S28="JD",0.57,IF(S28="P",0.24,IF(S28="I",0.12,IF(S28="D",0.13))))))) -> 0.68 | U28: =T28*R28 -> 0 | V28: =W28/F28 -> #REF! | W28: ='CD R Documentación'!O29+'CD R Documentación'!T29+'CD R Documentación'!Y29+'CD R Documentación'!AD29+'CD R Documentación'!AI29+'CD R Documentación'!AN29+#REF! -> #REF! | X28: ='CD R Documentación'!R29+'CD R Documentación'!W29+'CD R Documentación'!AB29+'CD R Documentación'!AG29+'CD R Documentación'!AL29+'CD R Documentación'!AQ29+#REF! -> #REF! | Y28: =Z28/F28 -> 0 | Z28: ='CD R Investigación'!P29+'CD R Investigación'!U29+'CD R Investigación'!Z29+'CD R Investigación'!AE29+'CD R Investigación'!AJ29+'CD R Investigación'!AO29+'CD R Investigación'!AT29+'CD R Investigación'!AY29 -> 0 | AA28: ='CD R Investigación'!S29+'CD R Investigación'!X29+'CD R Investigación'!AC29+'CD R Investigación'!AH29+'CD R Investigación'!AM29+'CD R Investigación'!AR29+'CD R Investigación'!AW29+'CD R Investigación'!BB29 -> 0 | AB28: =AC28/F28 -> #REF! | AC28: ='CD R Desarrollo'!P29+'CD R Desarrollo'!U29+'CD R Desarrollo'!Z29+'CD R Desarrollo'!AE29+'CD R Desarrollo'!AJ29+'CD R Desarrollo'!AO29+#REF!+#REF! -> #REF! | AD28: ='CD R Desarrollo'!S29+'CD R Desarrollo'!X29+'CD R Desarrollo'!AC29+'CD R Desarrollo'!AH29+'CD R Desarrollo'!AM29+'CD R Desarrollo'!AR29+#REF!+#REF! -> #REF! | AE28: 1 | AF28: ='PL Cronograma detallado'!L78*AE28 -> 6.84 | AG28: =AF28/'PL Cronograma detallado'!M$257 -> #DIV/0! | AH28: =AG28+AH27 -> #DIV/0!
A29: 2.2.2 | B29: Definción de Instrumentos de Análisis Altmetric | C29: 44670 | D29: 44671 | E29: =_xludf.DAYs(D29,C29)+1 -> #NAME? | F29: 2 | G29: =F29/F$105 -> 0.0022701476 | H29: =SUM(H28,G29) -> 0.047673099 | I29: =SUM(R29,W29,Z29,AC29) -> #REF! | J29: =SUM(I29,J28) -> #REF! | K29: =J29/$J$104 -> #REF! | L29: =SUM(U29,X29,AA29,AD29) -> #REF! | M29: =SUM(L29,M28) -> #REF! | N29: =G29*AE29 -> 0.0022701476 | O29: =SUM(N29,O28) -> 0.046538025 | P29: =M29/$M$93 -> #REF! | Q29: =R29/F29 -> 0 | R29: 0 | S29: L | T29: =IF(S29="L",0.68,IF(S29="JP",0.57,IF(S29="JI",0.57,IF(S29="JD",0.57,IF(S29="P",0.24,IF(S29="I",0.12,IF(S29="D",0.13))))))) -> 0.68 | U29: =T29*R29 -> 0 | V29: =W29/F29 -> #REF! | W29: ='CD R Documentación'!O30+'CD R Documentación'!T30+'CD R Documentación'!Y30+'CD R Documentación'!AD30+'CD R Documentación'!AI30+'CD R Documentación'!AN30+#REF! -> #REF! | X29: ='CD R Documentación'!R30+'CD R Documentación'!W30+'CD R Documentación'!AB30+'CD R Documentación'!AG30+'CD R Documentación'!AL30+'CD R Documentación'!AQ30+#REF! -> #REF! | Y29: =Z29/F29 -> 0 | Z29: ='CD R Investigación'!P30+'CD R Investigación'!U30+'CD R Investigación'!Z30+'CD R Investigación'!AE30+'CD R Investigación'!AJ30+'CD R Investigación'!AO30+'CD R Investigación'!AT30+'CD R Investigación'!AY30 -> 0 | AA29: ='CD R Investigación'!S30+'CD R Investigación'!X30+'CD R Investigación'!AC30+'CD R Investigación'!AH30+'CD R Investigación'!AM30+'CD R Investigación'!AR30+'CD R Investigación'!AW30+'CD R Investigación'!BB30 -> 0 | AB29: =AC29/F29 -> #REF! | AC29: ='CD R Desarrollo'!P30+'CD R Desarrollo'!U30+'CD R Desarrollo'!Z30+'CD R Desarrollo'!AE30+'CD R Desarrollo'!AJ30+'CD R Desarrollo'!AO30+#REF!+#REF! -> #REF! | AD29: ='CD R Desarrollo'!S30+'CD R Desarrollo'!X30+'CD R Desarrollo'!AC30+'CD R Desarrollo'!AH30+'CD R Desarrollo'!AM30+'CD R Desarrollo'!AR30+#REF!+#REF! -> #REF! | AE29: 1 | AF29: ='PL Cronograma detallado'!L79*AE29 -> 0 | AG29: =AF29/'PL Cronograma detallado'!M$257 -> #DIV/0! | AH29: =AG29+AH28 -> #DIV/0!
A30: 2.2.3 | B30: Analizar Estado del Arte de la Fase Anterior del Proyecto (Parte 1) | C30: 44671 | D30: 44677 | E30: =_xludf.DAYs(D30,C30)+1 -> #NAME? | F30: 14 | G30: =F30/F$105 -> 0.015891033 | H30: =SUM(H29,G30) -> 0.063564132 | I30: =SUM(R30,W30,Z30,AC30) -> #REF! | J30: =SUM(I30,J29) -> #REF! | K30: =J30/$J$104 -> #REF! | L30: =SUM(U30,X30,AA30,AD30) -> #REF! | M30: =SUM(L30,M29) -> #REF! | N30: =G30*AE30 -> 0.015891033 | O30: =SUM(N30,O29) -> 0.062429058 | P30: =M30/$M$93 -> #REF! | Q30: =R30/F30 -> 0 | R30: 0 | S30: L | T30: =IF(S30="L",0.68,IF(S30="JP",0.57,IF(S30="JI",0.57,IF(S30="JD",0.57,IF(S30="P",0.24,IF(S30="I",0.12,IF(S30="D",0.13))))))) -> 0.68 | U30: =T30*R30 -> 0 | V30: =W30/F30 -> #REF! | W30: ='CD R Documentación'!O31+'CD R Documentación'!T31+'CD R Documentación'!Y31+'CD R Documentación'!AD31+'CD R Documentación'!AI31+'CD R Documentación'!AN31+#REF! -> #REF! | X30: ='CD R Documentación'!R31+'CD R Documentación'!W31+'CD R Documentación'!AB31+'CD R Documentación'!AG31+'CD R Documentación'!AL31+'CD R Documentación'!AQ31+#REF! -> #REF! | Y30: =Z30/F30 -> 0 | Z30: ='CD R Investigación'!P31+'CD R Investigación'!U31+'CD R Investigación'!Z31+'CD R Investigación'!AE31+'CD R Investigación'!AJ31+'CD R Investigación'!AO31+'CD R Investigación'!AT31+'CD R Investigación'!AY31 -> 0 | AA30: ='CD R Investigación'!S31+'CD R Investigación'!X31+'CD R Investigación'!AC31+'CD R Investigación'!AH31+'CD R Investigación'!AM31+'CD R Investigación'!AR31+'CD R Investigación'!AW31+'CD R Investigación'!BB31 -> 0 | AB30: =AC30/F30 -> #REF! | AC30: ='CD R Desarrollo'!P31+'CD R Desarrollo'!U31+'CD R Desarrollo'!Z31+'CD R Desarrollo'!AE31+'CD R Desarrollo'!AJ31+'CD R Desarrollo'!AO31+#REF!+#REF! -> #REF! | AD30: ='CD R Desarrollo'!S31+'CD R Desarrollo'!X31+'CD R Desarrollo'!AC31+'CD R Desarrollo'!AH31+'CD R Desarrollo'!AM31+'CD R Desarrollo'!AR31+#REF!+#REF! -> #REF! | AE30: 1 | AF30: ='PL Cronograma detallado'!L80*AE30 -> 162.08 | AG30: =AF30/'PL Cronograma detallado'!M$257 -> #DIV/0! | AH30: =AG30+AH29 -> #DIV/0!
A31: 2.2.4 | B31: Reunión de Líderes 3 | C31: 44673 | D31: 44673 | E31: =_xludf.DAYs(D31,C31)+1 -> #NAME? | F31: 1 | G31: =F31/F$105 -> 0.0011350738 | H31: =SUM(H30,G31) -> 0.064699205 | I31: =SUM(R31,W31,Z31,AC31) -> #REF! | J31: =SUM(I31,J30) -> #REF! | K31: =J31/$J$104 -> #REF! | L31: =SUM(U31,X31,AA31,AD31) -> #REF! | M31: =SUM(L31,M30) -> #REF! | N31: =G31*AE31 -> 0.0011350738 | O31: =SUM(N31,O30) -> 0.063564132 | P31: =M31/$M$93 -> #REF! | Q31: =R31/F31 -> 1 | R31: 1 | S31: L | T31: =IF(S31="L",0.68,IF(S31="JP",0.57,IF(S31="JI",0.57,IF(S31="JD",0.57,IF(S31="P",0.24,IF(S31="I",0.12,IF(S31="D",0.13))))))) -> 0.68 | U31: =T31*R31 -> 0.68 | V31: =W31/F31 -> 1 | W31: 1 | X31: ='CD R Documentación'!R32+'CD R Documentación'!W32+'CD R Documentación'!AB32+'CD R Documentación'!AG32+'CD R Documentación'!AL32+'CD R Documentación'!AQ32+#REF! -> #REF! | Y31: =Z31/F31 -> 1 | Z31: 1 | AA31: ='CD R Investigación'!S32+'CD R Investigación'!X32+'CD R Investigación'!AC32+'CD R Investigación'!AH32+'CD R Investigación'!AM32+'CD R Investigación'!AR32+'CD R Investigación'!AW32+'CD R Investigación'!BB32 -> 2.64 | AB31: =AC31/F31 -> #REF! | AC31: ='CD R Desarrollo'!P32+'CD R Desarrollo'!U32+'CD R Desarrollo'!Z32+'CD R Desarrollo'!AE32+'CD R Desarrollo'!AJ32+'CD R Desarrollo'!AO32+#REF!+#REF! -> #REF! | AD31: ='CD R Desarrollo'!S32+'CD R Desarrollo'!X32+'CD R Desarrollo'!AC32+'CD R Desarrollo'!AH32+'CD R Desarrollo'!AM32+'CD R Desarrollo'!AR32+#REF!+#REF! -> #REF! | AE31: 1 | AF31: ='PL Cronograma detallado'!L127*AE31 -> 10.6 | AG31: =AF31/'PL Cronograma detallado'!M$257 -> #DIV/0! | AH31: =AG31+AH30 -> #DIV/0!
A32: 2.2.5 | B32: Definir Estrategias de Búsqueda | C32: 44674 | D32: 44674 | E32: =_xludf.DAYs(D32,C32)+1 -> #NAME? | F32: 2 | G32: =F32/F$105 -> 0.0022701476 | H32: =SUM(H31,G32) -> 0.066969353 | I32: =SUM(R32,W32,Z32,AC32) -> #REF! | J32: =SUM(I32,J31) -> #REF! | K32: =J32/$J$104 -> #REF! | L32: =SUM(U32,X32,AA32,AD32) -> #REF! | M32: =SUM(L32,M31) -> #REF! | N32: =G32*AE32 -> 0.0022701476 | O32: =SUM(N32,O31) -> 0.065834279 | P32: =M32/$M$93 -> #REF! | Q32: =R32/F32 -> 0 | R32: 0 | S32: L | T32: =IF(S32="L",0.68,IF(S32="JP",0.57,IF(S32="JI",0.57,IF(S32="JD",0.57,IF(S32="P",0.24,IF(S32="I",0.12,IF(S32="D",0.13))))))) -> 0.68 | U32: =T32*R32 -> 0 | V32: =W32/F32 -> #REF! | W32: ='CD R Documentación'!O33+'CD R Documentación'!T33+'CD R Documentación'!Y33+'CD R Documentación'!AD33+'CD R Documentación'!AI33+'CD R Documentación'!AN33+#REF! -> #REF! | X32: ='CD R Documentación'!R33+'CD R Documentación'!W33+'CD R Documentación'!AB33+'CD R Documentación'!AG33+'CD R Documentación'!AL33+'CD R Documentación'!AQ33+#REF! -> #REF! | Y32: =Z32/F32 -> 3 | Z32: ='CD R Investigación'!P33+'CD R Investigación'!U33+'CD R Investigación'!Z33+'CD R Investigación'!AE33+'CD R Investigación'!AJ33+'CD R Investigación'!AO33+'CD R Investigación'!AT33+'CD R Investigación'!AY33 -> 6 | AA32: ='CD R Investigación'!S33+'CD R Investigación'!X33+'CD R Investigación'!AC33+'CD R Investigación'!AH33+'CD R Investigación'!AM33+'CD R Investigación'!AR33+'CD R Investigación'!AW33+'CD R Investigación'!BB33 -> 2.64 | AB32: =AC32/F32 -> #REF! | AC32: ='CD R Desarrollo'!P33+'CD R Desarrollo'!U33+'CD R Desarrollo'!Z33+'CD R Desarrollo'!AE33+'CD R Desarrollo'!AJ33+'CD R Desarrollo'!AO33+#REF!+#REF! -> #REF! | AD32: ='CD R Desarrollo'!S33+'CD R Desarrollo'!X33+'CD R Desarrollo'!AC33+'CD R Desarrollo'!AH33+'CD R Desarrollo'!AM33+'CD R Desarrollo'!AR33+#REF!+#REF! -> #REF! | AE32: 1 | AF32: ='PL Cronograma detallado'!L128*AE32 -> 4.54 | AG32: =AF32/'PL Cronograma detallado'!M$257 -> #DIV/0! | AH32: =AG32+AH31 -> #DIV/0!
A33: 2.2.6 | B33: Realizar análisis bibliométrico en Springer Link y Virtual Pro | C33: 44676 | D33: 44688 | E33: =_xludf.DAYs(D33,C33)+1 -> #NAME? | F33: 10 | G33: =F33/F$105 -> 0.011350738 | H33: =SUM(H32,G33) -> 0.078320091 | I33: =SUM(R33,W33,Z33,AC33) -> #REF! | J33: =SUM(I33,J32) -> #REF! | K33: =J33/$J$104 -> #REF! | L33: =SUM(U33,X33,AA33,AD33) -> #REF! | M33: =SUM(L33,M32) -> #REF! | N33: =G33*AE33 -> 0.011350738 | O33: =SUM(N33,O32) -> 0.077185017 | P33: =M33/$M$93 -> #REF! | Q33: =R33/F33 -> 0 | R33: 0 | S33: L | T33: =IF(S33="L",0.68,IF(S33="JP",0.57,IF(S33="JI",0.57,IF(S33="JD",0.57,IF(S33="P",0.24,IF(S33="I",0.12,IF(S33="D",0.13))))))) -> 0.68 | U33: =T33*R33 -> 0 | V33: =W33/F33 -> #REF! | W33: ='CD R Documentación'!O34+'CD R Documentación'!T34+'CD R Documentación'!Y34+'CD R Documentación'!AD34+'CD R Documentación'!AI34+'CD R Documentación'!AN34+#REF! -> #REF! | X33: ='CD R Documentación'!R34+'CD R Documentación'!W34+'CD R Documentación'!AB34+'CD R Documentación'!AG34+'CD R Documentación'!AL34+'CD R Documentación'!AQ34+#REF! -> #REF! | Y33: =Z33/F33 -> 0.6 | Z33: ='CD R Investigación'!P34+'CD R Investigación'!U34+'CD R Investigación'!Z34+'CD R Investigación'!AE34+'CD R Investigación'!AJ34+'CD R Investigación'!AO34+'CD R Investigación'!AT34+'CD R Investigación'!AY34 -> 6 | AA33: ='CD R Investigación'!S34+'CD R Investigación'!X34+'CD R Investigación'!AC34+'CD R Investigación'!AH34+'CD R Investigación'!AM34+'CD R Investigación'!AR34+'CD R Investigación'!AW34+'CD R Investigación'!BB34 -> 2.64 | AB33: =AC33/F33 -> #REF! | AC33: ='CD R Desarrollo'!P34+'CD R Desarrollo'!U34+'CD R Desarrollo'!Z34+'CD R Desarrollo'!AE34+'CD R Desarrollo'!AJ34+'CD R Desarrollo'!AO34+#REF!+#REF! -> #REF! | AD33: ='CD R Desarrollo'!S34+'CD R Desarrollo'!X34+'CD R Desarrollo'!AC34+'CD R Desarrollo'!AH34+'CD R Desarrollo'!AM34+'CD R Desarrollo'!AR34+#REF!+#REF! -> #REF! | AE33: 1 | AF33: ='PL Cronograma detallado'!L129*AE33 -> 4.54 | AG33: =AF33/'PL Cronograma detallado'!M$257 -> #DIV/0! | AH33: =AG33+AH32 -> #DIV/0!
A34: 2.2.7 | B34: Realizar análisis bibliométrico en Proquest Engineering, Proquest D&T y Science Direct | C34: 44676 | D34: 44695 | E34: =_xludf.DAYs(D34,C34)+1 -> #NAME? | F34: 10 | G34: =F34/F$105 -> 0.011350738 | H34: =SUM(H33,G34) -> 0.089670829 | I34: =SUM(R34,W34,Z34,AC34) -> #REF! | J34: =SUM(I34,J33) -> #REF! | K34: =J34/$J$104 -> #REF! | L34: =SUM(U34,X34,AA34,AD34) -> #REF! | M34: =SUM(L34,M33) -> #REF! | N34: =G34*AE34 -> 0.011350738 | O34: =SUM(N34,O33) -> 0.088535755 | P34: =M34/$M$93 -> #REF! | Q34: =R34/F34 -> 0 | R34: 0 | S34: L | T34: =IF(S34="L",0.68,IF(S34="JP",0.57,IF(S34="JI",0.57,IF(S34="JD",0.57,IF(S34="P",0.24,IF(S34="I",0.12,IF(S34="D",0.13))))))) -> 0.68 | U34: =T34*R34 -> 0 | V34: =W34/F34 -> #REF! | W34: ='CD R Documentación'!O35+'CD R Documentación'!T35+'CD R Documentación'!Y35+'CD R Documentación'!AD35+'CD R Documentación'!AI35+'CD R Documentación'!AN35+#REF! -> #REF! | X34: ='CD R Documentación'!R35+'CD R Documentación'!W35+'CD R Documentación'!AB35+'CD R Documentación'!AG35+'CD R Documentación'!AL35+'CD R Documentación'!AQ35+#REF! -> #REF! | Y34: =Z34/F34 -> 0.4 | Z34: ='CD R Investigación'!P35+'CD R Investigación'!U35+'CD R Investigación'!Z35+'CD R Investigación'!AE35+'CD R Investigación'!AJ35+'CD R Investigación'!AO35+'CD R Investigación'!AT35+'CD R Investigación'!AY35 -> 4 | AA34: ='CD R Investigación'!S35+'CD R Investigación'!X35+'CD R Investigación'!AC35+'CD R Investigación'!AH35+'CD R Investigación'!AM35+'CD R Investigación'!AR35+'CD R Investigación'!AW35+'CD R Investigación'!BB35 -> 1.76 | AB34: =AC34/F34 -> #REF! | AC34: ='CD R Desarrollo'!P35+'CD R Desarrollo'!U35+'CD R Desarrollo'!Z35+'CD R Desarrollo'!AE35+'CD R Desarrollo'!AJ35+'CD R Desarrollo'!AO35+#REF!+#REF! -> #REF! | AD34: ='CD R Desarrollo'!S35+'CD R Desarrollo'!X35+'CD R Desarrollo'!AC35+'CD R Desarrollo'!AH35+'CD R Desarrollo'!AM35+'CD R Desarrollo'!AR35+#REF!+#REF! -> #REF! | AE34: 1 | AF34: ='PL Cronograma detallado'!L131*AE34 -> 12.05 | AG34: =AF34/'PL Cronograma detallado'!M$257 -> #DIV/0! | AH34: =AG34+AH33 -> #DIV/0!
A35: 2.2.8 | B35: Realizar análisis bibliométrico en Oxford Journals, IOP Science, WoL | C35: 44676 | D35: 44695 | E35: =_xludf.DAYs(D35,C35)+1 -> #NAME? | F35: 10 | G35: =F35/F$105 -> 0.011350738 | H35: =SUM(H34,G35) -> 0.10102157 | I35: =SUM(R35,W35,Z35,AC35) -> #REF! | J35: =SUM(I35,J34) -> #REF! | K35: =J35/$J$104 -> #REF! | L35: =SUM(U35,X35,AA35,AD35) -> #REF! | M35: =SUM(L35,M34) -> #REF! | N35: =G35*AE35 -> 0.011350738 | O35: =SUM(N35,O34) -> 0.099886493 | P35: =M35/$M$93 -> #REF! | Q35: =R35/F35 -> 0 | R35: 0 | S35: L | T35: =IF(S35="L",0.68,IF(S35="JP",0.57,IF(S35="JI",0.57,IF(S35="JD",0.57,IF(S35="P",0.24,IF(S35="I",0.12,IF(S35="D",0.13))))))) -> 0.68 | U35: =T35*R35 -> 0 | V35: =W35/F35 -> #REF! | W35: ='CD R Documentación'!O36+'CD R Documentación'!T36+'CD R Documentación'!Y36+'CD R Documentación'!AD36+'CD R Documentación'!AI36+'CD R Documentación'!AN36+#REF! -> #REF! | X35: ='CD R Documentación'!R36+'CD R Documentación'!W36+'CD R Documentación'!AB36+'CD R Documentación'!AG36+'CD R Documentación'!AL36+'CD R Documentación'!AQ36+#REF! -> #REF! | Y35: =Z35/F35 -> 0.8 | Z35: ='CD R Investigación'!P36+'CD R Investigación'!U36+'CD R Investigación'!Z36+'CD R Investigación'!AE36+'CD R Investigación'!AJ36+'CD R Investigación'!AO36+'CD R Investigación'!AT36+'CD R Investigación'!AY36 -> 8 | AA35: ='CD R Investigación'!S36+'CD R Investigación'!X36+'CD R Investigación'!AC36+'CD R Investigación'!AH36+'CD R Investigación'!AM36+'CD R Investigación'!AR36+'CD R Investigación'!AW36+'CD R Investigación'!BB36 -> 3.52 | AB35: =AC35/F35 -> #REF! | AC35: ='CD R Desarrollo'!P36+'CD R Desarrollo'!U36+'CD R Desarrollo'!Z36+'CD R Desarrollo'!AE36+'CD R Desarrollo'!AJ36+'CD R Desarrollo'!AO36+#REF!+#REF! -> #REF! | AD35: ='CD R Desarrollo'!S36+'CD R Desarrollo'!X36+'CD R Desarrollo'!AC36+'CD R Desarrollo'!AH36+'CD R Desarrollo'!AM36+'CD R Desarrollo'!AR36+#REF!+#REF! -> #REF! | AE35: 1 | AF35: ='PL Cronograma detallado'!L133*AE35 -> 5.01 | AG35: =AF35/'PL Cronograma detallado'!M$257 -> #DIV/0! | AH35: =AG35+AH34 -> #DIV/0!
A36: 2.2.9 | B36: Realizar análisis bibliométrico en Scopus, WoL e IEEE Xplore | C36: 44676 | D36: 44695 | E36: =_xludf.DAYs(D36,C36)+1 -> #NAME? | F36: 10 | G36: =F36/F$105 -> 0.011350738 | H36: =SUM(H35,G36) -> 0.1123723 | I36: =SUM(R36,W36,Z36,AC36) -> #REF! | J36: =SUM(I36,J35) -> #REF! | K36: =J36/$J$104 -> #REF! | L36: =SUM(U36,X36,AA36,AD36) -> #REF! | M36: =SUM(L36,M35) -> #REF! | N36: =G36*AE36 -> 0.011350738 | O36: =SUM(N36,O35) -> 0.11123723 | P36: =M36/$M$93 -> #REF! | Q36: =R36/F36 -> 0 | R36: 0 | S36: L | T36: =IF(S36="L",0.68,IF(S36="JP",0.57,IF(S36="JI",0.57,IF(S36="JD",0.57,IF(S36="P",0.24,IF(S36="I",0.12,IF(S36="D",0.13))))))) -> 0.68 | U36: =T36*R36 -> 0 | V36: =W36/F36 -> #REF! | W36: ='CD R Documentación'!O37+'CD R Documentación'!T37+'CD R Documentación'!Y37+'CD R Documentación'!AD37+'CD R Documentación'!AI37+'CD R Documentación'!AN37+#REF! -> #REF! | X36: ='CD R Documentación'!R37+'CD R Documentación'!W37+'CD R Documentación'!AB37+'CD R Documentación'!AG37+'CD R Documentación'!AL37+'CD R Documentación'!AQ37+#REF! -> #REF! | Y36: =Z36/F36 -> 0.4 | Z36: ='CD R Investigación'!P37+'CD R Investigación'!U37+'CD R Investigación'!Z37+'CD R Investigación'!AE37+'CD R Investigación'!AJ37+'CD R Investigación'!AO37+'CD R Investigación'!AT37+'CD R Investigación'!AY37 -> 4 | AA36: ='CD R Investigación'!S37+'CD R Investigación'!X37+'CD R Investigación'!AC37+'CD R Investigación'!AH37+'CD R Investigación'!AM37+'CD R Investigación'!AR37+'CD R Investigación'!AW37+'CD R Investigación'!BB37 -> 1.76 | AB36: =AC36/F36 -> #REF! | AC36: ='CD R Desarrollo'!P37+'CD R Desarrollo'!U37+'CD R Desarrollo'!Z37+'CD R Desarrollo'!AE37+'CD R Desarrollo'!AJ37+'CD R Desarrollo'!AO37+#REF!+#REF! -> #REF! | AD36: ='CD R Desarrollo'!S37+'CD R Desarrollo'!X37+'CD R Desarrollo'!AC37+'CD R Desarrollo'!AH37+'CD R Desarrollo'!AM37+'CD R Desarrollo'!AR37+#REF!+#REF! -> #REF! | AE36: 1 | AF36: ='PL Cronograma detallado'!L134*AE36 -> 5.11 | AG36: =AF36/'PL Cronograma detallado'!M$257 -> #DIV/0! | AH36: =AG36+AH35 -> #DIV/0!
A37: 2.3 | B37: Investigación de Lenguas | C37: 44676 | D37: 44695 | E37: =_xludf.DAYs(D37,C37)+1 -> #NAME? | F37: =SUM(F38:F49) -> 180 | G37: =SUM(G38:G49) -> 0.20431328 | H37: =SUM(H36,G37) -> 0.31668558 | I37: =SUM(I38:I49) -> #REF! | J37: =SUM(I37,J26) -> #REF! | K37: =J37/$J$104 -> #REF! | L37: =SUM(L38:L49) -> #REF! | M37: =SUM(L37,M26) -> #REF! | O37: =AH37 | P37: =M37/$M$93 -> #REF! | W37: ='CD R Documentación'!O38+'CD R Documentación'!T38+'CD R Documentación'!Y38+'CD R Documentación'!AD38+'CD R Documentación'!AI38+'CD R Documentación'!AN38+#REF! -> #REF! | X37: ='CD R Documentación'!R38+'CD R Documentación'!W38+'CD R Documentación'!AB38+'CD R Documentación'!AG38+'CD R Documentación'!AL38+'CD R Documentación'!AQ38+#REF! -> #REF! | Z37: ='CD R Investigación'!P38+'CD R Investigación'!U38+'CD R Investigación'!Z38+'CD R Investigación'!AE38+'CD R Investigación'!AJ38+'CD R Investigación'!AO38+'CD R Investigación'!AT38+'CD R Investigación'!AY38 -> 1 | AA37: ='CD R Investigación'!S38+'CD R Investigación'!X38+'CD R Investigación'!AC38+'CD R Investigación'!AH38+'CD R Investigación'!AM38+'CD R Investigación'!AR38+'CD R Investigación'!AW38+'CD R Investigación'!BB38 -> 0.44 | AC37: ='CD R Desarrollo'!P38+'CD R Desarrollo'!U38+'CD R Desarrollo'!Z38+'CD R Desarrollo'!AE38+'CD R Desarrollo'!AJ38+'CD R Desarrollo'!AO38+#REF!+#REF! -> #REF! | AD37: ='CD R Desarrollo'!S38+'CD R Desarrollo'!X38+'CD R Desarrollo'!AC38+'CD R Desarrollo'!AH38+'CD R Desarrollo'!AM38+'CD R Desarrollo'!AR38+#REF!+#REF! -> #REF!
A38: 2.3.1 | B38: Investigar Lengua Mapudungun | C38: 44676 | D38: 44681 | E38: =_xludf.DAYs(D38,C38)+1 -> #NAME? | F38: 7 | G38: =F38/F$105 -> 0.0079455165 | H38: =SUM(H36,G38) -> 0.12031782 | I38: =SUM(R38,W38,Z38,AC38) -> #REF! | J38: =SUM(I38,J36) -> #REF! | K38: =J38/$J$104 -> #REF! | L38: =SUM(U38,X38,AA38,AD38) -> #REF! | M38: =SUM(L38,M36) -> #REF! | N38: =G38*AE38 -> 0.0079455165 | O38: =SUM(N38,O36) -> 0.11918275 | P38: =M38/$M$93 -> #REF! | Q38: =R38/F38 -> 0 | R38: 0 | S38: L | T38: =IF(S38="L",0.68,IF(S38="JP",0.57,IF(S38="JI",0.57,IF(S38="JD",0.57,IF(S38="P",0.24,IF(S38="I",0.12,IF(S38="D",0.13))))))) -> 0.68 | U38: =T38*R38 -> 0 | V38: =W38/F38 -> #REF! | W38: ='CD R Documentación'!O39+'CD R Documentación'!T39+'CD R Documentación'!Y39+'CD R Documentación'!AD39+'CD R Documentación'!AI39+'CD R Documentación'!AN39+#REF! -> #REF! | X38: ='CD R Documentación'!R39+'CD R Documentación'!W39+'CD R Documentación'!AB39+'CD R Documentación'!AG39+'CD R Documentación'!AL39+'CD R Documentación'!AQ39+#REF! -> #REF! | Y38: =Z38/F38 -> 0 | Z38: ='CD R Investigación'!P39+'CD R Investigación'!U39+'CD R Investigación'!Z39+'CD R Investigación'!AE39+'CD R Investigación'!AJ39+'CD R Investigación'!AO39+'CD R Investigación'!AT39+'CD R Investigación'!AY39 -> 0 | AA38: ='CD R Investigación'!S39+'CD R Investigación'!X39+'CD R Investigación'!AC39+'CD R Investigación'!AH39+'CD R Investigación'!AM39+'CD R Investigación'!AR39+'CD R Investigación'!AW39+'CD R Investigación'!BB39 -> 0 | AB38: =AC38/F38 -> #REF! | AC38: ='CD R Desarrollo'!P39+'CD R Desarrollo'!U39+'CD R Desarrollo'!Z39+'CD R Desarrollo'!AE39+'CD R Desarrollo'!AJ39+'CD R Desarrollo'!AO39+#REF!+#REF! -> #REF! | AD38: ='CD R Desarrollo'!S39+'CD R Desarrollo'!X39+'CD R Desarrollo'!AC39+'CD R Desarrollo'!AH39+'CD R Desarrollo'!AM39+'CD R Desarrollo'!AR39+#REF!+#REF! -> #REF! | AE38: 1 | AF38: ='PL Cronograma detallado'!L136*AE38 -> 2.49 | AG38: =AF38/'PL Cronograma detallado'!M$257 -> #DIV/0! | AH38: =AG38+AH36 -> #DIV/0!
A39: 2.3.2 | B39: Investigación de herramientas de traducción de inglés a español | C39: 44676 | D39: 44681 | E39: =_xludf.DAYs(D39,C39)+1 -> #NAME? | F39: 6 | G39: =F39/F$105 -> 0.0068104427 | H39: =SUM(H38,G39) -> 0.12712826 | I39: =SUM(R39,W39,Z39,AC39) -> #REF! | J39: =SUM(I39,J38) -> #REF! | K39: =J39/$J$104 -> #REF! | L39: =SUM(U39,X39,AA39,AD39) -> #REF! | M39: =SUM(L39,M38) -> #REF! | N39: =G39*AE39 -> 0.0068104427 | O39: =SUM(N39,O38) -> 0.12599319 | P39: =M39/$M$93 -> #REF! | Q39: =R39/F39 -> 0 | R39: 0 | S39: L | T39: =IF(S39="L",0.68,IF(S39="JP",0.57,IF(S39="JI",0.57,IF(S39="JD",0.57,IF(S39="P",0.24,IF(S39="I",0.12,IF(S39="D",0.13))))))) -> 0.68 | U39: =T39*R39 -> 0 | V39: =W39/F39 -> #REF! | W39: ='CD R Documentación'!O40+'CD R Documentación'!T40+'CD R Documentación'!Y40+'CD R Documentación'!AD40+'CD R Documentación'!AI40+'CD R Documentación'!AN40+#REF! -> #REF! | X39: ='CD R Documentación'!R40+'CD R Documentación'!W40+'CD R Documentación'!AB40+'CD R Documentación'!AG40+'CD R Documentación'!AL40+'CD R Documentación'!AQ40+#REF! -> #REF! | Y39: =Z39/F39 -> 12.5 | Z39: ='CD R Investigación'!P40+'CD R Investigación'!U40+'CD R Investigación'!Z40+'CD R Investigación'!AE40+'CD R Investigación'!AJ40+'CD R Investigación'!AO40+'CD R Investigación'!AT40+'CD R Investigación'!AY40 -> 75 | AA39: ='CD R Investigación'!S40+'CD R Investigación'!X40+'CD R Investigación'!AC40+'CD R Investigación'!AH40+'CD R Investigación'!AM40+'CD R Investigación'!AR40+'CD R Investigación'!AW40+'CD R Investigación'!BB40 -> 33 | AB39: =AC39/F39 -> #REF! | AC39: ='CD R Desarrollo'!P40+'CD R Desarrollo'!U40+'CD R Desarrollo'!Z40+'CD R Desarrollo'!AE40+'CD R Desarrollo'!AJ40+'CD R Desarrollo'!AO40+#REF!+#REF! -> #REF! | AD39: ='CD R Desarrollo'!S40+'CD R Desarrollo'!X40+'CD R Desarrollo'!AC40+'CD R Desarrollo'!AH40+'CD R Desarrollo'!AM40+'CD R Desarrollo'!AR40+#REF!+#REF! -> #REF! | AE39: 1 | AF39: ='PL Cronograma detallado'!L138*AE39 -> 3.43 | AG39: =AF39/'PL Cronograma detallado'!M$257 -> #DIV/0! | AH39: =AG39+AH38 -> #DIV/0!
A40: 2.3.3 | B40: Investigación sobre Inteligencia artificial | C40: 44676 | D40: 44681 | E40: =_xludf.DAYs(D40,C40)+1 -> #NAME? | F40: 6 | G40: =F40/F$105 -> 0.0068104427 | H40: =SUM(H39,G40) -> 0.13393871 | I40: =SUM(R40,W40,Z40,AC40) -> #REF! | J40: =SUM(I40,J39) -> #REF! | K40: =J40/$J$104 -> #REF! | L40: =SUM(U40,X40,AA40,AD40) -> #REF! | M40: =SUM(L40,M39) -> #REF! | N40: =G40*AE40 -> 0.0068104427 | O40: =SUM(N40,O39) -> 0.13280363 | P40: =M40/$M$93 -> #REF! | Q40: =R40/F40 -> 0 | R40: 0 | S40: L | T40: =IF(S40="L",0.68,IF(S40="JP",0.57,IF(S40="JI",0.57,IF(S40="JD",0.57,IF(S40="P",0.24,IF(S40="I",0.12,IF(S40="D",0.13))))))) -> 0.68 | U40: =T40*R40 -> 0 | V40: =W40/F40 -> #REF! | W40: ='CD R Documentación'!O41+'CD R Documentación'!T41+'CD R Documentación'!Y41+'CD R Documentación'!AD41+'CD R Documentación'!AI41+'CD R Documentación'!AN41+#REF! -> #REF! | X40: ='CD R Documentación'!R41+'CD R Documentación'!W41+'CD R Documentación'!AB41+'CD R Documentación'!AG41+'CD R Documentación'!AL41+'CD R Documentación'!AQ41+#REF! -> #REF! | Y40: =Z40/F40 -> 5 | Z40: ='CD R Investigación'!P41+'CD R Investigación'!U41+'CD R Investigación'!Z41+'CD R Investigación'!AE41+'CD R Investigación'!AJ41+'CD R Investigación'!AO41+'CD R Investigación'!AT41+'CD R Investigación'!AY41 -> 30 | AA40: ='CD R Investigación'!S41+'CD R Investigación'!X41+'CD R Investigación'!AC41+'CD R Investigación'!AH41+'CD R Investigación'!AM41+'CD R Investigación'!AR41+'CD R Investigación'!AW41+'CD R Investigación'!BB41 -> 13.2 | AB40: =AC40/F40 -> #REF! | AC40: ='CD R Desarrollo'!P41+'CD R Desarrollo'!U41+'CD R Desarrollo'!Z41+'CD R Desarrollo'!AE41+'CD R Desarrollo'!AJ41+'CD R Desarrollo'!AO41+#REF!+#REF! -> #REF! | AD40: ='CD R Desarrollo'!S41+'CD R Desarrollo'!X41+'CD R Desarrollo'!AC41+'CD R Desarrollo'!AH41+'CD R Desarrollo'!AM41+'CD R Desarrollo'!AR41+#REF!+#REF! -> #REF! | AE40: 1 | AF40: ='PL Cronograma detallado'!L139*AE40 -> 7.94 | AG40: =AF40/'PL Cronograma detallado'!M$257 -> #DIV/0! | AH40: =AG40+AH39 -> #DIV/0!
A41: 2.4 | B41: Preparación Avance N°1 | C41: 44669 | D41: 44676 | E41: =_xludf.DAYs(D41,C41)+1 -> #NAME? | F41: 24 | G41: =(F41/F105) -> 0.027241771 | H41: =SUM(H40,G41) -> 0.16118048 | I41: =SUM(R41,W41,Z41,AC41) -> #REF! | J41: =I41+J40 -> #REF! | L41: =SUM(U41,X41,AA41,AD41) -> #REF! | M41: =SUM(L41,M40) -> #REF! | N41: =G41*AE41 -> 0.027241771 | O41: =SUM(N41,O40) -> 0.1600454 | P41: =M41/$M$93 -> #REF! | Q41: =R41/F41 -> 0.125 | R41: 3 | S41: L | T41: =IF(S41="L",0.68,IF(S41="JP",0.57,IF(S41="JI",0.57,IF(S41="JD",0.57,IF(S41="P",0.24,IF(S41="I",0.12,IF(S41="D",0.13))))))) -> 0.68 | U41: =T41*R41 -> 2.04 | V41: =W41/F41 -> #REF! | W41: ='CD R Documentación'!O42+'CD R Documentación'!T42+'CD R Documentación'!Y42+'CD R Documentación'!AD42+'CD R Documentación'!AI42+'CD R Documentación'!AN42+#REF! -> #REF! | X41: ='CD R Documentación'!R42+'CD R Documentación'!W42+'CD R Documentación'!AB42+'CD R Documentación'!AG42+'CD R Documentación'!AL42+'CD R Documentación'!AQ42+#REF! -> #REF! | Y41: =Z41/F41 -> 2.375 | Z41: ='CD R Investigación'!P42+'CD R Investigación'!U42+'CD R Investigación'!Z42+'CD R Investigación'!AE42+'CD R Investigación'!AJ42+'CD R Investigación'!AO42+'CD R Investigación'!AT42+'CD R Investigación'!AY42 -> 57 | AA41: ='CD R Investigación'!S42+'CD R Investigación'!X42+'CD R Investigación'!AC42+'CD R Investigación'!AH42+'CD R Investigación'!AM42+'CD R Investigación'!AR42+'CD R Investigación'!AW42+'CD R Investigación'!BB42 -> 25.08 | AB41: =AC41/F41 -> #REF! | AC41: ='CD R Desarrollo'!P42+'CD R Desarrollo'!U42+'CD R Desarrollo'!Z42+'CD R Desarrollo'!AE42+'CD R Desarrollo'!AJ42+'CD R Desarrollo'!AO42+#REF!+#REF! -> #REF! | AD41: ='CD R Desarrollo'!S42+'CD R Desarrollo'!X42+'CD R Desarrollo'!AC42+'CD R Desarrollo'!AH42+'CD R Desarrollo'!AM42+'CD R Desarrollo'!AR42+#REF!+#REF! -> #REF! | AE41: 1 | AF41: ='PL Cronograma detallado'!L140*AE41 -> 2.49 | AG41: =AF41/'PL Cronograma detallado'!M$257 -> #DIV/0! | AH41: =AG41+AH40 -> #DIV/0!
A42: H2 | B42: Entrega Avance N°1 y Defensa | C42: 44677 | D42: 44677 | E42: =_xludf.DAYs(D42,C42)+1 -> #NAME? | F42: 1 | G42: =(F42/F105) -> 0.0011350738 | H42: =SUM(H41,G42) -> 0.16231555 | I42: =SUM(R42,W42,Z42,AC42) -> #REF! | J42: =I42+J41 -> #REF! | K42: =J42/$J$104 -> #REF! | L42: =SUM(U42,X42,AA42,AD42) -> #REF! | M42: =SUM(L42,M41) -> #REF! | N42: =G42*AE42 -> 0.0011350738 | O42: =SUM(N42,O41) -> 0.16118048 | P42: =M42/$M$93 -> #REF! | Q42: =R42/F42 -> 1 | R42: 1 | S42: L | T42: =IF(S42="L",0.68,IF(S42="JP",0.57,IF(S42="JI",0.57,IF(S42="JD",0.57,IF(S42="P",0.24,IF(S42="I",0.12,IF(S42="D",0.13))))))) -> 0.68 | U42: =T42*R42 -> 0.68 | V42: =W42/F42 -> #REF! | W42: ='CD R Documentación'!O43+'CD R Documentación'!T43+'CD R Documentación'!Y43+'CD R Documentación'!AD43+'CD R Documentación'!AI43+'CD R Documentación'!AN43+#REF! -> #REF! | X42: ='CD R Documentación'!R43+'CD R Documentación'!W43+'CD R Documentación'!AB43+'CD R Documentación'!AG43+'CD R Documentación'!AL43+'CD R Documentación'!AQ43+#REF! -> #REF! | Y42: =Z42/F42 -> 15 | Z42: ='CD R Investigación'!P43+'CD R Investigación'!U43+'CD R Investigación'!Z43+'CD R Investigación'!AE43+'CD R Investigación'!AJ43+'CD R Investigación'!AO43+'CD R Investigación'!AT43+'CD R Investigación'!AY43 -> 15 | AA42: ='CD R Investigación'!S43+'CD R Investigación'!X43+'CD R Investigación'!AC43+'CD R Investigación'!AH43+'CD R Investigación'!AM43+'CD R Investigación'!AR43+'CD R Investigación'!AW43+'CD R Investigación'!BB43 -> 6.6 | AB42: =AC42/F42 -> #REF! | AC42: ='CD R Desarrollo'!P43+'CD R Desarrollo'!U43+'CD R Desarrollo'!Z43+'CD R Desarrollo'!AE43+'CD R Desarrollo'!AJ43+'CD R Desarrollo'!AO43+#REF!+#REF! -> #REF! | AD42: ='CD R Desarrollo'!S43+'CD R Desarrollo'!X43+'CD R Desarrollo'!AC43+'CD R Desarrollo'!AH43+'CD R Desarrollo'!AM43+'CD R Desarrollo'!AR43+#REF!+#REF! -> #REF! | AE42: 1 | AF42: ='PL Cronograma detallado'!L143*AE42 -> 0.61 | AG42: =AF42/'PL Cronograma detallado'!M$257 -> #DIV/0! | AH42: =AG42+AH41 -> #DIV/0!
A43: 2.3.4 | B43: Analizar Estado del Arte de la Fase Anterior del Proyecto (Parte 2) | C43: 44677 | D43: 44703 | E43: =_xludf.DAYs(D43,C43)+1 -> #NAME? | F43: 54 | G43: =F43/F$105 -> 0.061293984 | H43: =SUM(H42,G43) -> 0.22360953 | I43: =SUM(R43,W43,Z43,AC43) -> #REF! | J43: =SUM(I43,J42) -> #REF! | K43: =J43/$J$104 -> #REF! | L43: =SUM(U43,X43,AA43,AD43) -> #REF! | M43: =SUM(L43,M42) -> #REF! | N43: =G43*AE43 -> 0.061293984 | O43: =SUM(N43,O42) -> 0.22247446 | P43: =M43/$M$93 -> #REF! | Q43: =R43/F43 -> 0 | R43: 0 | S43: L | T43: =IF(S43="L",0.68,IF(S43="JP",0.57,IF(S43="JI",0.57,IF(S43="JD",0.57,IF(S43="P",0.24,IF(S43="I",0.12,IF(S43="D",0.13))))))) -> 0.68 | U43: =T43*R43 -> 0 | V43: =W43/F43 -> #REF! | W43: ='CD R Documentación'!O44+'CD R Documentación'!T44+'CD R Documentación'!Y44+'CD R Documentación'!AD44+'CD R Documentación'!AI44+'CD R Documentación'!AN44+#REF! -> #REF! | X43: ='CD R Documentación'!R44+'CD R Documentación'!W44+'CD R Documentación'!AB44+'CD R Documentación'!AG44+'CD R Documentación'!AL44+'CD R Documentación'!AQ44+#REF! -> #REF! | Y43: =Z43/F43 -> 0.14814815 | Z43: ='CD R Investigación'!P44+'CD R Investigación'!U44+'CD R Investigación'!Z44+'CD R Investigación'!AE44+'CD R Investigación'!AJ44+'CD R Investigación'!AO44+'CD R Investigación'!AT44+'CD R Investigación'!AY44 -> 8 | AA43: ='CD R Investigación'!S44+'CD R Investigación'!X44+'CD R Investigación'!AC44+'CD R Investigación'!AH44+'CD R Investigación'!AM44+'CD R Investigación'!AR44+'CD R Investigación'!AW44+'CD R Investigación'!BB44 -> 3.52 | AB43: =AC43/F43 -> #REF! | AC43: ='CD R Desarrollo'!P44+'CD R Desarrollo'!U44+'CD R Desarrollo'!Z44+'CD R Desarrollo'!AE44+'CD R Desarrollo'!AJ44+'CD R Desarrollo'!AO44+#REF!+#REF! -> #REF! | AD43: ='CD R Desarrollo'!S44+'CD R Desarrollo'!X44+'CD R Desarrollo'!AC44+'CD R Desarrollo'!AH44+'CD R Desarrollo'!AM44+'CD R Desarrollo'!AR44+#REF!+#REF! -> #REF! | AE43: 1 | AF43: ='PL Cronograma detallado'!L145*AE43 -> 0 | AG43: =AF43/'PL Cronograma detallado'!M$257 -> #DIV/0! | AH43: =AG43+AH42 -> #DIV/0!
A44: 2.3.5 | B44: Documentar palabras mapuches y su traducción al español | C44: 44680 | D44: 44690 | E44: =_xludf.DAYs(D44,C44)+1 -> #NAME? | F44: 22 | G44: =F44/F$105 -> 0.024971623 | H44: =SUM(H43,G44) -> 0.24858116 | I44: =SUM(R44,W44,Z44,AC44) -> #REF! | J44: =SUM(I44,J43) -> #REF! | K44: =J44/$J$104 -> #REF! | L44: =SUM(U44,X44,AA44,AD44) -> #REF! | M44: =SUM(L44,M43) -> #REF! | N44: =G44*AE44 -> 0.024971623 | O44: =SUM(N44,O43) -> 0.24744608 | P44: =M44/$M$93 -> #REF! | Q44: =R44/F44 -> 0 | R44: 0 | S44: L | T44: =IF(S44="L",0.68,IF(S44="JP",0.57,IF(S44="JI",0.57,IF(S44="JD",0.57,IF(S44="P",0.24,IF(S44="I",0.12,IF(S44="D",0.13))))))) -> 0.68 | U44: =T44*R44 -> 0 | V44: =W44/F44 -> #REF! | W44: ='CD R Documentación'!O45+'CD R Documentación'!T45+'CD R Documentación'!Y45+'CD R Documentación'!AD45+'CD R Documentación'!AI45+'CD R Documentación'!AN45+#REF! -> #REF! | X44: ='CD R Documentación'!R45+'CD R Documentación'!W45+'CD R Documentación'!AB45+'CD R Documentación'!AG45+'CD R Documentación'!AL45+'CD R Documentación'!AQ45+#REF! -> #REF! | Y44: =Z44/F44 -> 1 | Z44: 22 | AA44: ='CD R Investigación'!S45+'CD R Investigación'!X45+'CD R Investigación'!AC45+'CD R Investigación'!AH45+'CD R Investigación'!AM45+'CD R Investigación'!AR45+'CD R Investigación'!AW45+'CD R Investigación'!BB45 -> 0 | AB44: =AC44/F44 -> #REF! | AC44: ='CD R Desarrollo'!P45+'CD R Desarrollo'!U45+'CD R Desarrollo'!Z45+'CD R Desarrollo'!AE45+'CD R Desarrollo'!AJ45+'CD R Desarrollo'!AO45+#REF!+#REF! -> #REF! | AD44: ='CD R Desarrollo'!S45+'CD R Desarrollo'!X45+'CD R Desarrollo'!AC45+'CD R Desarrollo'!AH45+'CD R Desarrollo'!AM45+'CD R Desarrollo'!AR45+#REF!+#REF! -> #REF! | AE44: 1 | AF44: ='PL Cronograma detallado'!L146*AE44 -> 75.1 | AG44: =AF44/'PL Cronograma detallado'!M$257 -> #DIV/0! | AH44: =AG44+AH43 -> #DIV/0!
A45: 2.3.6 | B45: Definición de conjunto de Expresiones | C45: 44680 | D45: 44690 | E45: =_xludf.DAYs(D45,C45)+1 -> #NAME? | F45: 30 | G45: =F45/F$105 -> 0.034052213 | H45: =SUM(H44,G45) -> 0.28263337 | I45: =SUM(R45,W45,Z45,AC45) -> #REF! | J45: =SUM(I45,J44) -> #REF! | K45: =J45/$J$104 -> #REF! | L45: =SUM(U45,X45,AA45,AD45) -> #REF! | M45: =SUM(L45,M44) -> #REF! | N45: =G45*AE45 -> 0.034052213 | O45: =SUM(N45,O44) -> 0.2814983 | P45: =M45/$M$93 -> #REF! | Q45: =R45/F45 -> 0 | R45: 0 | S45: L | T45: =IF(S45="L",0.68,IF(S45="JP",0.57,IF(S45="JI",0.57,IF(S45="JD",0.57,IF(S45="P",0.24,IF(S45="I",0.12,IF(S45="D",0.13))))))) -> 0.68 | U45: =T45*R45 -> 0 | V45: =W45/F45 -> #REF! | W45: ='CD R Documentación'!O46+'CD R Documentación'!T46+'CD R Documentación'!Y46+'CD R Documentación'!AD46+'CD R Documentación'!AI46+'CD R Documentación'!AN46+#REF! -> #REF! | X45: ='CD R Documentación'!R46+'CD R Documentación'!W46+'CD R Documentación'!AB46+'CD R Documentación'!AG46+'CD R Documentación'!AL46+'CD R Documentación'!AQ46+#REF! -> #REF! | Y45: 0.3 | Z45: ='CD R Investigación'!P46+'CD R Investigación'!U46+'CD R Investigación'!Z46+'CD R Investigación'!AE46+'CD R Investigación'!AJ46+'CD R Investigación'!AO46+'CD R Investigación'!AT46+'CD R Investigación'!AY46 -> 12 | AA45: ='CD R Investigación'!S46+'CD R Investigación'!X46+'CD R Investigación'!AC46+'CD R Investigación'!AH46+'CD R Investigación'!AM46+'CD R Investigación'!AR46+'CD R Investigación'!AW46+'CD R Investigación'!BB46 -> 5.28 | AB45: =AC45/F45 -> #REF! | AC45: ='CD R Desarrollo'!P46+'CD R Desarrollo'!U46+'CD R Desarrollo'!Z46+'CD R Desarrollo'!AE46+'CD R Desarrollo'!AJ46+'CD R Desarrollo'!AO46+#REF!+#REF! -> #REF! | AD45: ='CD R Desarrollo'!S46+'CD R Desarrollo'!X46+'CD R Desarrollo'!AC46+'CD R Desarrollo'!AH46+'CD R Desarrollo'!AM46+'CD R Desarrollo'!AR46+#REF!+#REF! -> #REF! | AE45: 1 | AF45: ='PL Cronograma detallado'!L166*AE45 -> 12.99 | AG45: =AF45/'PL Cronograma detallado'!M$257 -> #DIV/0! | AH45: =AG45+AH44 -> #DIV/0!
A46: 2.3.7 | B46: Reunión de Líderes 4 | C46: 44682 | D46: 44682 | E46: =_xludf.DAYs(D46,C46)+1 -> #NAME? | F46: 1 | G46: =F46/F$105 -> 0.0011350738 | H46: =SUM(H45,G46) -> 0.28376844 | I46: =SUM(R46,W46,Z46,AC46) -> 4 | J46: =SUM(I46,J45) -> #REF! | K46: =J46/$J$104 -> #REF! | L46: =SUM(U46,X46,AA46,AD46) -> #REF! | M46: =SUM(L46,M45) -> #REF! | N46: =G46*AE46 -> 0.0011350738 | O46: =SUM(N46,O45) -> 0.28263337 | P46: =M46/$M$93 -> #REF! | Q46: =R46/F46 -> 1 | R46: 1 | S46: L | T46: =IF(S46="L",0.68,IF(S46="JP",0.57,IF(S46="JI",0.57,IF(S46="JD",0.57,IF(S46="P",0.24,IF(S46="I",0.12,IF(S46="D",0.13))))))) -> 0.68 | U46: =T46*R46 -> 0.68 | V46: =W46/F46 -> 1 | W46: 1 | X46: ='CD R Documentación'!R47+'CD R Documentación'!W47+'CD R Documentación'!AB47+'CD R Documentación'!AG47+'CD R Documentación'!AL47+'CD R Documentación'!AQ47+#REF! -> #REF! | Y46: =Z46/F46 -> 1 | Z46: 1 | AA46: ='CD R Investigación'!S47+'CD R Investigación'!X47+'CD R Investigación'!AC47+'CD R Investigación'!AH47+'CD R Investigación'!AM47+'CD R Investigación'!AR47+'CD R Investigación'!AW47+'CD R Investigación'!BB47 -> 0 | AB46: =AC46/F46 -> 1 | AC46: 1 | AD46: ='CD R Desarrollo'!S47+'CD R Desarrollo'!X47+'CD R Desarrollo'!AC47+'CD R Desarrollo'!AH47+'CD R Desarrollo'!AM47+'CD R Desarrollo'!AR47+#REF!+#REF! -> #REF! | AE46: 1 | AF46: ='PL Cronograma detallado'!L167*AE46 -> 5.75 | AG46: =AF46/'PL Cronograma detallado'!M$257 -> #DIV/0! | AH46: =AG46+AH45 -> #DIV/0!
A47: 2.3.8 | B47: Realizar análisis Altmetric en Google Scholar | C47: 44683 | D47: 44688 | E47: =_xludf.DAYs(D47,C47)+1 -> #NAME? | F47: 12 | G47: =F47/F$105 -> 0.013620885 | H47: =SUM(H46,G47) -> 0.29738933 | I47: =SUM(R47,W47,Z47,AC47) -> #REF! | J47: =SUM(I47,J46) -> #REF! | K47: =J47/$J$104 -> #REF! | L47: =SUM(U47,X47,AA47,AD47) -> #REF! | M47: =SUM(L47,M46) -> #REF! | N47: =G47*AE47 -> 0.013620885 | O47: =SUM(N47,O46) -> 0.29625426 | P47: =M47/$M$93 -> #REF! | Q47: =R47/F47 -> 0 | R47: 0 | S47: L | T47: =IF(S47="L",0.68,IF(S47="JP",0.57,IF(S47="JI",0.57,IF(S47="JD",0.57,IF(S47="P",0.24,IF(S47="I",0.12,IF(S47="D",0.13))))))) -> 0.68 | U47: =T47*R47 -> 0 | V47: =W47/F47 -> #REF! | W47: ='CD R Documentación'!O48+'CD R Documentación'!T48+'CD R Documentación'!Y48+'CD R Documentación'!AD48+'CD R Documentación'!AI48+'CD R Documentación'!AN48+#REF! -> #REF! | X47: ='CD R Documentación'!R48+'CD R Documentación'!W48+'CD R Documentación'!AB48+'CD R Documentación'!AG48+'CD R Documentación'!AL48+'CD R Documentación'!AQ48+#REF! -> #REF! | Y47: 1 | Z47: 7.5 | AA47: ='CD R Investigación'!S48+'CD R Investigación'!X48+'CD R Investigación'!AC48+'CD R Investigación'!AH48+'CD R Investigación'!AM48+'CD R Investigación'!AR48+'CD R Investigación'!AW48+'CD R Investigación'!BB48 -> 3.52 | AB47: =AC47/F47 -> #REF! | AC47: ='CD R Desarrollo'!P48+'CD R Desarrollo'!U48+'CD R Desarrollo'!Z48+'CD R Desarrollo'!AE48+'CD R Desarrollo'!AJ48+'CD R Desarrollo'!AO48+#REF!+#REF! -> #REF! | AD47: ='CD R Desarrollo'!S48+'CD R Desarrollo'!X48+'CD R Desarrollo'!AC48+'CD R Desarrollo'!AH48+'CD R Desarrollo'!AM48+'CD R Desarrollo'!AR48+#REF!+#REF! -> #REF! | AE47: 1 | AF47: ='PL Cronograma detallado'!L169*AE47 -> 5.31 | AG47: =AF47/'PL Cronograma detallado'!M$257 -> #DIV/0! | AH47: =AG47+AH46 -> #DIV/0!
A48: 2.3.9 | B48: Elaborar Documentación Relacionada al Levantamiento de Información | C48: 44683 | D48: 44694 | E48: =_xludf.DAYs(D48,C48)+1 -> #NAME? | F48: 16 | G48: =F48/F$105 -> 0.01816118 | H48: =SUM(H47,G48) -> 0.31555051 | I48: =SUM(R48,W48,Z48,AC48) -> #REF! | J48: =SUM(I48,J47) -> #REF! | K48: =J48/$J$104 -> #REF! | L48: =SUM(U48,X48,AA48,AD48) -> #REF! | M48: =SUM(L48,M47) -> #REF! | N48: =G48*AE48 -> 0.01816118 | O48: =SUM(N48,O47) -> 0.31441544 | P48: =M48/$M$93 -> #REF! | Q48: =R48/F48 -> 0 | R48: 0 | S48: L | T48: =IF(S48="L",0.68,IF(S48="JP",0.57,IF(S48="JI",0.57,IF(S48="JD",0.57,IF(S48="P",0.24,IF(S48="I",0.12,IF(S48="D",0.13))))))) -> 0.68 | U48: =T48*R48 -> 0 | V48: =W48/F48 -> #REF! | W48: ='CD R Documentación'!O49+'CD R Documentación'!T49+'CD R Documentación'!Y49+'CD R Documentación'!AD49+'CD R Documentación'!AI49+'CD R Documentación'!AN49+#REF! -> #REF! | X48: ='CD R Documentación'!R49+'CD R Documentación'!W49+'CD R Documentación'!AB49+'CD R Documentación'!AG49+'CD R Documentación'!AL49+'CD R Documentación'!AQ49+#REF! -> #REF! | Y48: =Z48/F48 -> 0.375 | Z48: ='CD R Investigación'!P49+'CD R Investigación'!U49+'CD R Investigación'!Z49+'CD R Investigación'!AE49+'CD R Investigación'!AJ49+'CD R Investigación'!AO49+'CD R Investigación'!AT49+'CD R Investigación'!AY49 -> 6 | AA48: ='CD R Investigación'!S49+'CD R Investigación'!X49+'CD R Investigación'!AC49+'CD R Investigación'!AH49+'CD R Investigación'!AM49+'CD R Investigación'!AR49+'CD R Investigación'!AW49+'CD R Investigación'!BB49 -> 2.64 | AB48: =AC48/F48 -> #REF! | AC48: ='CD R Desarrollo'!P49+'CD R Desarrollo'!U49+'CD R Desarrollo'!Z49+'CD R Desarrollo'!AE49+'CD R Desarrollo'!AJ49+'CD R Desarrollo'!AO49+#REF!+#REF! -> #REF! | AD48: ='CD R Desarrollo'!S49+'CD R Desarrollo'!X49+'CD R Desarrollo'!AC49+'CD R Desarrollo'!AH49+'CD R Desarrollo'!AM49+'CD R Desarrollo'!AR49+#REF!+#REF! -> #REF! | AE48: 1 | AF48: ='PL Cronograma detallado'!L170*AE48 -> 11.61 | AG48: =AF48/'PL Cronograma detallado'!M$257 -> #DIV/0! | AH48: =AG48+AH47 -> #DIV/0!
A49: 2.3.10 | B49: Reunión de Líderes 5 | C49: 44689 | D49: 44689 | E49: =_xludf.DAYs(D49,C49)+1 -> #NAME? | F49: 1 | G49: =F49/F$105 -> 0.0011350738 | H49: =SUM(H48,G49) -> 0.31668558 | I49: =SUM(R49,W49,Z49,AC49) -> 4 | J49: =SUM(I49,J48) -> #REF! | K49: =J49/$J$104 -> #REF! | L49: =SUM(U49,X49,AA49,AD49) -> #REF! | M49: =SUM(L49,M48) -> #REF! | N49: =G49*AE49 -> 0.0011350738 | O49: =SUM(N49,O48) -> 0.31555051 | P49: =M49/$M$93 -> #REF! | Q49: =R49/F49 -> 1 | R49: 1 | S49: L | T49: =IF(S49="L",0.68,IF(S49="JP",0.57,IF(S49="JI",0.57,IF(S49="JD",0.57,IF(S49="P",0.24,IF(S49="I",0.12,IF(S49="D",0.13))))))) -> 0.68 | U49: =T49*R49 -> 0.68 | V49: =W49/F49 -> 1 | W49: 1 | X49: ='CD R Documentación'!R50+'CD R Documentación'!W50+'CD R Documentación'!AB50+'CD R Documentación'!AG50+'CD R Documentación'!AL50+'CD R Documentación'!AQ50+#REF! -> #REF! | Y49: =Z49/F49 -> 1 | Z49: 1 | AA49: ='CD R Investigación'!S50+'CD R Investigación'!X50+'CD R Investigación'!AC50+'CD R Investigación'!AH50+'CD R Investigación'!AM50+'CD R Investigación'!AR50+'CD R Investigación'!AW50+'CD R Investigación'!BB50 -> 5.28 | AB49: =AC49/F49 -> 1 | AC49: 1 | AD49: ='CD R Desarrollo'!S50+'CD R Desarrollo'!X50+'CD R Desarrollo'!AC50+'CD R Desarrollo'!AH50+'CD R Desarrollo'!AM50+'CD R Desarrollo'!AR50+#REF!+#REF! -> #REF! | AE49: 1 | AF49: ='PL Cronograma detallado'!L172*AE49 -> 5.11 | AG49: =AF49/'PL Cronograma detallado'!M$257 -> #DIV/0! | AH49: =AG49+AH48 -> #DIV/0!
A50: 3 | B50: Fase de Desarrollo | C50: 44695 | D50: 44751 | E50: =_xludf.DAYs(D50,C50)+1 -> #NAME? | F50: =SUM(F51,F54,F57,F64,F74) -> 409 | G50: =SUM(G51,G54,G57,G64,G74) -> 0.46424518 | I50: =SUM(I51,I54,I57,I64,I74) -> #REF! | J50: =SUM(I50,J20) -> #REF! | K50: =J50/$J$104 -> #REF! | L50: =SUM(L51,L54,L57,L64,L74) -> #REF! | M50: =SUM(L50,M49) -> #REF! | P50: =M50/$M$93 -> #REF! | Q50: =R50/F50 -> 0 | R50: 0 | S50: L | T50: =IF(S50="L",0.68,IF(S50="JP",0.57,IF(S50="JI",0.57,IF(S50="JD",0.57,IF(S50="P",0.24,IF(S50="I",0.12,IF(S50="D",0.13))))))) -> 0.68 | U50: =T50*R50 -> 0 | V50: =W50/F50 -> #REF! | W50: ='CD R Documentación'!O51+'CD R Documentación'!T51+'CD R Documentación'!Y51+'CD R Documentación'!AD51+'CD R Documentación'!AI51+'CD R Documentación'!AN51+#REF! -> #REF! | X50: ='CD R Documentación'!R51+'CD R Documentación'!W51+'CD R Documentación'!AB51+'CD R Documentación'!AG51+'CD R Documentación'!AL51+'CD R Documentación'!AQ51+#REF! -> #REF! | Y50: =Z50/F50 -> 0.014669927 | Z50: ='CD R Investigación'!P51+'CD R Investigación'!U51+'CD R Investigación'!Z51+'CD R Investigación'!AE51+'CD R Investigación'!AJ51+'CD R Investigación'!AO51+'CD R Investigación'!AT51+'CD R Investigación'!AY51 -> 6 | AA50: ='CD R Investigación'!S51+'CD R Investigación'!X51+'CD R Investigación'!AC51+'CD R Investigación'!AH51+'CD R Investigación'!AM51+'CD R Investigación'!AR51+'CD R Investigación'!AW51+'CD R Investigación'!BB51 -> 2.64 | AB50: =AC50/F50 -> #REF! | AC50: ='CD R Desarrollo'!P51+'CD R Desarrollo'!U51+'CD R Desarrollo'!Z51+'CD R Desarrollo'!AE51+'CD R Desarrollo'!AJ51+'CD R Desarrollo'!AO51+#REF!+#REF! -> #REF! | AD50: ='CD R Desarrollo'!S51+'CD R Desarrollo'!X51+'CD R Desarrollo'!AC51+'CD R Desarrollo'!AH51+'CD R Desarrollo'!AM51+'CD R Desarrollo'!AR51+#REF!+#REF! -> #REF!
A51: 3.1 | B51: Formulacion de Diseños | C51: 44695 | D51: 44701 | E51: =_xludf.DAYs(D51,C51)+1 -> #NAME? | F51: =SUM(F52:F53) -> 11 | G51: =SUM(G52:G53) -> 0.012485812 | H51: =SUM(G51,H49) -> 0.3291714 | I51: =SUM(I52:I53) -> #REF! | J51: =SUM(I51,J37) -> #REF! | K51: =J51/$J$104 -> #REF! | L51: =SUM(L52:L53) -> #REF! | M51: =SUM(L51,M49) -> #REF! | P51: =M51/$M$93 -> #REF! | Q51: =R51/F51 -> 0 | R51: 0 | S51: L | T51: =IF(S51="L",0.68,IF(S51="JP",0.57,IF(S51="JI",0.57,IF(S51="JD",0.57,IF(S51="P",0.24,IF(S51="I",0.12,IF(S51="D",0.13))))))) -> 0.68 | U51: =T51*R51 -> 0 | V51: =W51/F51 -> #REF! | W51: ='CD R Documentación'!O52+'CD R Documentación'!T52+'CD R Documentación'!Y52+'CD R Documentación'!AD52+'CD R Documentación'!AI52+'CD R Documentación'!AN52+#REF! -> #REF! | X51: ='CD R Documentación'!R52+'CD R Documentación'!W52+'CD R Documentación'!AB52+'CD R Documentación'!AG52+'CD R Documentación'!AL52+'CD R Documentación'!AQ52+#REF! -> #REF! | Y51: =Z51/F51 -> 0 | Z51: ='CD R Investigación'!P52+'CD R Investigación'!U52+'CD R Investigación'!Z52+'CD R Investigación'!AE52+'CD R Investigación'!AJ52+'CD R Investigación'!AO52+'CD R Investigación'!AT52+'CD R Investigación'!AY52 -> 0 | AA51: ='CD R Investigación'!S52+'CD R Investigación'!X52+'CD R Investigación'!AC52+'CD R Investigación'!AH52+'CD R Investigación'!AM52+'CD R Investigación'!AR52+'CD R Investigación'!AW52+'CD R Investigación'!BB52 -> 0 | AB51: =AC51/F51 -> #REF! | AC51: ='CD R Desarrollo'!P52+'CD R Desarrollo'!U52+'CD R Desarrollo'!Z52+'CD R Desarrollo'!AE52+'CD R Desarrollo'!AJ52+'CD R Desarrollo'!AO52+#REF!+#REF! -> #REF! | AD51: ='CD R Desarrollo'!S52+'CD R Desarrollo'!X52+'CD R Desarrollo'!AC52+'CD R Desarrollo'!AH52+'CD R Desarrollo'!AM52+'CD R Desarrollo'!AR52+#REF!+#REF! -> #REF!
A52: 3.1.1 | B52: MockUp del Prototipo | C52: 44695 | D52: 44701 | E52: =_xludf.DAYs(D52,C52)+1 -> #NAME? | F52: 10 | G52: =F52/F$105 -> 0.011350738 | H52: =SUM(H49,G52) -> 0.32803632 | I52: =SUM(R52,W52,Z52,AC52) -> #REF! | J52: =SUM(I52,J49) -> #REF! | K52: =J52/$J$104 -> #REF! | L52: =SUM(U52,X52,AA52,AD52) -> #REF! | M52: =SUM(L52,M49) -> #REF! | N52: =G52*AE52 -> 0.011350738 | O52: =SUM(N52,O49) -> 0.32690125 | P52: =M52/$M$93 -> #REF! | Q52: =R52/F52 -> 0 | R52: 0 | S52: L | T52: =IF(S52="L",0.68,IF(S52="JP",0.57,IF(S52="JI",0.57,IF(S52="JD",0.57,IF(S52="P",0.24,IF(S52="I",0.12,IF(S52="D",0.13))))))) -> 0.68 | U52: =T52*R52 -> 0 | V52: =W52/F52 -> #REF! | W52: ='CD R Documentación'!O53+'CD R Documentación'!T53+'CD R Documentación'!Y53+'CD R Documentación'!AD53+'CD R Documentación'!AI53+'CD R Documentación'!AN53+#REF! -> #REF! | X52: ='CD R Documentación'!R53+'CD R Documentación'!W53+'CD R Documentación'!AB53+'CD R Documentación'!AG53+'CD R Documentación'!AL53+'CD R Documentación'!AQ53+#REF! -> #REF! | Y52: =Z52/F52 -> 0.6 | Z52: ='CD R Investigación'!P53+'CD R Investigación'!U53+'CD R Investigación'!Z53+'CD R Investigación'!AE53+'CD R Investigación'!AJ53+'CD R Investigación'!AO53+'CD R Investigación'!AT53+'CD R Investigación'!AY53 -> 6 | AA52: ='CD R Investigación'!S53+'CD R Investigación'!X53+'CD R Investigación'!AC53+'CD R Investigación'!AH53+'CD R Investigación'!AM53+'CD R Investigación'!AR53+'CD R Investigación'!AW53+'CD R Investigación'!BB53 -> 2.64 | AB52: =AC52/F52 -> #REF! | AC52: ='CD R Desarrollo'!P53+'CD R Desarrollo'!U53+'CD R Desarrollo'!Z53+'CD R Desarrollo'!AE53+'CD R Desarrollo'!AJ53+'CD R Desarrollo'!AO53+#REF!+#REF! -> #REF! | AD52: ='CD R Desarrollo'!S53+'CD R Desarrollo'!X53+'CD R Desarrollo'!AC53+'CD R Desarrollo'!AH53+'CD R Desarrollo'!AM53+'CD R Desarrollo'!AR53+#REF!+#REF! -> #REF! | AE52: 1 | AF52: ='PL Cronograma detallado'!L176*AE52 -> 3.43 | AG52: =AF52/'PL Cronograma detallado'!M$257 -> #DIV/0! | AH52: =SUM(AG52,AH49) -> #DIV/0!
A53: 3.1.2 | B53: Reunión de Líderes 6 | C53: 44696 | D53: 44696 | E53: =_xludf.DAYs(D53,C53)+1 -> #NAME? | F53: 1 | G53: =F53/F$105 -> 0.0011350738 | H53: =SUM(H52,G53) -> 0.3291714 | I53: =SUM(R53,W53,Z53,AC53) -> #REF! | J53: =SUM(I53,J52) -> #REF! | K53: =J53/$J$104 -> #REF! | L53: =SUM(U53,X53,AA53,AD53) -> #REF! | M53: =SUM(L53,M52) -> #REF! | N53: =G53*AE53 -> 0.0011350738 | O53: =SUM(N53,O52) -> 0.32803632 | P53: =M53/$M$93 -> #REF! | Q53: =R53/F53 -> 1 | R53: 1 | S53: L | T53: =IF(S53="L",0.68,IF(S53="JP",0.57,IF(S53="JI",0.57,IF(S53="JD",0.57,IF(S53="P",0.24,IF(S53="I",0.12,IF(S53="D",0.13))))))) -> 0.68 | U53: =T53*R53 -> 0.68 | V53: =W53/F53 -> #REF! | W53: ='CD R Documentación'!O54+'CD R Documentación'!T54+'CD R Documentación'!Y54+'CD R Documentación'!AD54+'CD R Documentación'!AI54+'CD R Documentación'!AN54+#REF! -> #REF! | X53: ='CD R Documentación'!R54+'CD R Documentación'!W54+'CD R Documentación'!AB54+'CD R Documentación'!AG54+'CD R Documentación'!AL54+'CD R Documentación'!AQ54+#REF! -> #REF! | Y53: =Z53/F53 -> 12 | Z53: ='CD R Investigación'!P54+'CD R Investigación'!U54+'CD R Investigación'!Z54+'CD R Investigación'!AE54+'CD R Investigación'!AJ54+'CD R Investigación'!AO54+'CD R Investigación'!AT54+'CD R Investigación'!AY54 -> 12 | AA53: ='CD R Investigación'!S54+'CD R Investigación'!X54+'CD R Investigación'!AC54+'CD R Investigación'!AH54+'CD R Investigación'!AM54+'CD R Investigación'!AR54+'CD R Investigación'!AW54+'CD R Investigación'!BB54 -> 5.28 | AB53: =AC53/F53 -> #REF! | AC53: ='CD R Desarrollo'!P54+'CD R Desarrollo'!U54+'CD R Desarrollo'!Z54+'CD R Desarrollo'!AE54+'CD R Desarrollo'!AJ54+'CD R Desarrollo'!AO54+#REF!+#REF! -> #REF! | AD53: ='CD R Desarrollo'!S54+'CD R Desarrollo'!X54+'CD R Desarrollo'!AC54+'CD R Desarrollo'!AH54+'CD R Desarrollo'!AM54+'CD R Desarrollo'!AR54+#REF!+#REF! -> #REF! | AE53: 1 | AF53: ='PL Cronograma detallado'!L178*AE53 -> 1.88 | AG53: =AF53/'PL Cronograma detallado'!M$257 -> #DIV/0! | AH53: =SUM(AG53,AH52) -> #DIV/0!
A54: 3.2 | B54: Obtención de Datos para el Prototipo | C54: 44697 | D54: 44719 | E54: =_xludf.DAYs(D54,C54)+1 -> #NAME? | F54: =SUM(F55:F56) -> 42 | G54: =SUM(G55:G56) -> 0.047673099 | H54: =SUM(G54,H53) -> 0.37684449 | I54: =SUM(I55:I56) -> #REF! | J54: =SUM(I54,J51) -> #REF! | K54: =J54/$J$104 -> #REF! | L54: =SUM(L55:L56) -> #REF! | M54: =SUM(L54,M53) -> #REF! | P54: =M54/$M$93 -> #REF! | Q54: =R54/F54 -> 0 | R54: 0 | S54: L | T54: =IF(S54="L",0.68,IF(S54="JP",0.57,IF(S54="JI",0.57,IF(S54="JD",0.57,IF(S54="P",0.24,IF(S54="I",0.12,IF(S54="D",0.13))))))) -> 0.68 | U54: =T54*R54 -> 0 | V54: =W54/F54 -> #REF! | W54: ='CD R Documentación'!O55+'CD R Documentación'!T55+'CD R Documentación'!Y55+'CD R Documentación'!AD55+'CD R Documentación'!AI55+'CD R Documentación'!AN55+#REF! -> #REF! | X54: ='CD R Documentación'!R55+'CD R Documentación'!W55+'CD R Documentación'!AB55+'CD R Documentación'!AG55+'CD R Documentación'!AL55+'CD R Documentación'!AQ55+#REF! -> #REF! | Y54: =Z54/F54 -> 0.28571429 | Z54: ='CD R Investigación'!P55+'CD R Investigación'!U55+'CD R Investigación'!Z55+'CD R Investigación'!AE55+'CD R Investigación'!AJ55+'CD R Investigación'!AO55+'CD R Investigación'!AT55+'CD R Investigación'!AY55 -> 12 | AA54: ='CD R Investigación'!S55+'CD R Investigación'!X55+'CD R Investigación'!AC55+'CD R Investigación'!AH55+'CD R Investigación'!AM55+'CD R Investigación'!AR55+'CD R Investigación'!AW55+'CD R Investigación'!BB55 -> 5.28 | AB54: =AC54/F54 -> #REF! | AC54: ='CD R Desarrollo'!P55+'CD R Desarrollo'!U55+'CD R Desarrollo'!Z55+'CD R Desarrollo'!AE55+'CD R Desarrollo'!AJ55+'CD R Desarrollo'!AO55+#REF!+#REF! -> #REF! | AD54: ='CD R Desarrollo'!S55+'CD R Desarrollo'!X55+'CD R Desarrollo'!AC55+'CD R Desarrollo'!AH55+'CD R Desarrollo'!AM55+'CD R Desarrollo'!AR55+#REF!+#REF! -> #REF!
A55: 3.2.1 | B55: Grabación de Dataset | C55: 44696 | D55: 44709 | E55: =_xludf.DAYs(D55,C55)+1 -> #NAME? | F55: 30 | G55: =F55/F$105 -> 0.034052213 | H55: =SUM(H53,G55) -> 0.36322361 | I55: =SUM(R55,W55,Z55,AC55) -> #REF! | J55: =SUM(I55,J53) -> #REF! | K55: =J55/$J$104 -> #REF! | L55: =SUM(U55,X55,AA55,AD55) -> #REF! | M55: =SUM(L55,M53) -> #REF! | N55: =G55*AE55 -> 0.034052213 | O55: =SUM(N55,O53) -> 0.36208854 | P55: =M55/$M$93 -> #REF! | Q55: =R55/F55 -> 0 | R55: 0 | S55: L | T55: =IF(S55="L",0.68,IF(S55="JP",0.57,IF(S55="JI",0.57,IF(S55="JD",0.57,IF(S55="P",0.24,IF(S55="I",0.12,IF(S55="D",0.13))))))) -> 0.68 | U55: =T55*R55 -> 0 | V55: =W55/F55 -> #REF! | W55: ='CD R Documentación'!O56+'CD R Documentación'!T56+'CD R Documentación'!Y56+'CD R Documentación'!AD56+'CD R Documentación'!AI56+'CD R Documentación'!AN56+#REF! -> #REF! | X55: ='CD R Documentación'!R56+'CD R Documentación'!W56+'CD R Documentación'!AB56+'CD R Documentación'!AG56+'CD R Documentación'!AL56+'CD R Documentación'!AQ56+#REF! -> #REF! | Y55: =Z55/F55 -> 0 | Z55: ='CD R Investigación'!P56+'CD R Investigación'!U56+'CD R Investigación'!Z56+'CD R Investigación'!AE56+'CD R Investigación'!AJ56+'CD R Investigación'!AO56+'CD R Investigación'!AT56+'CD R Investigación'!AY56 -> 0 | AA55: ='CD R Investigación'!S56+'CD R Investigación'!X56+'CD R Investigación'!AC56+'CD R Investigación'!AH56+'CD R Investigación'!AM56+'CD R Investigación'!AR56+'CD R Investigación'!AW56+'CD R Investigación'!BB56 -> 0 | AB55: =AC55/F55 -> #REF! | AC55: ='CD R Desarrollo'!P56+'CD R Desarrollo'!U56+'CD R Desarrollo'!Z56+'CD R Desarrollo'!AE56+'CD R Desarrollo'!AJ56+'CD R Desarrollo'!AO56+#REF!+#REF! -> #REF! | AD55: ='CD R Desarrollo'!S56+'CD R Desarrollo'!X56+'CD R Desarrollo'!AC56+'CD R Desarrollo'!AH56+'CD R Desarrollo'!AM56+'CD R Desarrollo'!AR56+#REF!+#REF! -> #REF! | AE55: 1 | AF55: ='PL Cronograma detallado'!L181*AE55 -> 5.06 | AG55: =AF55/'PL Cronograma detallado'!M$257 -> #DIV/0! | AH55: =SUM(AG55,AH53) -> #DIV/0!
A56: 3.2.2 | B56: Adecuación del Dataset para el uso en Desarrollo (Parte 1) | C56: 44709 | D56: 44711 | E56: =_xludf.DAYs(D56,C56)+1 -> #NAME? | F56: 12 | G56: =F56/F$105 -> 0.013620885 | H56: =SUM(H55,G56) -> 0.37684449 | I56: =SUM(R56,W56,Z56,AC56) -> #REF! | J56: =SUM(I56,J55) -> #REF! | K56: =J56/$J$104 -> #REF! | L56: =SUM(U56,X56,AA56,AD56) -> #REF! | M56: =SUM(L56,M55) -> #REF! | N56: =G56*AE56 -> 0.013620885 | O56: =SUM(N56,O55) -> 0.37570942 | P56: =M56/$M$93 -> #REF! | Q56: =R56/F56 -> 0.083333333 | R56: 1 | S56: L | T56: =IF(S56="L",0.68,IF(S56="JP",0.57,IF(S56="JI",0.57,IF(S56="JD",0.57,IF(S56="P",0.24,IF(S56="I",0.12,IF(S56="D",0.13))))))) -> 0.68 | U56: =T56*R56 -> 0.68 | V56: =W56/F56 -> #REF! | W56: ='CD R Documentación'!O57+'CD R Documentación'!T57+'CD R Documentación'!Y57+'CD R Documentación'!AD57+'CD R Documentación'!AI57+'CD R Documentación'!AN57+#REF! -> #REF! | X56: ='CD R Documentación'!R57+'CD R Documentación'!W57+'CD R Documentación'!AB57+'CD R Documentación'!AG57+'CD R Documentación'!AL57+'CD R Documentación'!AQ57+#REF! -> #REF! | Y56: =Z56/F56 -> 0 | Z56: ='CD R Investigación'!P57+'CD R Investigación'!U57+'CD R Investigación'!Z57+'CD R Investigación'!AE57+'CD R Investigación'!AJ57+'CD R Investigación'!AO57+'CD R Investigación'!AT57+'CD R Investigación'!AY57 -> 0 | AA56: ='CD R Investigación'!S57+'CD R Investigación'!X57+'CD R Investigación'!AC57+'CD R Investigación'!AH57+'CD R Investigación'!AM57+'CD R Investigación'!AR57+'CD R Investigación'!AW57+'CD R Investigación'!BB57 -> 0 | AB56: =AC56/F56 -> #REF! | AC56: ='CD R Desarrollo'!P57+'CD R Desarrollo'!U57+'CD R Desarrollo'!Z57+'CD R Desarrollo'!AE57+'CD R Desarrollo'!AJ57+'CD R Desarrollo'!AO57+#REF!+#REF! -> #REF! | AD56: ='CD R Desarrollo'!S57+'CD R Desarrollo'!X57+'CD R Desarrollo'!AC57+'CD R Desarrollo'!AH57+'CD R Desarrollo'!AM57+'CD R Desarrollo'!AR57+#REF!+#REF! -> #REF! | AE56: 1 | AF56: ='PL Cronograma detallado'!L184*AE56 -> 2.49 | AG56: =AF56/'PL Cronograma detallado'!M$257 -> #DIV/0! | AH56: =SUM(AG56,AH55) -> #DIV/0!
A57: 3.3 | B57: Creación y Entrenamiento de Red Neuronal | C57: 44697 | D57: 44711 | E57: =_xludf.DAYs(D57,C57)+1 -> #NAME? | F57: =SUM(F58:F63) -> 60 | G57: =SUM(G58:G63) -> 0.068104427 | H57: =SUM(G57,H56) -> 0.44494892 | I57: =SUM(I58:I63) -> #REF! | J57: =SUM(I57,J54) -> #REF! | K57: =J57/$J$104 -> #REF! | L57: =SUM(L58:L63) -> #REF! | M57: =SUM(L57,M56) -> #REF! | O57: =AH57 | P57: =M57/$M$93 -> #REF! | Q57: =R57/F57 -> 0 | R57: 0 | S57: L | T57: =IF(S57="L",0.68,IF(S57="JP",0.57,IF(S57="JI",0.57,IF(S57="JD",0.57,IF(S57="P",0.24,IF(S57="I",0.12,IF(S57="D",0.13))))))) -> 0.68 | U57: =T57*R57 -> 0 | V57: =W57/F57 -> #REF! | W57: ='CD R Documentación'!O58+'CD R Documentación'!T58+'CD R Documentación'!Y58+'CD R Documentación'!AD58+'CD R Documentación'!AI58+'CD R Documentación'!AN58+#REF! -> #REF! | X57: ='CD R Documentación'!R58+'CD R Documentación'!W58+'CD R Documentación'!AB58+'CD R Documentación'!AG58+'CD R Documentación'!AL58+'CD R Documentación'!AQ58+#REF! -> #REF! | Y57: =Z57/F57 -> 0 | Z57: ='CD R Investigación'!P58+'CD R Investigación'!U58+'CD R Investigación'!Z58+'CD R Investigación'!AE58+'CD R Investigación'!AJ58+'CD R Investigación'!AO58+'CD R Investigación'!AT58+'CD R Investigación'!AY58 -> 0 | AA57: ='CD R Investigación'!S58+'CD R Investigación'!X58+'CD R Investigación'!AC58+'CD R Investigación'!AH58+'CD R Investigación'!AM58+'CD R Investigación'!AR58+'CD R Investigación'!AW58+'CD R Investigación'!BB58 -> 0 | AB57: =AC57/F57 -> #REF! | AC57: ='CD R Desarrollo'!P58+'CD R Desarrollo'!U58+'CD R Desarrollo'!Z58+'CD R Desarrollo'!AE58+'CD R Desarrollo'!AJ58+'CD R Desarrollo'!AO58+#REF!+#REF! -> #REF! | AD57: ='CD R Desarrollo'!S58+'CD R Desarrollo'!X58+'CD R Desarrollo'!AC58+'CD R Desarrollo'!AH58+'CD R Desarrollo'!AM58+'CD R Desarrollo'!AR58+#REF!+#REF! -> #REF!
A58: 3.3.1 | B58: Creación de Red Neuronal | C58: 44697 | D58: 44709 | E58: =_xludf.DAYs(D58,C58)+1 -> #NAME? | F58: 30 | G58: =F58/F$105 -> 0.034052213 | H58: =SUM(H56,G58) -> 0.41089671 | I58: =SUM(R58,W58,Z58,AC58) -> #REF! | J58: =SUM(I58,J56) -> #REF! | K58: =J58/$J$104 -> #REF! | L58: =SUM(U58,X58,AA58,AD58) -> #REF! | M58: =SUM(L58,M56) -> #REF! | N58: =G58*AE58 -> 0.034052213 | O58: =SUM(N58,O56) -> 0.40976163 | P58: =M58/$M$93 -> #REF! | Q58: =R58/F58 -> 0 | R58: 0 | S58: L | T58: =IF(S58="L",0.68,IF(S58="JP",0.57,IF(S58="JI",0.57,IF(S58="JD",0.57,IF(S58="P",0.24,IF(S58="I",0.12,IF(S58="D",0.13))))))) -> 0.68 | U58: =T58*R58 -> 0 | V58: =W58/F58 -> #REF! | W58: ='CD R Documentación'!O59+'CD R Documentación'!T59+'CD R Documentación'!Y59+'CD R Documentación'!AD59+'CD R Documentación'!AI59+'CD R Documentación'!AN59+#REF! -> #REF! | X58: ='CD R Documentación'!R59+'CD R Documentación'!W59+'CD R Documentación'!AB59+'CD R Documentación'!AG59+'CD R Documentación'!AL59+'CD R Documentación'!AQ59+#REF! -> #REF! | Y58: =Z58/F58 -> 1.2666667 | Z58: ='CD R Investigación'!P59+'CD R Investigación'!U59+'CD R Investigación'!Z59+'CD R Investigación'!AE59+'CD R Investigación'!AJ59+'CD R Investigación'!AO59+'CD R Investigación'!AT59+'CD R Investigación'!AY59 -> 38 | AA58: ='CD R Investigación'!S59+'CD R Investigación'!X59+'CD R Investigación'!AC59+'CD R Investigación'!AH59+'CD R Investigación'!AM59+'CD R Investigación'!AR59+'CD R Investigación'!AW59+'CD R Investigación'!BB59 -> 16.72 | AB58: =AC58/F58 -> #REF! | AC58: ='CD R Desarrollo'!P59+'CD R Desarrollo'!U59+'CD R Desarrollo'!Z59+'CD R Desarrollo'!AE59+'CD R Desarrollo'!AJ59+'CD R Desarrollo'!AO59+#REF!+#REF! -> #REF! | AD58: ='CD R Desarrollo'!S59+'CD R Desarrollo'!X59+'CD R Desarrollo'!AC59+'CD R Desarrollo'!AH59+'CD R Desarrollo'!AM59+'CD R Desarrollo'!AR59+#REF!+#REF! -> #REF! | AE58: 1 | AF58: ='PL Cronograma detallado'!L186*AE58 -> 63.59 | AG58: =AF58/'PL Cronograma detallado'!M$257 -> #DIV/0! | AH58: =SUM(AG58,AH56) -> #DIV/0!
A59: 3.3.2 | B59: Reunion de Lideres 7 | C59: 44703 | D59: 44703 | E59: =_xludf.DAYs(D59,C59)+1 -> #NAME? | F59: 1 | G59: =F59/F$105 -> 0.0011350738 | H59: =SUM(H58,G59) -> 0.41203178 | I59: =SUM(R59,W59,Z59,AC59) -> #REF! | J59: =SUM(I59,J58) -> #REF! | K59: =J59/$J$104 -> #REF! | L59: =SUM(U59,X59,AA59,AD59) -> #REF! | M59: =SUM(L59,M58) -> #REF! | N59: =G59*AE59 -> 0.0011350738 | O59: =SUM(N59,O58) -> 0.41089671 | P59: =M59/$M$93 -> #REF! | Q59: =R59/F59 -> 1 | R59: 1 | S59: L | T59: =IF(S59="L",0.68,IF(S59="JP",0.57,IF(S59="JI",0.57,IF(S59="JD",0.57,IF(S59="P",0.24,IF(S59="I",0.12,IF(S59="D",0.13))))))) -> 0.68 | U59: =T59*R59 -> 0.68 | V59: =W59/F59 -> #REF! | W59: ='CD R Documentación'!O60+'CD R Documentación'!T60+'CD R Documentación'!Y60+'CD R Documentación'!AD60+'CD R Documentación'!AI60+'CD R Documentación'!AN60+#REF! -> #REF! | X59: ='CD R Documentación'!R60+'CD R Documentación'!W60+'CD R Documentación'!AB60+'CD R Documentación'!AG60+'CD R Documentación'!AL60+'CD R Documentación'!AQ60+#REF! -> #REF! | Y59: =Z59/F59 -> 38 | Z59: ='CD R Investigación'!P60+'CD R Investigación'!U60+'CD R Investigación'!Z60+'CD R Investigación'!AE60+'CD R Investigación'!AJ60+'CD R Investigación'!AO60+'CD R Investigación'!AT60+'CD R Investigación'!AY60 -> 38 | AA59: ='CD R Investigación'!S60+'CD R Investigación'!X60+'CD R Investigación'!AC60+'CD R Investigación'!AH60+'CD R Investigación'!AM60+'CD R Investigación'!AR60+'CD R Investigación'!AW60+'CD R Investigación'!BB60 -> 16.72 | AB59: =AC59/F59 -> #REF! | AC59: ='CD R Desarrollo'!P60+'CD R Desarrollo'!U60+'CD R Desarrollo'!Z60+'CD R Desarrollo'!AE60+'CD R Desarrollo'!AJ60+'CD R Desarrollo'!AO60+#REF!+#REF! -> #REF! | AD59: ='CD R Desarrollo'!S60+'CD R Desarrollo'!X60+'CD R Desarrollo'!AC60+'CD R Desarrollo'!AH60+'CD R Desarrollo'!AM60+'CD R Desarrollo'!AR60+#REF!+#REF! -> #REF! | AE59: 1 | AF59: ='PL Cronograma detallado'!L194*AE59 -> 15.65 | AG59: =AF59/'PL Cronograma detallado'!M$257 -> #DIV/0! | AH59: =SUM(AG59,AH58) -> #DIV/0!
A60: 3.3.3 | B60: Entrenamiento de Red Neuronal (Parte 1) | C60: 44709 | D60: 44711 | E60: =_xludf.DAYs(D60,C60)+1 -> #NAME? | F60: 12 | G60: =F60/F$105 -> 0.013620885 | H60: =SUM(H59,G60) -> 0.42565267 | I60: =SUM(R60,W60,Z60,AC60) -> #REF! | J60: =SUM(I60,J59) -> #REF! | K60: =J60/$J$104 -> #REF! | L60: =SUM(U60,X60,AA60,AD60) -> #REF! | M60: =SUM(L60,M59) -> #REF! | N60: =G60*AE60 -> 0.013620885 | O60: =SUM(N60,O59) -> 0.42451759 | P60: =M60/$M$93 -> #REF! | Q60: =R60/F60 -> 0 | R60: 0 | S60: L | T60: =IF(S60="L",0.68,IF(S60="JP",0.57,IF(S60="JI",0.57,IF(S60="JD",0.57,IF(S60="P",0.24,IF(S60="I",0.12,IF(S60="D",0.13))))))) -> 0.68 | U60: =T60*R60 -> 0 | V60: =W60/F60 -> #REF! | W60: ='CD R Documentación'!O61+'CD R Documentación'!T61+'CD R Documentación'!Y61+'CD R Documentación'!AD61+'CD R Documentación'!AI61+'CD R Documentación'!AN61+#REF! -> #REF! | X60: ='CD R Documentación'!R61+'CD R Documentación'!W61+'CD R Documentación'!AB61+'CD R Documentación'!AG61+'CD R Documentación'!AL61+'CD R Documentación'!AQ61+#REF! -> #REF! | Y60: =Z60/F60 -> 0.16666667 | Z60: ='CD R Investigación'!P61+'CD R Investigación'!U61+'CD R Investigación'!Z61+'CD R Investigación'!AE61+'CD R Investigación'!AJ61+'CD R Investigación'!AO61+'CD R Investigación'!AT61+'CD R Investigación'!AY61 -> 2 | AA60: ='CD R Investigación'!S61+'CD R Investigación'!X61+'CD R Investigación'!AC61+'CD R Investigación'!AH61+'CD R Investigación'!AM61+'CD R Investigación'!AR61+'CD R Investigación'!AW61+'CD R Investigación'!BB61 -> 0.88 | AB60: =AC60/F60 -> #REF! | AC60: ='CD R Desarrollo'!P61+'CD R Desarrollo'!U61+'CD R Desarrollo'!Z61+'CD R Desarrollo'!AE61+'CD R Desarrollo'!AJ61+'CD R Desarrollo'!AO61+#REF!+#REF! -> #REF! | AD60: ='CD R Desarrollo'!S61+'CD R Desarrollo'!X61+'CD R Desarrollo'!AC61+'CD R Desarrollo'!AH61+'CD R Desarrollo'!AM61+'CD R Desarrollo'!AR61+#REF!+#REF! -> #REF! | AE60: 1 | AF60: ='PL Cronograma detallado'!L195*AE60 -> 6.86 | AG60: =AF60/'PL Cronograma detallado'!M$257 -> #DIV/0! | AH60: =SUM(AG60,AH59) -> #DIV/0!
A61: 3.3.4 | B61: Reunión de Líderes 8 | C61: 44710 | D61: 44710 | E61: =_xludf.DAYs(D61,C61)+1 -> #NAME? | F61: 1 | G61: =F61/F$105 -> 0.0011350738 | H61: =SUM(H60,G61) -> 0.42678774 | I61: =SUM(R61,W61,Z61,AC61) -> #REF! | J61: =SUM(I61,J60) -> #REF! | K61: =J61/$J$104 -> #REF! | L61: =SUM(U61,X61,AA61,AD61) -> #REF! | M61: =SUM(L61,M60) -> #REF! | N61: =G61*AE61 -> 0.0011350738 | O61: =SUM(N61,O60) -> 0.42565267 | P61: =M61/$M$93 -> #REF! | Q61: =R61/F61 -> 1 | R61: 1 | S61: L | T61: =IF(S61="L",0.68,IF(S61="JP",0.57,IF(S61="JI",0.57,IF(S61="JD",0.57,IF(S61="P",0.24,IF(S61="I",0.12,IF(S61="D",0.13))))))) -> 0.68 | U61: =T61*R61 -> 0.68 | V61: =W61/F61 -> #REF! | W61: ='CD R Documentación'!O62+'CD R Documentación'!T62+'CD R Documentación'!Y62+'CD R Documentación'!AD62+'CD R Documentación'!AI62+'CD R Documentación'!AN62+#REF! -> #REF! | X61: ='CD R Documentación'!R62+'CD R Documentación'!W62+'CD R Documentación'!AB62+'CD R Documentación'!AG62+'CD R Documentación'!AL62+'CD R Documentación'!AQ62+#REF! -> #REF! | Y61: =Z61/F61 -> 0 | Z61: ='CD R Investigación'!P62+'CD R Investigación'!U62+'CD R Investigación'!Z62+'CD R Investigación'!AE62+'CD R Investigación'!AJ62+'CD R Investigación'!AO62+'CD R Investigación'!AT62+'CD R Investigación'!AY62 -> 0 | AA61: ='CD R Investigación'!S62+'CD R Investigación'!X62+'CD R Investigación'!AC62+'CD R Investigación'!AH62+'CD R Investigación'!AM62+'CD R Investigación'!AR62+'CD R Investigación'!AW62+'CD R Investigación'!BB62 -> 0 | AB61: =AC61/F61 -> #REF! | AC61: ='CD R Desarrollo'!P62+'CD R Desarrollo'!U62+'CD R Desarrollo'!Z62+'CD R Desarrollo'!AE62+'CD R Desarrollo'!AJ62+'CD R Desarrollo'!AO62+#REF!+#REF! -> #REF! | AD61: ='CD R Desarrollo'!S62+'CD R Desarrollo'!X62+'CD R Desarrollo'!AC62+'CD R Desarrollo'!AH62+'CD R Desarrollo'!AM62+'CD R Desarrollo'!AR62+#REF!+#REF! -> #REF! | AE61: 1 | AF61: ='PL Cronograma detallado'!L197*AE61 -> 6.86 | AG61: =AF61/'PL Cronograma detallado'!M$257 -> #DIV/0! | AH61: =SUM(AG61,AH60) -> #DIV/0!
A62: 3.4 | B62: Elaboración Informe de Avance N°2 | C62: 44704 | D62: 44711 | E62: =_xludf.DAYs(D62,C62)+1 -> #NAME? | F62: 15 | G62: =(F62/F105) -> 0.017026107 | H62: =SUM(H61,G62) -> 0.44381385 | I62: =SUM(R62,W62,Z62,AC62) -> #REF! | J62: =SUM(I62,J61) -> #REF! | K62: =J62/$J$104 -> #REF! | L62: =SUM(U62,X62,AA62,AD62) -> #REF! | M62: =SUM(L62,M61) -> #REF! | N62: =G62*AE62 -> 0.017026107 | O62: =SUM(N62,O61) -> 0.44267877 | P62: =M62/$M$93 -> #REF! | Q62: =R62/F62 -> 0.26666667 | R62: 4 | S62: L | T62: =IF(S62="L",0.68,IF(S62="JP",0.57,IF(S62="JI",0.57,IF(S62="JD",0.57,IF(S62="P",0.24,IF(S62="I",0.12,IF(S62="D",0.13))))))) -> 0.68 | U62: =T62*R62 -> 2.72 | V62: =W62/F62 -> #REF! | W62: ='CD R Documentación'!O63+'CD R Documentación'!T63+'CD R Documentación'!Y63+'CD R Documentación'!AD63+'CD R Documentación'!AI63+'CD R Documentación'!AN63+#REF! -> #REF! | X62: ='CD R Documentación'!R63+'CD R Documentación'!W63+'CD R Documentación'!AB63+'CD R Documentación'!AG63+'CD R Documentación'!AL63+'CD R Documentación'!AQ63+#REF! -> #REF! | Y62: =Z62/F62 -> 1.3333333 | Z62: ='CD R Investigación'!P63+'CD R Investigación'!U63+'CD R Investigación'!Z63+'CD R Investigación'!AE63+'CD R Investigación'!AJ63+'CD R Investigación'!AO63+'CD R Investigación'!AT63+'CD R Investigación'!AY63 -> 20 | AA62: ='CD R Investigación'!S63+'CD R Investigación'!X63+'CD R Investigación'!AC63+'CD R Investigación'!AH63+'CD R Investigación'!AM63+'CD R Investigación'!AR63+'CD R Investigación'!AW63+'CD R Investigación'!BB63 -> 8.8 | AB62: =AC62/F62 -> #REF! | AC62: ='CD R Desarrollo'!P63+'CD R Desarrollo'!U63+'CD R Desarrollo'!Z63+'CD R Desarrollo'!AE63+'CD R Desarrollo'!AJ63+'CD R Desarrollo'!AO63+#REF!+#REF! -> #REF! | AD62: ='CD R Desarrollo'!S63+'CD R Desarrollo'!X63+'CD R Desarrollo'!AC63+'CD R Desarrollo'!AH63+'CD R Desarrollo'!AM63+'CD R Desarrollo'!AR63+#REF!+#REF! -> #REF! | AE62: 1 | AF62: ='PL Cronograma detallado'!L198*AE62 -> 15.65 | AG62: =AF62/'PL Cronograma detallado'!M$257 -> #DIV/0! | AH62: =SUM(AG62,AH61) -> #DIV/0!
A63: H3 | B63: Entrega de Avance N°2 y Defensa | C63: 44712 | D63: 44712 | E63: =_xludf.DAYs(D63,C63)+1 -> #NAME? | F63: 1 | G63: =(F63/F105) -> 0.0011350738 | H63: =SUM(H62,G63) -> 0.44494892 | I63: =SUM(R63,W63,Z63,AC63) -> #REF! | J63: =SUM(I63,J62) -> #REF! | K63: =J63/$J$104 -> #REF! | L63: =SUM(U63,X63,AA63,AD63) -> #REF! | M63: =SUM(L63,M62) -> #REF! | N63: =G63*AE63 -> 0.0011350738 | O63: =SUM(N63,O62) -> 0.44381385 | P63: =M63/$M$93 -> #REF! | Q63: =R63/F63 -> 1 | R63: 1 | S63: L | T63: =IF(S63="L",0.68,IF(S63="JP",0.57,IF(S63="JI",0.57,IF(S63="JD",0.57,IF(S63="P",0.24,IF(S63="I",0.12,IF(S63="D",0.13))))))) -> 0.68 | U63: =T63*R63 -> 0.68 | V63: =W63/F63 -> #REF! | W63: ='CD R Documentación'!O64+'CD R Documentación'!T64+'CD R Documentación'!Y64+'CD R Documentación'!AD64+'CD R Documentación'!AI64+'CD R Documentación'!AN64+#REF! -> #REF! | X63: ='CD R Documentación'!R64+'CD R Documentación'!W64+'CD R Documentación'!AB64+'CD R Documentación'!AG64+'CD R Documentación'!AL64+'CD R Documentación'!AQ64+#REF! -> #REF! | Y63: =Z63/F63 -> 20 | Z63: ='CD R Investigación'!P64+'CD R Investigación'!U64+'CD R Investigación'!Z64+'CD R Investigación'!AE64+'CD R Investigación'!AJ64+'CD R Investigación'!AO64+'CD R Investigación'!AT64+'CD R Investigación'!AY64 -> 20 | AA63: ='CD R Investigación'!S64+'CD R Investigación'!X64+'CD R Investigación'!AC64+'CD R Investigación'!AH64+'CD R Investigación'!AM64+'CD R Investigación'!AR64+'CD R Investigación'!AW64+'CD R Investigación'!BB64 -> 8.8 | AB63: =AC63/F63 -> #REF! | AC63: ='CD R Desarrollo'!P64+'CD R Desarrollo'!U64+'CD R Desarrollo'!Z64+'CD R Desarrollo'!AE64+'CD R Desarrollo'!AJ64+'CD R Desarrollo'!AO64+#REF!+#REF! -> #REF! | AD63: ='CD R Desarrollo'!S64+'CD R Desarrollo'!X64+'CD R Desarrollo'!AC64+'CD R Desarrollo'!AH64+'CD R Desarrollo'!AM64+'CD R Desarrollo'!AR64+#REF!+#REF! -> #REF! | AE63: 1 | AF63: ='PL Cronograma detallado'!L200*AE63 -> 6.86 | AG63: =AF63/'PL Cronograma detallado'!M$257 -> #DIV/0! | AH63: =SUM(AG63,AH62) -> #DIV/0!
A64: 3.5 | B64: Construcción de Prototipo | C64: 44713 | D64: 44725 | E64: =_xludf.DAYs(D64,C64)+1 -> #NAME? | F64: =SUM(F65:F73) -> 124 | G64: =SUM(G65:G73) -> 0.14074915 | H64: =SUM(G64,H63) -> 0.58569807 | I64: =SUM(I65:I73) -> #REF! | J64: =SUM(I64,J57) -> #REF! | K64: =J64/$J$104 -> #REF! | L64: =SUM(L65:L73) -> #REF! | M64: =SUM(L64,M63) -> #REF! | O64: =AH64 | P64: =M64/$M$93 -> #REF! | Q64: =R64/F64 -> 0 | R64: 0 | S64: L | T64: =IF(S64="L",0.68,IF(S64="JP",0.57,IF(S64="JI",0.57,IF(S64="JD",0.57,IF(S64="P",0.24,IF(S64="I",0.12,IF(S64="D",0.13))))))) -> 0.68 | U64: =T64*R64 -> 0 | V64: =W64/F64 -> #REF! | W64: ='CD R Documentación'!O65+'CD R Documentación'!T65+'CD R Documentación'!Y65+'CD R Documentación'!AD65+'CD R Documentación'!AI65+'CD R Documentación'!AN65+#REF! -> #REF! | X64: ='CD R Documentación'!R65+'CD R Documentación'!W65+'CD R Documentación'!AB65+'CD R Documentación'!AG65+'CD R Documentación'!AL65+'CD R Documentación'!AQ65+#REF! -> #REF! | Y64: =Z64/F64 -> 0.024193548 | Z64: ='CD R Investigación'!P65+'CD R Investigación'!U65+'CD R Investigación'!Z65+'CD R Investigación'!AE65+'CD R Investigación'!AJ65+'CD R Investigación'!AO65+'CD R Investigación'!AT65+'CD R Investigación'!AY65 -> 3 | AA64: ='CD R Investigación'!S65+'CD R Investigación'!X65+'CD R Investigación'!AC65+'CD R Investigación'!AH65+'CD R Investigación'!AM65+'CD R Investigación'!AR65+'CD R Investigación'!AW65+'CD R Investigación'!BB65 -> 1.32 | AB64: =AC64/F64 -> #REF! | AC64: ='CD R Desarrollo'!P65+'CD R Desarrollo'!U65+'CD R Desarrollo'!Z65+'CD R Desarrollo'!AE65+'CD R Desarrollo'!AJ65+'CD R Desarrollo'!AO65+#REF!+#REF! -> #REF! | AD64: ='CD R Desarrollo'!S65+'CD R Desarrollo'!X65+'CD R Desarrollo'!AC65+'CD R Desarrollo'!AH65+'CD R Desarrollo'!AM65+'CD R Desarrollo'!AR65+#REF!+#REF! -> #REF!
A65: 3.5.1 | B65: Preparación de entorno de Desarrollo | C65: 44713 | D65: 44716 | E65: =_xludf.DAYs(D65,C65)+1 -> #NAME? | F65: 12 | G65: =F65/F$105 -> 0.013620885 | H65: =SUM(H63,G65) -> 0.45856981 | I65: =SUM(R65,W65,Z65,AC65) -> #REF! | J65: =SUM(I65,J63) -> #REF! | K65: =J65/$J$104 -> #REF! | L65: =SUM(U65,X65,AA65,AD65) -> #REF! | M65: =SUM(L65,M63) -> #REF! | N65: =G65*AE65 -> 0.013620885 | O65: =SUM(N65,O63) -> 0.45743473 | P65: =M65/$M$93 -> #REF! | Q65: =R65/F65 -> 0 | R65: 0 | S65: L | T65: =IF(S65="L",0.68,IF(S65="JP",0.57,IF(S65="JI",0.57,IF(S65="JD",0.57,IF(S65="P",0.24,IF(S65="I",0.12,IF(S65="D",0.13))))))) -> 0.68 | U65: =T65*R65 -> 0 | V65: =W65/F65 -> #REF! | W65: ='CD R Documentación'!O66+'CD R Documentación'!T66+'CD R Documentación'!Y66+'CD R Documentación'!AD66+'CD R Documentación'!AI66+'CD R Documentación'!AN66+#REF! -> #REF! | X65: ='CD R Documentación'!R66+'CD R Documentación'!W66+'CD R Documentación'!AB66+'CD R Documentación'!AG66+'CD R Documentación'!AL66+'CD R Documentación'!AQ66+#REF! -> #REF! | Y65: =Z65/F65 -> 0 | Z65: ='CD R Investigación'!P66+'CD R Investigación'!U66+'CD R Investigación'!Z66+'CD R Investigación'!AE66+'CD R Investigación'!AJ66+'CD R Investigación'!AO66+'CD R Investigación'!AT66+'CD R Investigación'!AY66 -> 0 | AA65: ='CD R Investigación'!S66+'CD R Investigación'!X66+'CD R Investigación'!AC66+'CD R Investigación'!AH66+'CD R Investigación'!AM66+'CD R Investigación'!AR66+'CD R Investigación'!AW66+'CD R Investigación'!BB66 -> 0 | AB65: =AC65/F65 -> #REF! | AC65: ='CD R Desarrollo'!P66+'CD R Desarrollo'!U66+'CD R Desarrollo'!Z66+'CD R Desarrollo'!AE66+'CD R Desarrollo'!AJ66+'CD R Desarrollo'!AO66+#REF!+#REF! -> #REF! | AD65: ='CD R Desarrollo'!S66+'CD R Desarrollo'!X66+'CD R Desarrollo'!AC66+'CD R Desarrollo'!AH66+'CD R Desarrollo'!AM66+'CD R Desarrollo'!AR66+#REF!+#REF! -> #REF! | AE65: 1 | AF65: ='PL Cronograma detallado'!L202*AE65 -> 9.4 | AG65: =AF65/'PL Cronograma detallado'!M$257 -> #DIV/0! | AH65: =SUM(AG65,AH63) -> #DIV/0!
A66: 3.5.2 | B66: Adecuación del Dataset para el uso en Desarrollo (parte 2) | C66: 44713 | D66: 44719 | E66: =_xludf.DAYs(D66,C66)+1 -> #NAME? | F66: 14 | G66: =F66/F$105 -> 0.015891033 | H66: =SUM(H65,G66) -> 0.47446084 | I66: =SUM(R66,W66,Z66,AC66) -> #REF! | J66: =SUM(I66,J65) -> #REF! | K66: =J66/$J$104 -> #REF! | L66: =SUM(U66,X66,AA66,AD66) -> #REF! | M66: =SUM(L66,M65) -> #REF! | N66: =G66*AE66 -> 0.015891033 | O66: =SUM(N66,O65) -> 0.47332577 | P66: =M66/$M$93 -> #REF! | Q66: =R66/F66 -> 0.14285714 | R66: 2 | S66: L | T66: =IF(S66="L",0.68,IF(S66="JP",0.57,IF(S66="JI",0.57,IF(S66="JD",0.57,IF(S66="P",0.24,IF(S66="I",0.12,IF(S66="D",0.13))))))) -> 0.68 | U66: =T66*R66 -> 1.36 | V66: =W66/F66 -> #REF! | W66: ='CD R Documentación'!O67+'CD R Documentación'!T67+'CD R Documentación'!Y67+'CD R Documentación'!AD67+'CD R Documentación'!AI67+'CD R Documentación'!AN67+#REF! -> #REF! | X66: ='CD R Documentación'!R67+'CD R Documentación'!W67+'CD R Documentación'!AB67+'CD R Documentación'!AG67+'CD R Documentación'!AL67+'CD R Documentación'!AQ67+#REF! -> #REF! | Y66: =Z66/F66 -> 0.071428571 | Z66: ='CD R Investigación'!P67+'CD R Investigación'!U67+'CD R Investigación'!Z67+'CD R Investigación'!AE67+'CD R Investigación'!AJ67+'CD R Investigación'!AO67+'CD R Investigación'!AT67+'CD R Investigación'!AY67 -> 1 | AA66: ='CD R Investigación'!S67+'CD R Investigación'!X67+'CD R Investigación'!AC67+'CD R Investigación'!AH67+'CD R Investigación'!AM67+'CD R Investigación'!AR67+'CD R Investigación'!AW67+'CD R Investigación'!BB67 -> 0.44 | AB66: =AC66/F66 -> #REF! | AC66: ='CD R Desarrollo'!P67+'CD R Desarrollo'!U67+'CD R Desarrollo'!Z67+'CD R Desarrollo'!AE67+'CD R Desarrollo'!AJ67+'CD R Desarrollo'!AO67+#REF!+#REF! -> #REF! | AD66: ='CD R Desarrollo'!S67+'CD R Desarrollo'!X67+'CD R Desarrollo'!AC67+'CD R Desarrollo'!AH67+'CD R Desarrollo'!AM67+'CD R Desarrollo'!AR67+#REF!+#REF! -> #REF! | AE66: 1 | AF66: ='PL Cronograma detallado'!L204*AE66 -> 4.98 | AG66: =AF66/'PL Cronograma detallado'!M$257 -> #DIV/0! | AH66: =SUM(AG66,AH65) -> #DIV/0!
A67: 3.5.3 | B67: Entrenamiento de Red Neuronal (Parte 2) | C67: 44713 | D67: 44719 | E67: =_xludf.DAYs(D67,C67)+1 -> #NAME? | F67: 21 | G67: =F67/F$105 -> 0.023836549 | H67: =SUM(H66,G67) -> 0.49829739 | I67: =SUM(R67,W67,Z67,AC67) -> #REF! | J67: =SUM(I67,J66) -> #REF! | K67: =J67/$J$104 -> #REF! | L67: =SUM(U67,X67,AA67,AD67) -> #REF! | M67: =SUM(L67,M66) -> #REF! | N67: =G67*AE67 -> 0.023836549 | O67: =SUM(N67,O66) -> 0.49716232 | P67: =M67/$M$93 -> #REF! | Q67: =R67/F67 -> 0 | R67: 0 | S67: L | T67: =IF(S67="L",0.68,IF(S67="JP",0.57,IF(S67="JI",0.57,IF(S67="JD",0.57,IF(S67="P",0.24,IF(S67="I",0.12,IF(S67="D",0.13))))))) -> 0.68 | U67: =T67*R67 -> 0 | V67: =W67/F67 -> #REF! | W67: ='CD R Documentación'!O68+'CD R Documentación'!T68+'CD R Documentación'!Y68+'CD R Documentación'!AD68+'CD R Documentación'!AI68+'CD R Documentación'!AN68+#REF! -> #REF! | X67: ='CD R Documentación'!R68+'CD R Documentación'!W68+'CD R Documentación'!AB68+'CD R Documentación'!AG68+'CD R Documentación'!AL68+'CD R Documentación'!AQ68+#REF! -> #REF! | Y67: =Z67/F67 -> 0 | Z67: ='CD R Investigación'!P68+'CD R Investigación'!U68+'CD R Investigación'!Z68+'CD R Investigación'!AE68+'CD R Investigación'!AJ68+'CD R Investigación'!AO68+'CD R Investigación'!AT68+'CD R Investigación'!AY68 -> 0 | AA67: ='CD R Investigación'!S68+'CD R Investigación'!X68+'CD R Investigación'!AC68+'CD R Investigación'!AH68+'CD R Investigación'!AM68+'CD R Investigación'!AR68+'CD R Investigación'!AW68+'CD R Investigación'!BB68 -> 0 | AB67: =AC67/F67 -> #REF! | AC67: ='CD R Desarrollo'!P68+'CD R Desarrollo'!U68+'CD R Desarrollo'!Z68+'CD R Desarrollo'!AE68+'CD R Desarrollo'!AJ68+'CD R Desarrollo'!AO68+#REF!+#REF! -> #REF! | AD67: ='CD R Desarrollo'!S68+'CD R Desarrollo'!X68+'CD R Desarrollo'!AC68+'CD R Desarrollo'!AH68+'CD R Desarrollo'!AM68+'CD R Desarrollo'!AR68+#REF!+#REF! -> #REF! | AE67: 1 | AF67: ='PL Cronograma detallado'!L205*AE67 -> 2.49 | AG67: =AF67/'PL Cronograma detallado'!M$257 -> #DIV/0! | AH67: =SUM(AG67,AH66) -> #DIV/0!
A68: 3.5.4 | B68: Desarrollo del Prototipo (parte 1) | C68: 44715 | D68: 44725 | E68: =_xludf.DAYs(D68,C68)+1 -> #NAME? | F68: 40 | G68: =F68/F$105 -> 0.045402951 | H68: =SUM(H67,G68) -> 0.54370034 | I68: =SUM(R68,W68,Z68,AC68) -> #REF! | J68: =SUM(I68,J67) -> #REF! | K68: =J68/$J$104 -> #REF! | L68: =SUM(U68,X68,AA68,AD68) -> #REF! | M68: =SUM(L68,M67) -> #REF! | N68: =G68*AE68 -> 0.045402951 | O68: =SUM(N68,O67) -> 0.54256527 | P68: =M68/$M$93 -> #REF! | Q68: =R68/F68 -> 0 | R68: 0 | S68: L | T68: =IF(S68="L",0.68,IF(S68="JP",0.57,IF(S68="JI",0.57,IF(S68="JD",0.57,IF(S68="P",0.24,IF(S68="I",0.12,IF(S68="D",0.13))))))) -> 0.68 | U68: =T68*R68 -> 0 | V68: =W68/F68 -> #REF! | W68: ='CD R Documentación'!O70+'CD R Documentación'!T70+'CD R Documentación'!Y70+'CD R Documentación'!AD70+'CD R Documentación'!AI70+'CD R Documentación'!AN70+#REF! -> #REF! | X68: ='CD R Documentación'!R70+'CD R Documentación'!W70+'CD R Documentación'!AB70+'CD R Documentación'!AG70+'CD R Documentación'!AL70+'CD R Documentación'!AQ70+#REF! -> #REF! | Y68: =Z68/F68 -> 0 | Z68: ='CD R Investigación'!P70+'CD R Investigación'!U70+'CD R Investigación'!Z70+'CD R Investigación'!AE70+'CD R Investigación'!AJ70+'CD R Investigación'!AO70+'CD R Investigación'!AT70+'CD R Investigación'!AY70 -> 0 | AA68: ='CD R Investigación'!S70+'CD R Investigación'!X70+'CD R Investigación'!AC70+'CD R Investigación'!AH70+'CD R Investigación'!AM70+'CD R Investigación'!AR70+'CD R Investigación'!AW70+'CD R Investigación'!BB70 -> 0 | AB68: =AC68/F68 -> #REF! | AC68: ='CD R Desarrollo'!P69+'CD R Desarrollo'!U69+'CD R Desarrollo'!Z69+'CD R Desarrollo'!AE69+'CD R Desarrollo'!AJ69+'CD R Desarrollo'!AO69+#REF!+#REF! -> #REF! | AD68: ='CD R Desarrollo'!S69+'CD R Desarrollo'!X69+'CD R Desarrollo'!AC69+'CD R Desarrollo'!AH69+'CD R Desarrollo'!AM69+'CD R Desarrollo'!AR69+#REF!+#REF! -> #REF! | AE68: 1 | AF68: ='PL Cronograma detallado'!L206*AE68 -> 14.21 | AG68: =AF68/'PL Cronograma detallado'!M$257 -> #DIV/0! | AH68: =SUM(AG68,AH69) -> #DIV/0!
A69: 3.5.5 | B69: Reunión de Líderes 9 | C69: 44717 | D69: 44717 | E69: =_xludf.DAYs(D69,C69)+1 -> #NAME? | F69: 1 | G69: =F69/F$105 -> 0.0011350738 | H69: =SUM(H68,G69) -> 0.54483541 | I69: =SUM(R69,W69,Z69,AC69) -> #REF! | J69: =SUM(I69,J68) -> #REF! | K69: =J69/$J$104 -> #REF! | L69: =SUM(U69,X69,AA69,AD69) -> #REF! | M69: =SUM(L69,M68) -> #REF! | N69: =G69*AE69 -> 0.0011350738 | O69: =SUM(N69,O68) -> 0.54370034 | P69: =M69/$M$93 -> #REF! | Q69: =R69/F69 -> 1 | R69: 1 | S69: L | T69: =IF(S69="L",0.68,IF(S69="JP",0.57,IF(S69="JI",0.57,IF(S69="JD",0.57,IF(S69="P",0.24,IF(S69="I",0.12,IF(S69="D",0.13))))))) -> 0.68 | U69: =T69*R69 -> 0.68 | V69: =W69/F69 -> #REF! | W69: ='CD R Documentación'!O69+'CD R Documentación'!T69+'CD R Documentación'!Y69+'CD R Documentación'!AD69+'CD R Documentación'!AI69+'CD R Documentación'!AN69+#REF! -> #REF! | X69: ='CD R Documentación'!R69+'CD R Documentación'!W69+'CD R Documentación'!AB69+'CD R Documentación'!AG69+'CD R Documentación'!AL69+'CD R Documentación'!AQ69+#REF! -> #REF! | Y69: =Z69/F69 -> 0 | Z69: ='CD R Investigación'!P69+'CD R Investigación'!U69+'CD R Investigación'!Z69+'CD R Investigación'!AE69+'CD R Investigación'!AJ69+'CD R Investigación'!AO69+'CD R Investigación'!AT69+'CD R Investigación'!AY69 -> 0 | AA69: ='CD R Investigación'!S69+'CD R Investigación'!X69+'CD R Investigación'!AC69+'CD R Investigación'!AH69+'CD R Investigación'!AM69+'CD R Investigación'!AR69+'CD R Investigación'!AW69+'CD R Investigación'!BB69 -> 0 | AB69: =AC69/F69 -> #REF! | AC69: ='CD R Desarrollo'!P70+'CD R Desarrollo'!U70+'CD R Desarrollo'!Z70+'CD R Desarrollo'!AE70+'CD R Desarrollo'!AJ70+'CD R Desarrollo'!AO70+#REF!+#REF! -> #REF! | AD69: ='CD R Desarrollo'!S69+'CD R Desarrollo'!X69+'CD R Desarrollo'!AC69+'CD R Desarrollo'!AH69+'CD R Desarrollo'!AM69+'CD R Desarrollo'!AR69+#REF!+#REF! -> #REF! | AE69: 1 | AF69: ='PL Cronograma detallado'!L207*AE69 -> 2.49 | AG69: =AF69/'PL Cronograma detallado'!M$257 -> #DIV/0! | AH69: =SUM(AG69,AH67) -> #DIV/0!
A70: 3.5.6 | B70: Pruebas de Uso Básico | C70: 44721 | D70: 44722 | E70: =_xludf.DAYs(D70,C70)+1 -> #NAME? | F70: 10 | G70: =F70/F$105 -> 0.011350738 | H70: =SUM(H69,G70) -> 0.55618615 | I70: =SUM(R70,W70,Z70,AC70) -> #REF! | J70: =SUM(I70,J69) -> #REF! | K70: =J70/$J$104 -> #REF! | L70: =SUM(U70,X70,AA70,AD70) -> #REF! | M70: =SUM(L70,M69) -> #REF! | N70: =G70*AE70 -> 0.011350738 | O70: =SUM(N70,O69) -> 0.55505108 | P70: =M70/$M$93 -> #REF! | Q70: =R70/F70 -> 0 | R70: 0 | S70: L | T70: =IF(S70="L",0.68,IF(S70="JP",0.57,IF(S70="JI",0.57,IF(S70="JD",0.57,IF(S70="P",0.24,IF(S70="I",0.12,IF(S70="D",0.13))))))) -> 0.68 | U70: =T70*R70 -> 0 | V70: =W70/F70 -> #REF! | W70: ='CD R Documentación'!O71+'CD R Documentación'!T71+'CD R Documentación'!Y71+'CD R Documentación'!AD71+'CD R Documentación'!AI71+'CD R Documentación'!AN71+#REF! -> #REF! | X70: ='CD R Documentación'!R71+'CD R Documentación'!W71+'CD R Documentación'!AB71+'CD R Documentación'!AG71+'CD R Documentación'!AL71+'CD R Documentación'!AQ71+#REF! -> #REF! | Y70: =Z70/F70 -> 0 | Z70: ='CD R Investigación'!P71+'CD R Investigación'!U71+'CD R Investigación'!Z71+'CD R Investigación'!AE71+'CD R Investigación'!AJ71+'CD R Investigación'!AO71+'CD R Investigación'!AT71+'CD R Investigación'!AY71 -> 0 | AA70: ='CD R Investigación'!S71+'CD R Investigación'!X71+'CD R Investigación'!AC71+'CD R Investigación'!AH71+'CD R Investigación'!AM71+'CD R Investigación'!AR71+'CD R Investigación'!AW71+'CD R Investigación'!BB71 -> 0 | AB70: =AC70/F70 -> #REF! | AC70: ='CD R Desarrollo'!P71+'CD R Desarrollo'!U71+'CD R Desarrollo'!Z71+'CD R Desarrollo'!AE71+'CD R Desarrollo'!AJ71+'CD R Desarrollo'!AO71+#REF!+#REF! -> #REF! | AD70: ='CD R Desarrollo'!S71+'CD R Desarrollo'!X71+'CD R Desarrollo'!AC71+'CD R Desarrollo'!AH71+'CD R Desarrollo'!AM71+'CD R Desarrollo'!AR71+#REF!+#REF! -> #REF! | AE70: 1 | AF70: ='PL Cronograma detallado'!L210*AE70 -> 7.28 | AG70: =AF70/'PL Cronograma detallado'!M$257 -> #DIV/0! | AH70: =SUM(AG70,AH68) -> #DIV/0!
A71: 3.5.7 | B71: Reunión de Líderes 10 | C71: 44724 | D71: 44724 | E71: =_xludf.DAYs(D71,C71)+1 -> #NAME? | F71: 1 | G71: =F71/F$105 -> 0.0011350738 | H71: =SUM(H70,G71) -> 0.55732123 | I71: =SUM(R71,W71,Z71,AC71) -> #REF! | J71: =SUM(I71,J70) -> #REF! | K71: =J71/$J$104 -> #REF! | L71: =SUM(U71,X71,AA71,AD71) -> #REF! | M71: =SUM(L71,M70) -> #REF! | N71: =G71*AE71 -> 0.0011350738 | O71: =SUM(N71,O70) -> 0.55618615 | P71: =M71/$M$93 -> #REF! | Q71: =R71/F71 -> 1 | R71: 1 | S71: L | T71: =IF(S71="L",0.68,IF(S71="JP",0.57,IF(S71="JI",0.57,IF(S71="JD",0.57,IF(S71="P",0.24,IF(S71="I",0.12,IF(S71="D",0.13))))))) -> 0.68 | U71: =T71*R71 -> 0.68 | V71: =W71/F71 -> #REF! | W71: ='CD R Documentación'!O72+'CD R Documentación'!T72+'CD R Documentación'!Y72+'CD R Documentación'!AD72+'CD R Documentación'!AI72+'CD R Documentación'!AN72+#REF! -> #REF! | X71: ='CD R Documentación'!R72+'CD R Documentación'!W72+'CD R Documentación'!AB72+'CD R Documentación'!AG72+'CD R Documentación'!AL72+'CD R Documentación'!AQ72+#REF! -> #REF! | Y71: =Z71/F71 -> 0 | Z71: ='CD R Investigación'!P72+'CD R Investigación'!U72+'CD R Investigación'!Z72+'CD R Investigación'!AE72+'CD R Investigación'!AJ72+'CD R Investigación'!AO72+'CD R Investigación'!AT72+'CD R Investigación'!AY72 -> 0 | AA71: ='CD R Investigación'!S72+'CD R Investigación'!X72+'CD R Investigación'!AC72+'CD R Investigación'!AH72+'CD R Investigación'!AM72+'CD R Investigación'!AR72+'CD R Investigación'!AW72+'CD R Investigación'!BB72 -> 0 | AB71: =AC71/F71 -> #REF! | AC71: ='CD R Desarrollo'!P72+'CD R Desarrollo'!U72+'CD R Desarrollo'!Z72+'CD R Desarrollo'!AE72+'CD R Desarrollo'!AJ72+'CD R Desarrollo'!AO72+#REF!+#REF! -> #REF! | AD71: ='CD R Desarrollo'!S72+'CD R Desarrollo'!X72+'CD R Desarrollo'!AC72+'CD R Desarrollo'!AH72+'CD R Desarrollo'!AM72+'CD R Desarrollo'!AR72+#REF!+#REF! -> #REF! | AE71: 1 | AF71: ='PL Cronograma detallado'!L212*AE71 -> 0 | AG71: =AF71/'PL Cronograma detallado'!M$257 -> #DIV/0! | AH71: =SUM(AG71,AH70) -> #DIV/0!
A72: 3.6 | B72: Elaboración Informe de Avance N°3 | C72: 44718 | D72: 44725 | E72: =_xludf.DAYs(D72,C72)+1 -> #NAME? | F72: 24 | G72: =F72/F$105 -> 0.027241771 | H72: =SUM(H71,G72) -> 0.584563 | I72: =SUM(R72,W72,Z72,AC72) -> #REF! | J72: =SUM(I72,J71) -> #REF! | K72: =J72/$J$104 -> #REF! | L72: =SUM(U72,X72,AA72,AD72) -> #REF! | M72: =SUM(L72,M71) -> #REF! | N72: =G72*AE72 -> 0.027241771 | O72: =SUM(N72,O71) -> 0.58342792 | P72: =M72/$M$93 -> #REF! | Q72: =R72/F72 -> 0.16666667 | R72: 4 | S72: L | T72: =IF(S72="L",0.68,IF(S72="JP",0.57,IF(S72="JI",0.57,IF(S72="JD",0.57,IF(S72="P",0.24,IF(S72="I",0.12,IF(S72="D",0.13))))))) -> 0.68 | U72: =T72*R72 -> 2.72 | V72: =W72/F72 -> #REF! | W72: ='CD R Documentación'!O73+'CD R Documentación'!T73+'CD R Documentación'!Y73+'CD R Documentación'!AD73+'CD R Documentación'!AI73+'CD R Documentación'!AN73+#REF! -> #REF! | X72: ='CD R Documentación'!R73+'CD R Documentación'!W73+'CD R Documentación'!AB73+'CD R Documentación'!AG73+'CD R Documentación'!AL73+'CD R Documentación'!AQ73+#REF! -> #REF! | Y72: =Z72/F72 -> 0 | Z72: ='CD R Investigación'!P73+'CD R Investigación'!U73+'CD R Investigación'!Z73+'CD R Investigación'!AE73+'CD R Investigación'!AJ73+'CD R Investigación'!AO73+'CD R Investigación'!AT73+'CD R Investigación'!AY73 -> 0 | AA72: ='CD R Investigación'!S73+'CD R Investigación'!X73+'CD R Investigación'!AC73+'CD R Investigación'!AH73+'CD R Investigación'!AM73+'CD R Investigación'!AR73+'CD R Investigación'!AW73+'CD R Investigación'!BB73 -> 0 | AB72: =AC72/F72 -> #REF! | AC72: ='CD R Desarrollo'!P73+'CD R Desarrollo'!U73+'CD R Desarrollo'!Z73+'CD R Desarrollo'!AE73+'CD R Desarrollo'!AJ73+'CD R Desarrollo'!AO73+#REF!+#REF! -> #REF! | AD72: ='CD R Desarrollo'!S73+'CD R Desarrollo'!X73+'CD R Desarrollo'!AC73+'CD R Desarrollo'!AH73+'CD R Desarrollo'!AM73+'CD R Desarrollo'!AR73+#REF!+#REF! -> #REF! | AE72: 1 | AF72: ='PL Cronograma detallado'!L213*AE72 -> 51.68 | AG72: =AF72/'PL Cronograma detallado'!M$257 -> #DIV/0! | AH72: =SUM(AG72,AH71) -> #DIV/0!
A73: H4 | B73: Entrega de Avance N°3 y Defensa | C73: 44726 | D73: 44726 | E73: =_xludf.DAYs(D73,C73)+1 -> #NAME? | F73: 1 | G73: =(F73/F$105) -> 0.0011350738 | H73: =SUM(H72,G73) -> 0.58569807 | I73: =SUM(R73,W73,Z73,AC73) -> #REF! | J73: =SUM(I73,J72) -> #REF! | K73: =J73/$J$104 -> #REF! | L73: =SUM(U73,X73,AA73,AD73) -> #REF! | M73: =SUM(L73,M72) -> #REF! | N73: =G73*AE73 -> 0.0011350738 | O73: =SUM(N73,O72) -> 0.584563 | P73: =M73/$M$93 -> #REF! | Q73: =R73/F73 -> 1 | R73: 1 | S73: L | T73: =IF(S73="L",0.68,IF(S73="JP",0.57,IF(S73="JI",0.57,IF(S73="JD",0.57,IF(S73="P",0.24,IF(S73="I",0.12,IF(S73="D",0.13))))))) -> 0.68 | U73: =T73*R73 -> 0.68 | V73: =W73/F73 -> #REF! | W73: ='CD R Documentación'!O74+'CD R Documentación'!T74+'CD R Documentación'!Y74+'CD R Documentación'!AD74+'CD R Documentación'!AI74+'CD R Documentación'!AN74+#REF! -> #REF! | X73: ='CD R Documentación'!R74+'CD R Documentación'!W74+'CD R Documentación'!AB74+'CD R Documentación'!AG74+'CD R Documentación'!AL74+'CD R Documentación'!AQ74+#REF! -> #REF! | Y73: =Z73/F73 -> 0 | Z73: ='CD R Investigación'!P74+'CD R Investigación'!U74+'CD R Investigación'!Z74+'CD R Investigación'!AE74+'CD R Investigación'!AJ74+'CD R Investigación'!AO74+'CD R Investigación'!AT74+'CD R Investigación'!AY74 -> 0 | AA73: ='CD R Investigación'!S74+'CD R Investigación'!X74+'CD R Investigación'!AC74+'CD R Investigación'!AH74+'CD R Investigación'!AM74+'CD R Investigación'!AR74+'CD R Investigación'!AW74+'CD R Investigación'!BB74 -> 0 | AB73: =AC73/F73 -> #REF! | AC73: ='CD R Desarrollo'!P74+'CD R Desarrollo'!U74+'CD R Desarrollo'!Z74+'CD R Desarrollo'!AE74+'CD R Desarrollo'!AJ74+'CD R Desarrollo'!AO74+#REF!+#REF! -> #REF! | AD73: ='CD R Desarrollo'!S74+'CD R Desarrollo'!X74+'CD R Desarrollo'!AC74+'CD R Desarrollo'!AH74+'CD R Desarrollo'!AM74+'CD R Desarrollo'!AR74+#REF!+#REF! -> #REF! | AE73: 1 | AF73: ='PL Cronograma detallado'!L214*AE73 -> 10.41 | AG73: =AF73/'PL Cronograma detallado'!M$257 -> #DIV/0! | AH73: =SUM(AG73,AH72) -> #DIV/0!
A74: 3.7 | B74: Construcción de Prototipo (Parte 2) | C74: 44726 | D74: 44749 | E74: =_xludf.DAYs(D74,C74)+1 -> #NAME? | F74: =SUM(F75:F83) -> 172 | G74: =SUM(G75:G83) -> 0.19523269 | H74: =SUM(G74,H73) -> 0.78093076 | I74: =SUM(I75:I83) -> #REF! | J74: =SUM(I74,J64) -> #REF! | K74: =J74/$J$104 -> #REF! | L74: =SUM(L75:L83) -> #REF! | M74: =SUM(L74,M73) -> #REF! | O74: =AH74 | P74: =M74/$M$93 -> #REF! | Q74: =R74/F74 -> 0 | R74: 0 | S74: L | T74: =IF(S74="L",0.68,IF(S74="JP",0.57,IF(S74="JI",0.57,IF(S74="JD",0.57,IF(S74="P",0.24,IF(S74="I",0.12,IF(S74="D",0.13))))))) -> 0.68 | U74: =T74*R74 -> 0 | V74: =W74/F74 -> #REF! | W74: ='CD R Documentación'!O75+'CD R Documentación'!T75+'CD R Documentación'!Y75+'CD R Documentación'!AD75+'CD R Documentación'!AI75+'CD R Documentación'!AN75+#REF! -> #REF! | X74: ='CD R Documentación'!R75+'CD R Documentación'!W75+'CD R Documentación'!AB75+'CD R Documentación'!AG75+'CD R Documentación'!AL75+'CD R Documentación'!AQ75+#REF! -> #REF! | Y74: =Z74/F74 -> 0.011627907 | Z74: ='CD R Investigación'!P75+'CD R Investigación'!U75+'CD R Investigación'!Z75+'CD R Investigación'!AE75+'CD R Investigación'!AJ75+'CD R Investigación'!AO75+'CD R Investigación'!AT75+'CD R Investigación'!AY75 -> 2 | AA74: ='CD R Investigación'!S75+'CD R Investigación'!X75+'CD R Investigación'!AC75+'CD R Investigación'!AH75+'CD R Investigación'!AM75+'CD R Investigación'!AR75+'CD R Investigación'!AW75+'CD R Investigación'!BB75 -> 0.88 | AB74: =AC74/F74 -> #REF! | AC74: ='CD R Desarrollo'!P75+'CD R Desarrollo'!U75+'CD R Desarrollo'!Z75+'CD R Desarrollo'!AE75+'CD R Desarrollo'!AJ75+'CD R Desarrollo'!AO75+#REF!+#REF! -> #REF! | AD74: ='CD R Desarrollo'!S75+'CD R Desarrollo'!X75+'CD R Desarrollo'!AC75+'CD R Desarrollo'!AH75+'CD R Desarrollo'!AM75+'CD R Desarrollo'!AR75+#REF!+#REF! -> #REF!
A75: 3.7.1 | B75: Desarrollo del Prototipo (parte 2) | C75: 44726 | D75: 44742 | E75: =_xludf.DAYs(D75,C75)+1 -> #NAME? | F75: 70 | G75: =F75/F$105 -> 0.079455165 | H75: =SUM(H73,G75) -> 0.66515324 | I75: =SUM(R75,W75,Z75,AC75) -> #REF! | J75: =SUM(I75,J73) -> #REF! | K75: =J75/$J$104 -> #REF! | L75: =SUM(U75,X75,AA75,AD75) -> #REF! | M75: =SUM(L75,M73) -> #REF! | N75: =G75*AE75 -> 0.079455165 | O75: =SUM(N75,O73) -> 0.66401816 | P75: =M75/$M$93 -> #REF! | Q75: =R75/F75 -> 0 | R75: 0 | S75: L | T75: =IF(S75="L",0.68,IF(S75="JP",0.57,IF(S75="JI",0.57,IF(S75="JD",0.57,IF(S75="P",0.24,IF(S75="I",0.12,IF(S75="D",0.13))))))) -> 0.68 | U75: =T75*R75 -> 0 | V75: =W75/F75 -> #REF! | W75: ='CD R Documentación'!O76+'CD R Documentación'!T76+'CD R Documentación'!Y76+'CD R Documentación'!AD76+'CD R Documentación'!AI76+'CD R Documentación'!AN76+#REF! -> #REF! | X75: ='CD R Documentación'!R76+'CD R Documentación'!W76+'CD R Documentación'!AB76+'CD R Documentación'!AG76+'CD R Documentación'!AL76+'CD R Documentación'!AQ76+#REF! -> #REF! | Y75: =Z75/F75 -> 0 | Z75: ='CD R Investigación'!P76+'CD R Investigación'!U76+'CD R Investigación'!Z76+'CD R Investigación'!AE76+'CD R Investigación'!AJ76+'CD R Investigación'!AO76+'CD R Investigación'!AT76+'CD R Investigación'!AY76 -> 0 | AA75: ='CD R Investigación'!S76+'CD R Investigación'!X76+'CD R Investigación'!AC76+'CD R Investigación'!AH76+'CD R Investigación'!AM76+'CD R Investigación'!AR76+'CD R Investigación'!AW76+'CD R Investigación'!BB76 -> 0 | AB75: =AC75/F75 -> #REF! | AC75: ='CD R Desarrollo'!P76+'CD R Desarrollo'!U76+'CD R Desarrollo'!Z76+'CD R Desarrollo'!AE76+'CD R Desarrollo'!AJ76+'CD R Desarrollo'!AO76+#REF!+#REF! -> #REF! | AD75: ='CD R Desarrollo'!S76+'CD R Desarrollo'!X76+'CD R Desarrollo'!AC76+'CD R Desarrollo'!AH76+'CD R Desarrollo'!AM76+'CD R Desarrollo'!AR76+#REF!+#REF! -> #REF! | AE75: 1 | AF75: ='PL Cronograma detallado'!L217*AE75 -> 3.43 | AG75: =AF75/'PL Cronograma detallado'!M$257 -> #DIV/0! | AH75: =SUM(AG75,AH73) -> #DIV/0!
A76: 3.7.2 | B76: Ingresar Red Neuronal a una Maquina Virtual | C76: 44727 | D76: 44730 | E76: =_xludf.DAYs(D76,C76)+1 -> #NAME? | F76: 10 | G76: =F76/F$105 -> 0.011350738 | H76: =SUM(H75,G76) -> 0.67650397 | I76: =SUM(R76,W76,Z76,AC76) -> #REF! | J76: =SUM(I76,J75) -> #REF! | K76: =J76/$J$104 -> #REF! | L76: =SUM(U76,X76,AA76,AD76) -> #REF! | M76: =SUM(L76,M75) -> #REF! | N76: =G76*AE76 -> 0.011350738 | O76: =SUM(N76,O75) -> 0.6753689 | P76: =M76/$M$93 -> #REF! | Q76: =R76/F76 -> 0 | R76: 0 | S76: L | T76: =IF(S76="L",0.68,IF(S76="JP",0.57,IF(S76="JI",0.57,IF(S76="JD",0.57,IF(S76="P",0.24,IF(S76="I",0.12,IF(S76="D",0.13))))))) -> 0.68 | U76: =T76*R76 -> 0 | V76: =W76/F76 -> #REF! | W76: ='CD R Documentación'!O77+'CD R Documentación'!T77+'CD R Documentación'!Y77+'CD R Documentación'!AD77+'CD R Documentación'!AI77+'CD R Documentación'!AN77+#REF! -> #REF! | X76: ='CD R Documentación'!R77+'CD R Documentación'!W77+'CD R Documentación'!AB77+'CD R Documentación'!AG77+'CD R Documentación'!AL77+'CD R Documentación'!AQ77+#REF! -> #REF! | Y76: =Z76/F76 -> 0 | Z76: ='CD R Investigación'!P77+'CD R Investigación'!U77+'CD R Investigación'!Z77+'CD R Investigación'!AE77+'CD R Investigación'!AJ77+'CD R Investigación'!AO77+'CD R Investigación'!AT77+'CD R Investigación'!AY77 -> 0 | AA76: ='CD R Investigación'!S77+'CD R Investigación'!X77+'CD R Investigación'!AC77+'CD R Investigación'!AH77+'CD R Investigación'!AM77+'CD R Investigación'!AR77+'CD R Investigación'!AW77+'CD R Investigación'!BB77 -> 0 | AB76: =AC76/F76 -> #REF! | AC76: ='CD R Desarrollo'!P77+'CD R Desarrollo'!U77+'CD R Desarrollo'!Z77+'CD R Desarrollo'!AE77+'CD R Desarrollo'!AJ77+'CD R Desarrollo'!AO77+#REF!+#REF! -> #REF! | AD76: ='CD R Desarrollo'!S77+'CD R Desarrollo'!X77+'CD R Desarrollo'!AC77+'CD R Desarrollo'!AH77+'CD R Desarrollo'!AM77+'CD R Desarrollo'!AR77+#REF!+#REF! -> #REF! | AE76: 1 | AF76: ='PL Cronograma detallado'!L218*AE76 -> 12.44 | AG76: =AF76/'PL Cronograma detallado'!M$257 -> #DIV/0! | AH76: =SUM(AG76,AH75) -> #DIV/0!
A77: 3.7.3 | B77: Reunión de Líderes 11 | C77: 44731 | D77: 44731 | E77: =_xludf.DAYs(D77,C77)+1 -> #NAME? | F77: 1 | G77: =F77/F$105 -> 0.0011350738 | H77: =SUM(H76,G77) -> 0.67763905 | I77: =SUM(R77,W77,Z77,AC77) -> #REF! | J77: =SUM(I77,J76) -> #REF! | K77: =J77/$J$104 -> #REF! | L77: =SUM(U77,X77,AA77,AD77) -> #REF! | M77: =SUM(L77,M76) -> #REF! | N77: =G77*AE77 -> 0.0011350738 | O77: =SUM(N77,O76) -> 0.67650397 | P77: =M77/$M$93 -> #REF! | Q77: =R77/F77 -> 1 | R77: 1 | S77: L | T77: =IF(S77="L",0.68,IF(S77="JP",0.57,IF(S77="JI",0.57,IF(S77="JD",0.57,IF(S77="P",0.24,IF(S77="I",0.12,IF(S77="D",0.13))))))) -> 0.68 | U77: =T77*R77 -> 0.68 | V77: =W77/F77 -> #REF! | W77: ='CD R Documentación'!O78+'CD R Documentación'!T78+'CD R Documentación'!Y78+'CD R Documentación'!AD78+'CD R Documentación'!AI78+'CD R Documentación'!AN78+#REF! -> #REF! | X77: ='CD R Documentación'!R78+'CD R Documentación'!W78+'CD R Documentación'!AB78+'CD R Documentación'!AG78+'CD R Documentación'!AL78+'CD R Documentación'!AQ78+#REF! -> #REF! | Y77: =Z77/F77 -> 0 | Z77: ='CD R Investigación'!P78+'CD R Investigación'!U78+'CD R Investigación'!Z78+'CD R Investigación'!AE78+'CD R Investigación'!AJ78+'CD R Investigación'!AO78+'CD R Investigación'!AT78+'CD R Investigación'!AY78 -> 0 | AA77: ='CD R Investigación'!S78+'CD R Investigación'!X78+'CD R Investigación'!AC78+'CD R Investigación'!AH78+'CD R Investigación'!AM78+'CD R Investigación'!AR78+'CD R Investigación'!AW78+'CD R Investigación'!BB78 -> 0 | AB77: =AC77/F77 -> #REF! | AC77: ='CD R Desarrollo'!P78+'CD R Desarrollo'!U78+'CD R Desarrollo'!Z78+'CD R Desarrollo'!AE78+'CD R Desarrollo'!AJ78+'CD R Desarrollo'!AO78+#REF!+#REF! -> #REF! | AD77: ='CD R Desarrollo'!S78+'CD R Desarrollo'!X78+'CD R Desarrollo'!AC78+'CD R Desarrollo'!AH78+'CD R Desarrollo'!AM78+'CD R Desarrollo'!AR78+#REF!+#REF! -> #REF! | AE77: 1 | AF77: ='PL Cronograma detallado'!L219*AE77 -> 4.41 | AG77: =AF77/'PL Cronograma detallado'!M$257 -> #DIV/0! | AH77: =SUM(AG77,AH76) -> #DIV/0!
A78: 3.7.4 | B78: Conexion Front y Backend | C78: 44732 | D78: 44744 | E78: =_xludf.DAYs(D78,C78)+1 -> #NAME? | F78: 25 | G78: =F78/F$105 -> 0.028376844 | H78: =SUM(H77,G78) -> 0.70601589 | I78: =SUM(R78,W78,Z78,AC78) -> #REF! | J78: =SUM(I78,J77) -> #REF! | K78: =J78/$J$104 -> #REF! | L78: =SUM(U78,X78,AA78,AD78) -> #REF! | M78: =SUM(L78,M77) -> #REF! | N78: =G78*AE78 -> 0.028376844 | O78: =SUM(N78,O77) -> 0.70488082 | P78: =M78/$M$93 -> #REF! | Q78: =R78/F78 -> 0 | R78: 0 | S78: L | T78: =IF(S78="L",0.68,IF(S78="JP",0.57,IF(S78="JI",0.57,IF(S78="JD",0.57,IF(S78="P",0.24,IF(S78="I",0.12,IF(S78="D",0.13))))))) -> 0.68 | U78: =T78*R78 -> 0 | V78: =W78/F78 -> #REF! | W78: ='CD R Documentación'!O79+'CD R Documentación'!T79+'CD R Documentación'!Y79+'CD R Documentación'!AD79+'CD R Documentación'!AI79+'CD R Documentación'!AN79+#REF! -> #REF! | X78: ='CD R Documentación'!R79+'CD R Documentación'!W79+'CD R Documentación'!AB79+'CD R Documentación'!AG79+'CD R Documentación'!AL79+'CD R Documentación'!AQ79+#REF! -> #REF! | Y78: =Z78/F78 -> 0 | Z78: ='CD R Investigación'!P79+'CD R Investigación'!U79+'CD R Investigación'!Z79+'CD R Investigación'!AE79+'CD R Investigación'!AJ79+'CD R Investigación'!AO79+'CD R Investigación'!AT79+'CD R Investigación'!AY79 -> 0 | AA78: ='CD R Investigación'!S79+'CD R Investigación'!X79+'CD R Investigación'!AC79+'CD R Investigación'!AH79+'CD R Investigación'!AM79+'CD R Investigación'!AR79+'CD R Investigación'!AW79+'CD R Investigación'!BB79 -> 0 | AB78: =AC78/F78 -> #REF! | AC78: ='CD R Desarrollo'!P79+'CD R Desarrollo'!U79+'CD R Desarrollo'!Z79+'CD R Desarrollo'!AE79+'CD R Desarrollo'!AJ79+'CD R Desarrollo'!AO79+#REF!+#REF! -> #REF! | AD78: ='CD R Desarrollo'!S79+'CD R Desarrollo'!X79+'CD R Desarrollo'!AC79+'CD R Desarrollo'!AH79+'CD R Desarrollo'!AM79+'CD R Desarrollo'!AR79+#REF!+#REF! -> #REF! | AE78: 1 | AF78: ='PL Cronograma detallado'!L222*AE78 -> 3.65 | AG78: =AF78/'PL Cronograma detallado'!M$257 -> #DIV/0! | AH78: =SUM(AG78,AH77) -> #DIV/0!
A79: 3.7.5 | B79: Reunión de Líderes 12 | C79: 44738 | D79: 44738 | E79: =_xludf.DAYs(D79,C79)+1 -> #NAME? | F79: 1 | G79: =F79/F$105 -> 0.0011350738 | H79: =SUM(H78,G79) -> 0.70715096 | I79: =SUM(R79,W79,Z79,AC79) -> #REF! | J79: =SUM(I79,J78) -> #REF! | K79: =J79/$J$104 -> #REF! | L79: =SUM(U79,X79,AA79,AD79) -> #REF! | M79: =SUM(L79,M80) -> #REF! | N79: =G79*AE79 -> 0.0011350738 | O79: =SUM(N79,O78) -> 0.70601589 | P79: =M79/$M$93 -> #REF! | Q79: =R79/F79 -> 1 | R79: 1 | S79: L | T79: =IF(S79="L",0.68,IF(S79="JP",0.57,IF(S79="JI",0.57,IF(S79="JD",0.57,IF(S79="P",0.24,IF(S79="I",0.12,IF(S79="D",0.13))))))) -> 0.68 | U79: =T79*R79 -> 0.68 | V79: =W79/F79 -> #REF! | W79: ='CD R Documentación'!O80+'CD R Documentación'!T80+'CD R Documentación'!Y80+'CD R Documentación'!AD80+'CD R Documentación'!AI80+'CD R Documentación'!AN80+#REF! -> #REF! | X79: ='CD R Documentación'!R80+'CD R Documentación'!W80+'CD R Documentación'!AB80+'CD R Documentación'!AG80+'CD R Documentación'!AL80+'CD R Documentación'!AQ80+#REF! -> #REF! | Y79: =Z79/F79 -> 0 | Z79: ='CD R Investigación'!P80+'CD R Investigación'!U80+'CD R Investigación'!Z80+'CD R Investigación'!AE80+'CD R Investigación'!AJ80+'CD R Investigación'!AO80+'CD R Investigación'!AT80+'CD R Investigación'!AY80 -> 0 | AA79: ='CD R Investigación'!S80+'CD R Investigación'!X80+'CD R Investigación'!AC80+'CD R Investigación'!AH80+'CD R Investigación'!AM80+'CD R Investigación'!AR80+'CD R Investigación'!AW80+'CD R Investigación'!BB80 -> 0 | AB79: =AC79/F79 -> #REF! | AC79: ='CD R Desarrollo'!P80+'CD R Desarrollo'!U80+'CD R Desarrollo'!Z80+'CD R Desarrollo'!AE80+'CD R Desarrollo'!AJ80+'CD R Desarrollo'!AO80+#REF!+#REF! -> #REF! | AD79: ='CD R Desarrollo'!S80+'CD R Desarrollo'!X80+'CD R Desarrollo'!AC80+'CD R Desarrollo'!AH80+'CD R Desarrollo'!AM80+'CD R Desarrollo'!AR80+#REF!+#REF! -> #REF! | AE79: 1 | AF79: ='PL Cronograma detallado'!L229*AE79 -> 5.8 | AG79: =AF79/'PL Cronograma detallado'!M$257 -> #DIV/0! | AH79: =SUM(AG79,AH80) -> #DIV/0!
A80: 3.7.6 | B80: Documentación del Desarrollo | C80: 44739 | D80: 44744 | E80: =_xludf.DAYs(D80,C80)+1 -> #NAME? | F80: 30 | G80: =F80/F$105 -> 0.034052213 | H80: =SUM(H79,G80) -> 0.74120318 | I80: =SUM(R80,W80,Z80,AC80) -> #REF! | J80: =SUM(I80,J79) -> #REF! | K80: =J80/$J$104 -> #REF! | L80: =SUM(U80,X80,AA80,AD80) -> #REF! | M80: =SUM(L80,M78) -> #REF! | N80: =G80*AE80 -> 0.034052213 | O80: =SUM(N80,O79) -> 0.7400681 | P80: =M80/$M$93 -> #REF! | Q80: =R80/F80 -> 0 | R80: 0 | S80: L | T80: =IF(S80="L",0.68,IF(S80="JP",0.57,IF(S80="JI",0.57,IF(S80="JD",0.57,IF(S80="P",0.24,IF(S80="I",0.12,IF(S80="D",0.13))))))) -> 0.68 | U80: =T80*R80 -> 0 | V80: =W80/F80 -> #REF! | W80: ='CD R Documentación'!O81+'CD R Documentación'!T81+'CD R Documentación'!Y81+'CD R Documentación'!AD81+'CD R Documentación'!AI81+'CD R Documentación'!AN81+#REF! -> #REF! | X80: ='CD R Documentación'!R81+'CD R Documentación'!W81+'CD R Documentación'!AB81+'CD R Documentación'!AG81+'CD R Documentación'!AL81+'CD R Documentación'!AQ81+#REF! -> #REF! | Y80: =Z80/F80 -> 0 | Z80: ='CD R Investigación'!P81+'CD R Investigación'!U81+'CD R Investigación'!Z81+'CD R Investigación'!AE81+'CD R Investigación'!AJ81+'CD R Investigación'!AO81+'CD R Investigación'!AT81+'CD R Investigación'!AY81 -> 0 | AA80: ='CD R Investigación'!S81+'CD R Investigación'!X81+'CD R Investigación'!AC81+'CD R Investigación'!AH81+'CD R Investigación'!AM81+'CD R Investigación'!AR81+'CD R Investigación'!AW81+'CD R Investigación'!BB81 -> 0 | AB80: =AC80/F80 -> #REF! | AC80: ='CD R Desarrollo'!P81+'CD R Desarrollo'!U81+'CD R Desarrollo'!Z81+'CD R Desarrollo'!AE81+'CD R Desarrollo'!AJ81+'CD R Desarrollo'!AO81+#REF!+#REF! -> #REF! | AD80: ='CD R Desarrollo'!S81+'CD R Desarrollo'!X81+'CD R Desarrollo'!AC81+'CD R Desarrollo'!AH81+'CD R Desarrollo'!AM81+'CD R Desarrollo'!AR81+#REF!+#REF! -> #REF! | AE80: 1 | AF80: ='PL Cronograma detallado'!L230*AE80 -> 3.31 | AG80: =AF80/'PL Cronograma detallado'!M$257 -> #DIV/0! | AH80: =SUM(AG80,AH78) -> #DIV/0!
A81: 3.7.7 | B81: Pruebas de experiencia de usuario | C81: 44739 | D81: 44744 | E81: =_xludf.DAYs(D81,C81)+1 -> #NAME? | F81: 10 | G81: =F81/F$105 -> 0.011350738 | H81: =SUM(H80,G81) -> 0.75255392 | I81: =SUM(R81,W81,Z81,AC81) -> #REF! | J81: =SUM(I81,J80) -> #REF! | K81: =J81/$J$104 -> #REF! | L81: =SUM(U81,X81,AA81,AD81) -> #REF! | M81: =SUM(L81,M79) -> #REF! | N81: =G81*AE81 -> 0.011350738 | O81: =SUM(N81,O80) -> 0.75141884 | P81: =M81/$M$93 -> #REF! | Q81: =R81/F81 -> 0 | R81: 0 | S81: L | T81: =IF(S81="L",0.68,IF(S81="JP",0.57,IF(S81="JI",0.57,IF(S81="JD",0.57,IF(S81="P",0.24,IF(S81="I",0.12,IF(S81="D",0.13))))))) -> 0.68 | U81: =T81*R81 -> 0 | V81: =W81/F81 -> #REF! | W81: ='CD R Documentación'!O82+'CD R Documentación'!T82+'CD R Documentación'!Y82+'CD R Documentación'!AD82+'CD R Documentación'!AI82+'CD R Documentación'!AN82+#REF! -> #REF! | X81: ='CD R Documentación'!R82+'CD R Documentación'!W82+'CD R Documentación'!AB82+'CD R Documentación'!AG82+'CD R Documentación'!AL82+'CD R Documentación'!AQ82+#REF! -> #REF! | Y81: =Z81/F81 -> 0.3 | Z81: ='CD R Investigación'!P82+'CD R Investigación'!U82+'CD R Investigación'!Z82+'CD R Investigación'!AE82+'CD R Investigación'!AJ82+'CD R Investigación'!AO82+'CD R Investigación'!AT82+'CD R Investigación'!AY82 -> 3 | AA81: ='CD R Investigación'!S82+'CD R Investigación'!X82+'CD R Investigación'!AC82+'CD R Investigación'!AH82+'CD R Investigación'!AM82+'CD R Investigación'!AR82+'CD R Investigación'!AW82+'CD R Investigación'!BB82 -> 1.32 | AB81: =AC81/F81 -> #REF! | AC81: ='CD R Desarrollo'!P82+'CD R Desarrollo'!U82+'CD R Desarrollo'!Z82+'CD R Desarrollo'!AE82+'CD R Desarrollo'!AJ82+'CD R Desarrollo'!AO82+#REF!+#REF! -> #REF! | AD81: ='CD R Desarrollo'!S82+'CD R Desarrollo'!X82+'CD R Desarrollo'!AC82+'CD R Desarrollo'!AH82+'CD R Desarrollo'!AM82+'CD R Desarrollo'!AR82+#REF!+#REF! -> #REF! | AE81: 1 | AF81: ='PL Cronograma detallado'!L231*AE81 -> 2.49 | AG81: =AF81/'PL Cronograma detallado'!M$257 -> #DIV/0! | AH81: =SUM(AG81,AH79) -> #DIV/0!
A82: 3.8 | B82: Elaboración Informe de Avance N°4 | C82: 44732 | D82: 44740 | E82: =_xludf.DAYs(D82,C82)+1 -> #NAME? | F82: 24 | G82: =F82/F$105 -> 0.027241771 | H82: =SUM(H81,G82) -> 0.77979569 | I82: =SUM(R82,W82,Z82,AC82) -> #REF! | J82: =SUM(I82,J81) -> #REF! | K82: =J82/$J$104 -> #REF! | L82: =SUM(U82,X82,AA82,AD82) -> #REF! | M82: =SUM(L82,M81) -> #REF! | N82: =G82*AE82 -> 0.027241771 | O82: =SUM(N82,O81) -> 0.77866061 | P82: =M82/$M$93 -> #REF! | Q82: =R82/F82 -> 0.125 | R82: 3 | S82: L | T82: =IF(S82="L",0.68,IF(S82="JP",0.57,IF(S82="JI",0.57,IF(S82="JD",0.57,IF(S82="P",0.24,IF(S82="I",0.12,IF(S82="D",0.13))))))) -> 0.68 | U82: =T82*R82 -> 2.04 | V82: =W82/F82 -> #REF! | W82: ='CD R Documentación'!O83+'CD R Documentación'!T83+'CD R Documentación'!Y83+'CD R Documentación'!AD83+'CD R Documentación'!AI83+'CD R Documentación'!AN83+#REF! -> #REF! | X82: ='CD R Documentación'!R83+'CD R Documentación'!W83+'CD R Documentación'!AB83+'CD R Documentación'!AG83+'CD R Documentación'!AL83+'CD R Documentación'!AQ83+#REF! -> #REF! | Y82: =Z82/F82 -> 0.33333333 | Z82: ='CD R Investigación'!P83+'CD R Investigación'!U83+'CD R Investigación'!Z83+'CD R Investigación'!AE83+'CD R Investigación'!AJ83+'CD R Investigación'!AO83+'CD R Investigación'!AT83+'CD R Investigación'!AY83 -> 8 | AA82: ='CD R Investigación'!S83+'CD R Investigación'!X83+'CD R Investigación'!AC83+'CD R Investigación'!AH83+'CD R Investigación'!AM83+'CD R Investigación'!AR83+'CD R Investigación'!AW83+'CD R Investigación'!BB83 -> 3.52 | AB82: =AC82/F82 -> #REF! | AC82: ='CD R Desarrollo'!P83+'CD R Desarrollo'!U83+'CD R Desarrollo'!Z83+'CD R Desarrollo'!AE83+'CD R Desarrollo'!AJ83+'CD R Desarrollo'!AO83+#REF!+#REF! -> #REF! | AD82: ='CD R Desarrollo'!S83+'CD R Desarrollo'!X83+'CD R Desarrollo'!AC83+'CD R Desarrollo'!AH83+'CD R Desarrollo'!AM83+'CD R Desarrollo'!AR83+#REF!+#REF! -> #REF! | AE82: 1 | AF82: ='PL Cronograma detallado'!L232*AE82 -> 15.2 | AG82: =AF82/'PL Cronograma detallado'!M$257 -> #DIV/0! | AH82: =SUM(AG82,AH81) -> #DIV/0!
A83: H5 | B83: Entrega de Avance N°4 y Defensa | C83: 44740 | D83: 44740 | E83: =_xludf.DAYs(D83,C83)+1 -> #NAME? | F83: 1 | G83: =(F83/F$105) -> 0.0011350738 | H83: =SUM(H82,G83) -> 0.78093076 | I83: =SUM(R83,W83,Z83,AC83) -> #REF! | J83: =SUM(I83,J82) -> #REF! | K83: =J83/$J$104 -> #REF! | L83: =SUM(U83,X83,AA83,AD83) -> #REF! | M83: =SUM(L83,M82) -> #REF! | N83: =G83*AE83 -> 0.0011350738 | O83: =SUM(N83,O82) -> 0.77979569 | P83: =M83/$M$93 -> #REF! | Q83: =R83/F83 -> 1 | R83: 1 | S83: L | T83: =IF(S83="L",0.68,IF(S83="JP",0.57,IF(S83="JI",0.57,IF(S83="JD",0.57,IF(S83="P",0.24,IF(S83="I",0.12,IF(S83="D",0.13))))))) -> 0.68 | U83: =T83*R83 -> 0.68 | V83: =W83/F83 -> #REF! | W83: ='CD R Documentación'!O84+'CD R Documentación'!T84+'CD R Documentación'!Y84+'CD R Documentación'!AD84+'CD R Documentación'!AI84+'CD R Documentación'!AN84+#REF! -> #REF! | X83: ='CD R Documentación'!R84+'CD R Documentación'!W84+'CD R Documentación'!AB84+'CD R Documentación'!AG84+'CD R Documentación'!AL84+'CD R Documentación'!AQ84+#REF! -> #REF! | Y83: =Z83/F83 -> 3 | Z83: ='CD R Investigación'!P84+'CD R Investigación'!U84+'CD R Investigación'!Z84+'CD R Investigación'!AE84+'CD R Investigación'!AJ84+'CD R Investigación'!AO84+'CD R Investigación'!AT84+'CD R Investigación'!AY84 -> 3 | AA83: ='CD R Investigación'!S84+'CD R Investigación'!X84+'CD R Investigación'!AC84+'CD R Investigación'!AH84+'CD R Investigación'!AM84+'CD R Investigación'!AR84+'CD R Investigación'!AW84+'CD R Investigación'!BB84 -> 1.32 | AB83: =AC83/F83 -> #REF! | AC83: ='CD R Desarrollo'!P84+'CD R Desarrollo'!U84+'CD R Desarrollo'!Z84+'CD R Desarrollo'!AE84+'CD R Desarrollo'!AJ84+'CD R Desarrollo'!AO84+#REF!+#REF! -> #REF! | AD83: ='CD R Desarrollo'!S84+'CD R Desarrollo'!X84+'CD R Desarrollo'!AC84+'CD R Desarrollo'!AH84+'CD R Desarrollo'!AM84+'CD R Desarrollo'!AR84+#REF!+#REF! -> #REF! | AE83: 1 | AF83: ='PL Cronograma detallado'!L234*AE83 -> 5.06 | AG83: =AF83/'PL Cronograma detallado'!M$257 -> #DIV/0! | AH83: =SUM(AG83,AH82) -> #DIV/0!
A84: 4 | B84: Fase de Estudio de Resultados | C84: 44744 | D84: 44754 | E84: =_xludf.DAYs(D84,C84)+1 -> #NAME? | F84: =F85 -> 52 | G84: =SUM(G85) -> 0.059023837 | I84: =SUM(I85) -> #REF! | J84: =SUM(I84,J50) -> #REF! | K84: =J84/$J$104 -> #REF! | L84: =SUM(L85) -> #REF! | M84: =SUM(L84,M81) -> #REF! | O84: =AH84 | P84: =M84/$M$93 -> #REF! | Q84: =R84/F84 -> 0 | R84: 0 | S84: L | T84: =IF(S84="L",0.68,IF(S84="JP",0.57,IF(S84="JI",0.57,IF(S84="JD",0.57,IF(S84="P",0.24,IF(S84="I",0.12,IF(S84="D",0.13))))))) -> 0.68 | U84: =T84*R84 -> 0 | V84: =W84/F84 -> #REF! | W84: ='CD R Documentación'!O85+'CD R Documentación'!T85+'CD R Documentación'!Y85+'CD R Documentación'!AD85+'CD R Documentación'!AI85+'CD R Documentación'!AN85+#REF! -> #REF! | X84: ='CD R Documentación'!R85+'CD R Documentación'!W85+'CD R Documentación'!AB85+'CD R Documentación'!AG85+'CD R Documentación'!AL85+'CD R Documentación'!AQ85+#REF! -> #REF! | Y84: =Z84/F84 -> 0.73076923 | Z84: ='CD R Investigación'!P85+'CD R Investigación'!U85+'CD R Investigación'!Z85+'CD R Investigación'!AE85+'CD R Investigación'!AJ85+'CD R Investigación'!AO85+'CD R Investigación'!AT85+'CD R Investigación'!AY85 -> 38 | AA84: ='CD R Investigación'!S85+'CD R Investigación'!X85+'CD R Investigación'!AC85+'CD R Investigación'!AH85+'CD R Investigación'!AM85+'CD R Investigación'!AR85+'CD R Investigación'!AW85+'CD R Investigación'!BB85 -> 16.72 | AB84: =AC84/F84 -> #REF! | AC84: ='CD R Desarrollo'!P85+'CD R Desarrollo'!U85+'CD R Desarrollo'!Z85+'CD R Desarrollo'!AE85+'CD R Desarrollo'!AJ85+'CD R Desarrollo'!AO85+#REF!+#REF! -> #REF! | AD84: ='CD R Desarrollo'!S85+'CD R Desarrollo'!X85+'CD R Desarrollo'!AC85+'CD R Desarrollo'!AH85+'CD R Desarrollo'!AM85+'CD R Desarrollo'!AR85+#REF!+#REF! -> #REF!
A85: 4.1 | B85: Analisis de Resultados | C85: 44744 | D85: 44754 | E85: =_xludf.DAYs(D85,C85)+1 -> #NAME? | F85: =SUM(F86:F91) -> 52 | G85: =SUM(G86:G91) -> 0.059023837 | H85: =SUM(G85,H83) -> 0.8399546 | I85: =SUM(I86:I91) -> #REF! | J85: =SUM(I85,J74) -> #REF! | K85: =J85/$J$104 -> #REF! | L85: =SUM(L86:L91) -> #REF! | M85: =SUM(L85,M84) -> #REF! | O85: =AH85 | P85: =M85/$M$93 -> #REF! | Q85: =R85/F85 -> 0 | R85: 0 | S85: L | T85: =IF(S85="L",0.68,IF(S85="JP",0.57,IF(S85="JI",0.57,IF(S85="JD",0.57,IF(S85="P",0.24,IF(S85="I",0.12,IF(S85="D",0.13))))))) -> 0.68 | U85: =T85*R85 -> 0 | V85: =W85/F85 -> #REF! | W85: ='CD R Documentación'!O86+'CD R Documentación'!T86+'CD R Documentación'!Y86+'CD R Documentación'!AD86+'CD R Documentación'!AI86+'CD R Documentación'!AN86+#REF! -> #REF! | X85: ='CD R Documentación'!R86+'CD R Documentación'!W86+'CD R Documentación'!AB86+'CD R Documentación'!AG86+'CD R Documentación'!AL86+'CD R Documentación'!AQ86+#REF! -> #REF! | Y85: =Z85/F85 -> 0 | Z85: ='CD R Investigación'!P86+'CD R Investigación'!U86+'CD R Investigación'!Z86+'CD R Investigación'!AE86+'CD R Investigación'!AJ86+'CD R Investigación'!AO86+'CD R Investigación'!AT86+'CD R Investigación'!AY86 -> 0 | AA85: ='CD R Investigación'!S86+'CD R Investigación'!X86+'CD R Investigación'!AC86+'CD R Investigación'!AH86+'CD R Investigación'!AM86+'CD R Investigación'!AR86+'CD R Investigación'!AW86+'CD R Investigación'!BB86 -> 0 | AB85: =AC85/F85 -> #REF! | AC85: ='CD R Desarrollo'!P86+'CD R Desarrollo'!U86+'CD R Desarrollo'!Z86+'CD R Desarrollo'!AE86+'CD R Desarrollo'!AJ86+'CD R Desarrollo'!AO86+#REF!+#REF! -> #REF! | AD85: ='CD R Desarrollo'!S86+'CD R Desarrollo'!X86+'CD R Desarrollo'!AC86+'CD R Desarrollo'!AH86+'CD R Desarrollo'!AM86+'CD R Desarrollo'!AR86+#REF!+#REF! -> #REF!
A86: 4.1.1 | B86: Realizar Pruebas al Prototipo Funcional | C86: 44744 | D86: 44751 | E86: =_xludf.DAYs(D86,C86)+1 -> #NAME? | F86: 20 | G86: =F86/F$105 -> 0.022701476 | H86: =SUM(H83,G86) -> 0.80363224 | I86: =SUM(R86,W86,Z86,AC86) -> #REF! | J86: =SUM(I86,J83) -> #REF! | K86: =J86/$J$104 -> #REF! | L86: =SUM(U86,X86,AA86,AD86) -> #REF! | M86: =SUM(L86,M83) -> #REF! | N86: =G86*AE86 -> 0.022701476 | O86: =SUM(N86,O83) -> 0.80249716 | P86: =M86/$M$93 -> #REF! | Q86: =R86/F86 -> 0 | R86: 0 | S86: L | T86: =IF(S86="L",0.68,IF(S86="JP",0.57,IF(S86="JI",0.57,IF(S86="JD",0.57,IF(S86="P",0.24,IF(S86="I",0.12,IF(S86="D",0.13))))))) -> 0.68 | U86: =T86*R86 -> 0 | V86: =W86/F86 -> #REF! | W86: ='CD R Documentación'!O87+'CD R Documentación'!T87+'CD R Documentación'!Y87+'CD R Documentación'!AD87+'CD R Documentación'!AI87+'CD R Documentación'!AN87+#REF! -> #REF! | X86: ='CD R Documentación'!R87+'CD R Documentación'!W87+'CD R Documentación'!AB87+'CD R Documentación'!AG87+'CD R Documentación'!AL87+'CD R Documentación'!AQ87+#REF! -> #REF! | Y86: =Z86/F86 -> 0.6 | Z86: ='CD R Investigación'!P87+'CD R Investigación'!U87+'CD R Investigación'!Z87+'CD R Investigación'!AE87+'CD R Investigación'!AJ87+'CD R Investigación'!AO87+'CD R Investigación'!AT87+'CD R Investigación'!AY87 -> 12 | AA86: ='CD R Investigación'!S87+'CD R Investigación'!X87+'CD R Investigación'!AC87+'CD R Investigación'!AH87+'CD R Investigación'!AM87+'CD R Investigación'!AR87+'CD R Investigación'!AW87+'CD R Investigación'!BB87 -> 5.28 | AB86: =AC86/F86 -> #REF! | AC86: ='CD R Desarrollo'!P87+'CD R Desarrollo'!U87+'CD R Desarrollo'!Z87+'CD R Desarrollo'!AE87+'CD R Desarrollo'!AJ87+'CD R Desarrollo'!AO87+#REF!+#REF! -> #REF! | AD86: ='CD R Desarrollo'!S87+'CD R Desarrollo'!X87+'CD R Desarrollo'!AC87+'CD R Desarrollo'!AH87+'CD R Desarrollo'!AM87+'CD R Desarrollo'!AR87+#REF!+#REF! -> #REF! | AE86: 1 | AF86: ='PL Cronograma detallado'!L239*AE86 -> 589.52 | AG86: =AF86/'PL Cronograma detallado'!M$257 -> #DIV/0! | AH86: =SUM(AG86,AH81) -> #DIV/0!
A87: 4.1.2 | B87: Reunión de Líderes 13 | C87: 44745 | D87: 44745 | E87: =_xludf.DAYs(D87,C87)+1 -> #NAME? | F87: 1 | G87: =F87/F$105 -> 0.0011350738 | H87: =SUM(H86,G87) -> 0.80476731 | I87: =SUM(R87,W87,Z87,AC87) -> #REF! | J87: =SUM(I87,J86) -> #REF! | K87: =J87/$J$104 -> #REF! | L87: =SUM(U87,X87,AA87,AD87) -> #REF! | M87: =SUM(L87,M86) -> #REF! | N87: =G87*AE87 -> 0.0011350738 | O87: =SUM(N87,O86) -> 0.80363224 | P87: =M87/$M$93 -> #REF! | Q87: =R87/F87 -> 1 | R87: 1 | S87: L | T87: =IF(S87="L",0.68,IF(S87="JP",0.57,IF(S87="JI",0.57,IF(S87="JD",0.57,IF(S87="P",0.24,IF(S87="I",0.12,IF(S87="D",0.13))))))) -> 0.68 | U87: =T87*R87 -> 0.68 | V87: =W87/F87 -> #REF! | W87: =#REF!+#REF!+#REF!+#REF!+#REF!+#REF!+#REF! -> #REF! | X87: =#REF!+#REF!+#REF!+#REF!+#REF!+#REF!+#REF! -> #REF! | Y87: =Z87/F87 -> #REF! | Z87: =#REF!+#REF!+#REF!+#REF!+#REF!+#REF!+#REF!+#REF! -> #REF! | AA87: =#REF!+#REF!+#REF!+#REF!+#REF!+#REF!+#REF!+#REF! -> #REF! | AB87: =AC87/F87 -> #REF! | AC87: =#REF!+#REF!+#REF!+#REF!+#REF!+#REF!+#REF!+#REF! -> #REF! | AD87: =#REF!+#REF!+#REF!+#REF!+#REF!+#REF!+#REF!+#REF! -> #REF! | AE87: 1 | AF87: ='PL Cronograma detallado'!L240*AE87 -> 0 | AG87: =AF87/'PL Cronograma detallado'!M$257 -> #DIV/0! | AH87: =SUM(AG87,AH86) -> #DIV/0!
A88: 4.1.3 | B88: Analizar y Evaluar Resultados | C88: 44746 | D88: 44751 | E88: =_xludf.DAYs(D88,C88)+1 -> #NAME? | F88: 12 | G88: =F88/F$105 -> 0.013620885 | H88: =SUM(H87,G88) -> 0.8183882 | I88: =SUM(R88,W88,Z88,AC88) -> #REF! | J88: =SUM(I88,J87) -> #REF! | K88: =J88/$J$104 -> #REF! | L88: =SUM(U88,X88,AA88,AD88) -> #REF! | M88: =SUM(L88,M87) -> #REF! | N88: =G88*AE88 -> 0.013620885 | O88: =SUM(N88,O87) -> 0.81725312 | P88: =M88/$M$93 -> #REF! | Q88: =R88/F88 -> 0 | R88: 0 | S88: L | T88: =IF(S88="L",0.68,IF(S88="JP",0.57,IF(S88="JI",0.57,IF(S88="JD",0.57,IF(S88="P",0.24,IF(S88="I",0.12,IF(S88="D",0.13))))))) -> 0.68 | U88: =T88*R88 -> 0 | V88: =W88/F88 -> #REF! | W88: =#REF!+#REF!+#REF!+#REF!+#REF!+#REF!+#REF! -> #REF! | X88: =#REF!+#REF!+#REF!+#REF!+#REF!+#REF!+#REF! -> #REF! | Y88: =Z88/F88 -> #REF! | Z88: =#REF!+#REF!+#REF!+#REF!+#REF!+#REF!+#REF!+#REF! -> #REF! | AA88: =#REF!+#REF!+#REF!+#REF!+#REF!+#REF!+#REF!+#REF! -> #REF! | AB88: =AC88/F88 -> #REF! | AC88: =#REF!+#REF!+#REF!+#REF!+#REF!+#REF!+#REF!+#REF! -> #REF! | AD88: =#REF!+#REF!+#REF!+#REF!+#REF!+#REF!+#REF!+#REF! -> #REF! | AE88: 1 | AF88: ='PL Cronograma detallado'!L241*AE88 -> 0 | AG88: =AF88/'PL Cronograma detallado'!M$257 -> #DIV/0! | AH88: =SUM(AG88,AH87) -> #DIV/0!
A89: 4.1.4 | B89: Documentar Pruebas de Software | C89: 44746 | D89: 44751 | E89: =_xludf.DAYs(D89,C89)+1 -> #NAME? | F89: 10 | G89: =F89/F$105 -> 0.011350738 | H89: =SUM(H88,G89) -> 0.82973893 | I89: =SUM(R89,W89,Z89,AC89) -> #REF! | J89: =SUM(I89,J88) -> #REF! | K89: =J89/$J$104 -> #REF! | L89: =SUM(U89,X89,AA89,AD89) -> #REF! | M89: =SUM(L89,M88) -> #REF! | N89: =G89*AE89 -> 0.011350738 | O89: =SUM(N89,O88) -> 0.82860386 | P89: =M89/$M$93 -> #REF! | Q89: =R89/F89 -> 0 | R89: 0 | S89: L | T89: =IF(S89="L",0.68,IF(S89="JP",0.57,IF(S89="JI",0.57,IF(S89="JD",0.57,IF(S89="P",0.24,IF(S89="I",0.12,IF(S89="D",0.13))))))) -> 0.68 | U89: =T89*R89 -> 0 | V89: =W89/F89 -> #REF! | W89: =#REF!+#REF!+#REF!+#REF!+#REF!+#REF!+#REF! -> #REF! | X89: =#REF!+#REF!+#REF!+#REF!+#REF!+#REF!+#REF! -> #REF! | Y89: =Z89/F89 -> #REF! | Z89: =#REF!+#REF!+#REF!+#REF!+#REF!+#REF!+#REF!+#REF! -> #REF! | AA89: =#REF!+#REF!+#REF!+#REF!+#REF!+#REF!+#REF!+#REF! -> #REF! | AB89: =AC89/F89 -> #REF! | AC89: =#REF!+#REF!+#REF!+#REF!+#REF!+#REF!+#REF!+#REF! -> #REF! | AD89: =#REF!+#REF!+#REF!+#REF!+#REF!+#REF!+#REF!+#REF! -> #REF! | AE89: 1 | AF89: ='PL Cronograma detallado'!L242*AE89 -> 0 | AG89: =AF89/'PL Cronograma detallado'!M$257 -> #DIV/0! | AH89: =SUM(AG89,AH88) -> #DIV/0!
A90: 4.1.5 | B90: Realizar conclusiones y recomendaciones | C90: 44751 | D90: 44753 | E90: =_xludf.DAYs(D90,C90)+1 -> #NAME? | F90: 8 | G90: =F90/F$105 -> 0.0090805902 | H90: =SUM(H89,G90) -> 0.83881952 | I90: =SUM(R90,W90,Z90,AC90) -> #REF! | J90: =SUM(I90,J89) -> #REF! | K90: =J90/$J$104 -> #REF! | L90: =SUM(U90,X90,AA90,AD90) -> #REF! | M90: =SUM(L90,M89) -> #REF! | N90: =G90*AE90 -> 0.0090805902 | O90: =SUM(N90,O89) -> 0.83768445 | P90: =M90/$M$93 -> #REF! | Q90: =R90/F90 -> 0.125 | R90: 1 | S90: L | T90: =IF(S90="L",0.68,IF(S90="JP",0.57,IF(S90="JI",0.57,IF(S90="JD",0.57,IF(S90="P",0.24,IF(S90="I",0.12,IF(S90="D",0.13))))))) -> 0.68 | U90: =T90*R90 -> 0.68 | V90: =W90/F90 -> #REF! | W90: =#REF!+#REF!+#REF!+#REF!+#REF!+#REF!+#REF! -> #REF! | X90: =#REF!+#REF!+#REF!+#REF!+#REF!+#REF!+#REF! -> #REF! | Y90: =Z90/F90 -> #REF! | Z90: =#REF!+#REF!+#REF!+#REF!+#REF!+#REF!+#REF!+#REF! -> #REF! | AA90: =#REF!+#REF!+#REF!+#REF!+#REF!+#REF!+#REF!+#REF! -> #REF! | AB90: =AC90/F90 -> #REF! | AC90: =#REF!+#REF!+#REF!+#REF!+#REF!+#REF!+#REF!+#REF! -> #REF! | AD90: =#REF!+#REF!+#REF!+#REF!+#REF!+#REF!+#REF!+#REF! -> #REF! | AE90: 1 | AF90: ='PL Cronograma detallado'!L243*AE90 -> 0 | AG90: =AF90/'PL Cronograma detallado'!M$257 -> #DIV/0! | AH90: =SUM(AG90,AH89) -> #DIV/0!
A91: 4.1.6 | B91: Reunión de Líderes 14 | C91: 44752 | D91: 44752 | E91: =_xludf.DAYs(D91,C91)+1 -> #NAME? | F91: 1 | G91: =F91/F$105 -> 0.0011350738 | H91: =SUM(H90,G91) -> 0.8399546 | I91: =SUM(R91,W91,Z91,AC91) -> #REF! | J91: =SUM(I91,J90) -> #REF! | K91: =J91/$J$104 -> #REF! | L91: =SUM(U91,X91,AA91,AD91) -> #REF! | M91: =SUM(L91,M90) -> #REF! | N91: =G91*AE91 -> 0.0011350738 | O91: =SUM(N91,O90) -> 0.83881952 | P91: =M91/$M$93 -> #REF! | Q91: =R91/F91 -> 1 | R91: 1 | S91: L | T91: =IF(S91="L",0.68,IF(S91="JP",0.57,IF(S91="JI",0.57,IF(S91="JD",0.57,IF(S91="P",0.24,IF(S91="I",0.12,IF(S91="D",0.13))))))) -> 0.68 | U91: =T91*R91 -> 0.68 | V91: =W91/F91 -> #REF! | W91: =#REF!+#REF!+#REF!+#REF!+#REF!+#REF!+#REF! -> #REF! | X91: =#REF!+#REF!+#REF!+#REF!+#REF!+#REF!+#REF! -> #REF! | Y91: =Z91/F91 -> #REF! | Z91: =#REF!+#REF!+#REF!+#REF!+#REF!+#REF!+#REF!+#REF! -> #REF! | AA91: =#REF!+#REF!+#REF!+#REF!+#REF!+#REF!+#REF!+#REF! -> #REF! | AB91: =AC91/F91 -> #REF! | AC91: =#REF!+#REF!+#REF!+#REF!+#REF!+#REF!+#REF!+#REF! -> #REF! | AD91: =#REF!+#REF!+#REF!+#REF!+#REF!+#REF!+#REF!+#REF! -> #REF! | AE91: 1 | AF91: ='PL Cronograma detallado'!L244*AE91 -> 0 | AG91: =AF91/'PL Cronograma detallado'!M$257 -> #DIV/0! | AH91: =SUM(AG91,AH90) -> #DIV/0!
A92: 5 | B92: Fase de Cierre del Proyecto | C92: 44754 | D92: 44770 | E92: =_xludf.DAYs(D92,C92)+1 -> #NAME? | F92: =F93 -> 141 | G92: =G93 -> 0.1600454 | I92: =SUM(I93) -> #REF! | J92: =SUM(I92,J84) -> #REF! | K92: =J92/$J$104 -> #REF! | L92: =SUM(L93) -> #REF! | M92: =SUM(L92,M91) -> #REF! | O92: =AH92 | P92: =M92/$M$93 -> #REF! | Q92: =R92/F92 -> 0 | R92: 0 | S92: L | T92: =IF(S92="L",0.68,IF(S92="JP",0.57,IF(S92="JI",0.57,IF(S92="JD",0.57,IF(S92="P",0.24,IF(S92="I",0.12,IF(S92="D",0.13))))))) -> 0.68 | U92: =T92*R92 -> 0 | V92: =W92/F92 -> #REF! | W92: =#REF!+#REF!+#REF!+#REF!+#REF!+#REF!+#REF! -> #REF! | X92: =#REF!+#REF!+#REF!+#REF!+#REF!+#REF!+#REF! -> #REF! | Y92: =Z92/F92 -> #REF! | Z92: =#REF!+#REF!+#REF!+#REF!+#REF!+#REF!+#REF!+#REF! -> #REF! | AA92: =#REF!+#REF!+#REF!+#REF!+#REF!+#REF!+#REF!+#REF! -> #REF! | AB92: =AC92/F92 -> #REF! | AC92: =#REF!+#REF!+#REF!+#REF!+#REF!+#REF!+#REF!+#REF! -> #REF! | AD92: =#REF!+#REF!+#REF!+#REF!+#REF!+#REF!+#REF!+#REF! -> #REF!
A93: 5.1 | B93: Elaboración Documentación Final | C93: 44743 | D93: 44761 | E93: =_xludf.DAYs(D93,C93)+1 -> #NAME? | F93: =SUM(F94:F104) -> 141 | G93: =SUM(G94:G104) -> 0.1600454 | H93: =SUM(G93,H91) -> 1 | I93: =SUM(I94:I104) -> #REF! | J93: =SUM(I93,J91) -> #REF! | K93: =J93/$J$104 -> #REF! | L93: =SUM(L94:L104) -> #REF! | M93: =SUM(L93,M91) -> #REF! | O93: =AH93 | P93: =M93/M93 -> #REF! | Q93: =R93/F93 -> 0 | R93: 0 | S93: L | T93: =IF(S93="L",0.68,IF(S93="JP",0.57,IF(S93="JI",0.57,IF(S93="JD",0.57,IF(S93="P",0.24,IF(S93="I",0.12,IF(S93="D",0.13))))))) -> 0.68 | U93: =T93*R93 -> 0 | V93: =W93/F93 -> #REF! | W93: =#REF!+#REF!+#REF!+#REF!+#REF!+#REF!+#REF! -> #REF! | X93: =#REF!+#REF!+#REF!+#REF!+#REF!+#REF!+#REF! -> #REF! | Y93: =Z93/F93 -> #REF! | Z93: =#REF!+#REF!+#REF!+#REF!+#REF!+#REF!+#REF!+#REF! -> #REF! | AA93: =#REF!+#REF!+#REF!+#REF!+#REF!+#REF!+#REF!+#REF! -> #REF! | AB93: =AC93/F93 -> #REF! | AC93: =#REF!+#REF!+#REF!+#REF!+#REF!+#REF!+#REF!+#REF! -> #REF! | AD93: =#REF!+#REF!+#REF!+#REF!+#REF!+#REF!+#REF!+#REF! -> #REF!
A94: 5.1.1 | B94: Recopilación de Información del Proyecto | C94: 44743 | D94: 44746 | E94: =_xludf.DAYs(D94,C94)+1 -> #NAME? | F94: 12 | G94: =F94/F$105 -> 0.013620885 | H94: =SUM(H91,G94) -> 0.85357548 | I94: =SUM(R94,W94,Z94,AC94) -> #REF! | J94: =SUM(I94,J91) -> #REF! | K94: =J94/$J$104 -> #REF! | L94: =SUM(U94,X94,AA94,AD94) -> #REF! | M94: =SUM(L94,M91) -> #REF! | N94: =G94*AE94 -> 0.013620885 | O94: =SUM(N94,O91) -> 0.85244041 | P94: =M94/$M$93 -> #REF! | Q94: =R94/F94 -> 0 | R94: 0 | S94: L | T94: =IF(S94="L",0.68,IF(S94="JP",0.57,IF(S94="JI",0.57,IF(S94="JD",0.57,IF(S94="P",0.24,IF(S94="I",0.12,IF(S94="D",0.13))))))) -> 0.68 | U94: =T94*R94 -> 0 | V94: =W94/F94 -> #REF! | W94: =#REF!+#REF!+#REF!+#REF!+#REF!+#REF!+#REF! -> #REF! | X94: =#REF!+#REF!+#REF!+#REF!+#REF!+#REF!+#REF! -> #REF! | Y94: =Z94/F94 -> #REF! | Z94: =#REF!+#REF!+#REF!+#REF!+#REF!+#REF!+#REF!+#REF! -> #REF! | AA94: =#REF!+#REF!+#REF!+#REF!+#REF!+#REF!+#REF!+#REF! -> #REF! | AB94: =AC94/F94 -> #REF! | AC94: =#REF!+#REF!+#REF!+#REF!+#REF!+#REF!+#REF!+#REF! -> #REF! | AD94: =#REF!+#REF!+#REF!+#REF!+#REF!+#REF!+#REF!+#REF! -> #REF! | AE94: 1 | AF94: ='PL Cronograma detallado'!L247*AE94 -> 0 | AG94: =AF94/'PL Cronograma detallado'!M$257 -> #DIV/0! | AH94: =SUM(AG94,AH91) -> #DIV/0!
A95: 5.1.2 | B95: Elaboración Informe Final (Parte 1) | C95: 44746 | D95: 44753 | E95: =_xludf.DAYs(D95,C95)+1 -> #NAME? | F95: 18 | G95: =F95/F$105 -> 0.020431328 | H95: =SUM(H94,G95) -> 0.87400681 | I95: =SUM(R95,W95,Z95,AC95) -> #REF! | J95: =SUM(I95,J94) -> #REF! | K95: =J95/$J$104 -> #REF! | L95: =SUM(U95,X95,AA95,AD95) -> #REF! | M95: =SUM(L95,M94) -> #REF! | N95: =G95*AE95 -> 0.020431328 | O95: =SUM(N95,O94) -> 0.87287174 | P95: =M95/M95 -> #REF! | Q95: =R95/F95 -> 0.11111111 | R95: 2 | S95: L | T95: =IF(S95="L",0.68,IF(S95="JP",0.57,IF(S95="JI",0.57,IF(S95="JD",0.57,IF(S95="P",0.24,IF(S95="I",0.12,IF(S95="D",0.13))))))) -> 0.68 | U95: =T95*R95 -> 1.36 | V95: =W95/F95 -> #REF! | W95: =#REF!+#REF!+#REF!+#REF!+#REF!+#REF!+#REF! -> #REF! | X95: =#REF!+#REF!+#REF!+#REF!+#REF!+#REF!+#REF! -> #REF! | Y95: =Z95/F95 -> #REF! | Z95: =#REF!+#REF!+#REF!+#REF!+#REF!+#REF!+#REF!+#REF! -> #REF! | AA95: =#REF!+#REF!+#REF!+#REF!+#REF!+#REF!+#REF!+#REF! -> #REF! | AB95: =AC95/F95 -> #REF! | AC95: =#REF!+#REF!+#REF!+#REF!+#REF!+#REF!+#REF!+#REF! -> #REF! | AD95: =#REF!+#REF!+#REF!+#REF!+#REF!+#REF!+#REF!+#REF! -> #REF! | AE95: 1 | AF95: ='PL Cronograma detallado'!L248*AE95 -> 0 | AG95: =AF95/'PL Cronograma detallado'!M$257 -> #DIV/0! | AH95: =SUM(AG95,AH94) -> #DIV/0!
A96: 5.1.3 | B96: Elaboración Paper (Parte 1) | C96: 44746 | D96: 44753 | E96: =_xludf.DAYs(D96,C96)+1 -> #NAME? | F96: 18 | G96: =F96/F$105 -> 0.020431328 | H96: =SUM(H95,G96) -> 0.89443814 | I96: =SUM(R96,W96,Z96,AC96) -> #REF! | J96: =SUM(I96,J95) -> #REF! | K96: =J96/$J$104 -> #REF! | L96: =SUM(U96,X96,AA96,AD96) -> #REF! | M96: =SUM(L96,M95) -> #REF! | N96: =G96*AE96 -> 0.010215664 | O96: =SUM(N96,O95) -> 0.8830874 | P96: =M96/$M$93 -> #REF! | Q96: =R96/F96 -> 0 | R96: 0 | S96: L | T96: =IF(S96="L",0.68,IF(S96="JP",0.57,IF(S96="JI",0.57,IF(S96="JD",0.57,IF(S96="P",0.24,IF(S96="I",0.12,IF(S96="D",0.13))))))) -> 0.68 | U96: =T96*R96 -> 0 | V96: =W96/F96 -> #REF! | W96: =#REF!+#REF!+#REF!+#REF!+#REF!+#REF!+#REF! -> #REF! | X96: =#REF!+#REF!+#REF!+#REF!+#REF!+#REF!+#REF! -> #REF! | Y96: =Z96/F96 -> #REF! | Z96: =#REF!+#REF!+#REF!+#REF!+#REF!+#REF!+#REF!+#REF! -> #REF! | AA96: =#REF!+#REF!+#REF!+#REF!+#REF!+#REF!+#REF!+#REF! -> #REF! | AB96: =AC96/F96 -> #REF! | AC96: =#REF!+#REF!+#REF!+#REF!+#REF!+#REF!+#REF!+#REF! -> #REF! | AD96: =#REF!+#REF!+#REF!+#REF!+#REF!+#REF!+#REF!+#REF! -> #REF! | AE96: 0.5 | AF96: ='PL Cronograma detallado'!L249*AE96 -> 0 | AG96: =AF96/'PL Cronograma detallado'!M$257 -> #DIV/0! | AH96: =SUM(AG96,AH95) -> #DIV/0!
A97: 5.2 | B97: Elaboración Informe de Avance N°5 | C97: 44746 | D97: 44753 | E97: =_xludf.DAYs(D97,C97)+1 -> #NAME? | F97: 24 | G97: =(F97/F105) -> 0.027241771 | H97: =SUM(H96,G97) -> 0.92167991 | I97: =SUM(R97,W97,Z97,AC97) -> #REF! | J97: =SUM(I97,J96) -> #REF! | L97: =SUM(U97,X97,AA97,AD97) -> #REF! | M97: =SUM(L97,M96) -> #REF! | N97: =G97*AE97 -> 0.027241771 | O97: =SUM(N97,O96) -> 0.91032917 | P97: =M97/M97 -> #REF! | Q97: =R97/F97 -> 0 | R97: 0 | S97: L | T97: =IF(S97="L",0.68,IF(S97="JP",0.57,IF(S97="JI",0.57,IF(S97="JD",0.57,IF(S97="P",0.24,IF(S97="I",0.12,IF(S97="D",0.13))))))) -> 0.68 | U97: =T97*R97 -> 0 | V97: =W97/F97 -> #REF! | W97: =#REF!+#REF!+#REF!+#REF!+#REF!+#REF!+#REF! -> #REF! | X97: =#REF!+#REF!+#REF!+#REF!+#REF!+#REF!+#REF! -> #REF! | Y97: =Z97/F97 -> #REF! | Z97: =#REF!+#REF!+#REF!+#REF!+#REF!+#REF!+#REF!+#REF! -> #REF! | AA97: =#REF!+#REF!+#REF!+#REF!+#REF!+#REF!+#REF!+#REF! -> #REF! | AB97: =AC97/F97 -> #REF! | AC97: =#REF!+#REF!+#REF!+#REF!+#REF!+#REF!+#REF!+#REF! -> #REF! | AD97: =#REF!+#REF!+#REF!+#REF!+#REF!+#REF!+#REF!+#REF! -> #REF! | AE97: 1 | AF97: ='PL Cronograma detallado'!L250*AE97 -> 0 | AG97: =AF97/'PL Cronograma detallado'!M$257 -> #DIV/0! | AH97: =SUM(AG97,AH96) -> #DIV/0!
A98: H6 | B98: Entrega de Avance N°5 y Defensa | C98: 44754 | D98: 44754 | E98: =_xludf.DAYs(D98,C98)+1 -> #NAME? | F98: 1 | G98: =(F98/F105) -> 0.0011350738 | H98: =SUM(H97,G98) -> 0.92281498 | I98: =SUM(R98,W98,Z98,AC98) -> #REF! | J98: =SUM(I98,J97) -> #REF! | K98: =J98/$J$104 -> #REF! | L98: =SUM(U98,X98,AA98,AD98) -> #REF! | M98: =SUM(L98,M97) -> #REF! | N98: =G98*AE98 -> 0.0011350738 | O98: =SUM(N98,O97) -> 0.91146425 | P98: =M98/$M$93 -> #REF! | Q98: =R98/F98 -> 1 | R98: 1 | S98: L | T98: =IF(S98="L",0.68,IF(S98="JP",0.57,IF(S98="JI",0.57,IF(S98="JD",0.57,IF(S98="P",0.24,IF(S98="I",0.12,IF(S98="D",0.13))))))) -> 0.68 | U98: =T98*R98 -> 0.68 | V98: =W98/F98 -> #REF! | W98: =#REF!+#REF!+#REF!+#REF!+#REF!+#REF!+#REF! -> #REF! | X98: =#REF!+#REF!+#REF!+#REF!+#REF!+#REF!+#REF! -> #REF! | Y98: =Z98/F98 -> #REF! | Z98: =#REF!+#REF!+#REF!+#REF!+#REF!+#REF!+#REF!+#REF! -> #REF! | AA98: =#REF!+#REF!+#REF!+#REF!+#REF!+#REF!+#REF!+#REF! -> #REF! | AB98: =AC98/F98 -> #REF! | AC98: =#REF!+#REF!+#REF!+#REF!+#REF!+#REF!+#REF!+#REF! -> #REF! | AD98: =#REF!+#REF!+#REF!+#REF!+#REF!+#REF!+#REF!+#REF! -> #REF! | AE98: 1 | AF98: ='PL Cronograma detallado'!L251*AE98 -> 0 | AG98: =AF98/'PL Cronograma detallado'!M$257 -> #DIV/0! | AH98: =SUM(AG98,AH97) -> #DIV/0!
A99: 5.1.4 | B99: Elaboración Informe Final (parte 2) | C99: 44754 | D99: 44761 | E99: =_xludf.DAYs(D99,C99)+1 -> #NAME? | F99: 32 | G99: =F99/F$105 -> 0.036322361 | H99: =SUM(H98,G99) -> 0.95913734 | I99: =SUM(R99,W99,Z99,AC99) -> #REF! | J99: =SUM(I99,J98) -> #REF! | K99: =J99/$J$104 -> #REF! | L99: =SUM(U99,X99,AA99,AD99) -> #REF! | M99: =SUM(L99,M98) -> #REF! | N99: =G99*AE99 -> 0.036322361 | O99: =SUM(N99,O98) -> 0.94778661 | P99: =M99/M99 -> #REF! | Q99: =R99/F99 -> 0.1875 | R99: 6 | S99: L | T99: =IF(S99="L",0.68,IF(S99="JP",0.57,IF(S99="JI",0.57,IF(S99="JD",0.57,IF(S99="P",0.24,IF(S99="I",0.12,IF(S99="D",0.13))))))) -> 0.68 | U99: =T99*R99 -> 4.08 | V99: =W99/F99 -> #REF! | W99: =#REF!+#REF!+#REF!+#REF!+#REF!+#REF!+#REF! -> #REF! | X99: =#REF!+#REF!+#REF!+#REF!+#REF!+#REF!+#REF! -> #REF! | Y99: =Z99/F99 -> #REF! | Z99: =#REF!+#REF!+#REF!+#REF!+#REF!+#REF!+#REF!+#REF! -> #REF! | AA99: =#REF!+#REF!+#REF!+#REF!+#REF!+#REF!+#REF!+#REF! -> #REF! | AB99: =AC99/F99 -> #REF! | AC99: =#REF!+#REF!+#REF!+#REF!+#REF!+#REF!+#REF!+#REF! -> #REF! | AD99: =#REF!+#REF!+#REF!+#REF!+#REF!+#REF!+#REF!+#REF! -> #REF! | AE99: 1 | AF99: ='PL Cronograma detallado'!L252*AE99 -> 0 | AG99: =AF99/'PL Cronograma detallado'!M$257 -> #DIV/0! | AH99: =SUM(AG99,AH98) -> #DIV/0!
A100: 5.1.5 | B100: Elaboración Paper (parte 2) | C100: 44754 | D100: 44761 | E100: =_xludf.DAYs(D100,C100)+1 -> #NAME? | F100: 32 | G100: =F100/F$105 -> 0.036322361 | H100: =SUM(H99,G100) -> 0.9954597 | I100: =SUM(R100,W100,Z100,AC100) -> #REF! | J100: =SUM(I100,J99) -> #REF! | K100: =J100/$J$104 -> #REF! | L100: =SUM(U100,X100,AA100,AD100) -> #REF! | M100: =SUM(L100,M99) -> #REF! | N100: =G100*AE100 -> 0 | O100: =SUM(N100,O99) -> 0.94778661 | P100: =M100/$M$93 -> #REF! | Q100: =R100/F100 -> 0 | R100: 0 | S100: L | T100: =IF(S100="L",0.68,IF(S100="JP",0.57,IF(S100="JI",0.57,IF(S100="JD",0.57,IF(S100="P",0.24,IF(S100="I",0.12,IF(S100="D",0.13))))))) -> 0.68 | U100: =T100*R100 -> 0 | V100: =W100/F100 -> #REF! | W100: =#REF!+#REF!+#REF!+#REF!+#REF!+#REF!+#REF! -> #REF! | X100: =#REF!+#REF!+#REF!+#REF!+#REF!+#REF!+#REF! -> #REF! | Y100: =Z100/F100 -> #REF! | Z100: =#REF!+#REF!+#REF!+#REF!+#REF!+#REF!+#REF!+#REF! -> #REF! | AA100: =#REF!+#REF!+#REF!+#REF!+#REF!+#REF!+#REF!+#REF! -> #REF! | AB100: =AC100/F100 -> #REF! | AC100: =#REF!+#REF!+#REF!+#REF!+#REF!+#REF!+#REF!+#REF! -> #REF! | AD100: =#REF!+#REF!+#REF!+#REF!+#REF!+#REF!+#REF!+#REF! -> #REF! | AF100: ='PL Cronograma detallado'!L253*AE100 -> 0 | AG100: =AF100/'PL Cronograma detallado'!M$257 -> #DIV/0! | AH100: =SUM(AG100,AH99) -> #DIV/0!
...

Sheet Hitos
A1: Hito | C1: Fecha | D1: Avance Planificado | E1: Avance Real | F1: Desviación
A2: N° | B2: Descripción
A3: 0 | B3: Entrega Informe Propuesta inicial | C3: 46268 | D3: ='PL Cronograma General'!K2 -> 0 | E3: 0% | F3: =E3-D3 -> 0
A4: 1 | B4: Entrega Informe Propuesta V1 | C4: 46275 | D4: ='PL Cronograma detallado'!H29 -> 0.049956934 | E4: ='R Cronograma detallado'!O22 -> 0.032730405 | F4: =E4-D4 -> -0.017226529
A5: 2 | B5: Entrega Avance N°1 y Defensa | C5: 46289 | D5: ='PL Cronograma detallado'!H79 -> 0.25925926 | E5: ='R Cronograma detallado'!O47 -> 0.096468562 | F5: =E5-D5 -> -0.1627907
A6: 3 | B6: Entrega Avance N°2 y Defensa | C6: 46310 | D6: ='PL Cronograma detallado'!H145 -> 0.52885444
A7: 4 | B7: Entrega Avance N°3 y Defensa | C7: 46331 | D7: ='PL Cronograma detallado'!H185 -> 0.71748493
A8: 5 | B8: Entrega Avance N°4 y Defensa (Hito 5) | C8: 46352 | D8: ='PL Cronograma detallado'!H212 -> 0.89750215
A9: 6 | B9: Entrega Informe Final (Hito 6) | C9: 46367 | D9: ='PL Cronograma detallado'!H238 -> 1

Sheet PL Cronograma General
A1: N° | B1: Actividad | C1: Inicio | D1: Término | E1: Días | F1: HH | G1: Esfuerzo(HH) unit. | H1: Esfuerzo (HH) acum. | I1: Costo (UF) unit. | J1: Costo (UF) acum. | K1: % Avance Planificado | L1: % Avance Real
A2: ='PL Cronograma detallado'!A4 -> H0 | B2: ='PL Cronograma detallado'!B4 -> Entrega Informe Propuesta inicial (Hito 0) | C2: ='PL Cronograma detallado'!C4 -> 46268 | D2: ='PL Cronograma detallado'!D4 -> 46268 | E2: ='PL Cronograma detallado'!E4 -> 1 | F2: ='PL Cronograma detallado'!F4 -> 0 | G2: 0 | H2: 0 | I2: 0 | J2: 0 | K2: 0 | L2: 0
A3: ='PL Cronograma detallado'!A5 -> 1 | B3: ='PL Cronograma detallado'!B5 -> Inicio proyecto | C3: ='PL Cronograma detallado'!C5 -> 46268 | D3: ='PL Cronograma detallado'!D5 -> 46274 | E3: ='PL Cronograma detallado'!E5 -> 7 | F3: ='PL Cronograma detallado'!F5 -> 58 | G3: ='PL Cronograma detallado'!I5 -> 145 | H3: ='PL Cronograma detallado'!J5 -> 145 | I3: ='PL Cronograma detallado'!L5 -> 54.39 | J3: ='PL Cronograma detallado'!M5 -> 54.39 | K3: ='PL Cronograma detallado'!H5 -> 0.049956934 | L3: ='R Cronograma detallado'!O5 -> 0
A4: ='PL Cronograma detallado'!A29 -> H1 | B4: ='PL Cronograma detallado'!B29 -> Entrega Informe Propuesta V1 (Hito 1) | C4: ='PL Cronograma detallado'!C29 -> 46275 | D4: ='PL Cronograma detallado'!D29 -> 46275 | E4: ='PL Cronograma detallado'!E29 -> 1 | F4: ='PL Cronograma detallado'!F29 -> 0 | G4: ='PL Cronograma detallado'!I29 -> 0 | H4: ='PL Cronograma detallado'!J29 -> 145 | I4: ='PL Cronograma detallado'!L29 -> 0 | J4: ='PL Cronograma detallado'!M29 -> 54.39 | K4: ='PL Cronograma detallado'!H29 -> 0.049956934 | L4: ='R Cronograma detallado'!O22 -> 0.032730405
A5: ='PL Cronograma detallado'!A30 -> 2 | B5: ='PL Cronograma detallado'!B30 -> Planificación de Alcances y Diseño de la Arquitectura | C5: ='PL Cronograma detallado'!C30 -> 46275 | D5: ='PL Cronograma detallado'!D30 -> 46289 | E5: ='PL Cronograma detallado'!E30 -> 15 | F5: ='PL Cronograma detallado'!F30 -> 243 | G5: ='PL Cronograma detallado'!I30 -> 1074 | H5: ='PL Cronograma detallado'!J30 -> 1219 | I5: ='PL Cronograma detallado'!L30 -> 182.68 | J5: ='PL Cronograma detallado'!M30 -> 237.07 | K5: ='PL Cronograma detallado'!H30 -> 0.25925926 | L5: ='R Cronograma detallado'!O23 -> 0.032730405
A6: ='PL Cronograma detallado'!A79 -> H2 | B6: ='PL Cronograma detallado'!B79 -> Entrega Avance N°1 y Defensa (Hito 2) | C6: ='PL Cronograma detallado'!C79 -> 46289 | D6: ='PL Cronograma detallado'!D79 -> 46289 | E6: ='PL Cronograma detallado'!E79 -> 1 | F6: ='PL Cronograma detallado'!F79 -> 0 | G6: ='PL Cronograma detallado'!I79 -> 0 | H6: ='PL Cronograma detallado'!J79 -> 1219 | I6: ='PL Cronograma detallado'!L79 -> 0 | J6: ='PL Cronograma detallado'!M79 -> 237.07 | K6: ='PL Cronograma detallado'!H79 -> 0.25925926 | L6: ='R Cronograma detallado'!O47 -> 0.096468562
A7: ='PL Cronograma detallado'!A80 -> 3 | B7: ='PL Cronograma detallado'!B80 -> Construcción del Conocimiento | C7: ='PL Cronograma detallado'!C80 -> 46290 | D7: ='PL Cronograma detallado'!D80 -> 46310 | E7: ='PL Cronograma detallado'!E80 -> 21 | F7: ='PL Cronograma detallado'!F80 -> 313 | G7: ='PL Cronograma detallado'!I80 -> 785 | H7: ='PL Cronograma detallado'!J80 -> 2004 | I7: ='PL Cronograma detallado'!L80 -> 162.08 | J7: ='PL Cronograma detallado'!M80 -> 399.15 | K7: ='PL Cronograma detallado'!H80 -> 0.52885444 | L7: ='R Cronograma detallado'!O48 -> 0.099913867
A8: ='PL Cronograma detallado'!A145 -> H3 | B8: ='PL Cronograma detallado'!B145 -> Entrega Avance N°2 y Defensa (Hito 3) | C8: ='PL Cronograma detallado'!C145 -> 46310 | D8: ='PL Cronograma detallado'!D145 -> 46310 | E8: ='PL Cronograma detallado'!E145 -> 1 | F8: ='PL Cronograma detallado'!F145 -> 0 | G8: ='PL Cronograma detallado'!I145 -> 0 | H8: ='PL Cronograma detallado'!J145 -> 2004 | I8: ='PL Cronograma detallado'!L145 -> 0 | J8: ='PL Cronograma detallado'!M145 -> 399.15 | K8: ='PL Cronograma detallado'!H145 -> 0.52885444 | L8: ='R Cronograma detallado'!O63 -> 0.15331611
A9: ='PL Cronograma detallado'!A146 -> 4 | B9: ='PL Cronograma detallado'!B146 -> Integración de Datos | C9: ='PL Cronograma detallado'!C146 -> 46311 | D9: ='PL Cronograma detallado'!D146 -> 46331 | E9: ='PL Cronograma detallado'!E146 -> 21 | F9: ='PL Cronograma detallado'!F146 -> 219 | G9: ='PL Cronograma detallado'!I146 -> 351 | H9: ='PL Cronograma detallado'!J146 -> 2355 | I9: ='PL Cronograma detallado'!L146 -> 75.1 | J9: ='PL Cronograma detallado'!M146 -> 474.25 | K9: ='PL Cronograma detallado'!H146 -> 0.71748493 | L9: ='R Cronograma detallado'!O64 -> 0.16192937
A10: ='PL Cronograma detallado'!A185 -> H4 | B10: ='PL Cronograma detallado'!B185 -> Entrega Avance N°3 y Defensa (Hito 4) | C10: ='PL Cronograma detallado'!C185 -> 46331 | D10: ='PL Cronograma detallado'!D185 -> 46331 | E10: ='PL Cronograma detallado'!E185 -> 1 | F10: ='PL Cronograma detallado'!F185 -> 0 | G10: ='PL Cronograma detallado'!I185 -> 0 | H10: ='PL Cronograma detallado'!J185 -> 2355 | I10: ='PL Cronograma detallado'!L185 -> 0 | J10: ='PL Cronograma detallado'!M185 -> 474.25 | K10: ='PL Cronograma detallado'!H185 -> 0.71748493 | L10: ='R Cronograma detallado'!O80 -> 0.25925926
A11: ='PL Cronograma detallado'!A186 -> 5 | B11: ='PL Cronograma detallado'!B186 -> Implementación Multiagente | C11: ='PL Cronograma detallado'!C186 -> 46332 | D11: ='PL Cronograma detallado'!D186 -> 46352 | E11: ='PL Cronograma detallado'!E186 -> 21 | F11: ='PL Cronograma detallado'!F186 -> 209 | G11: ='PL Cronograma detallado'!I186 -> 318 | H11: ='PL Cronograma detallado'!J186 -> 2673 | I11: ='PL Cronograma detallado'!L186 -> 63.59 | J11: ='PL Cronograma detallado'!M186 -> 537.84 | K11: ='PL Cronograma detallado'!H186 -> 0.89750215 | L11: ='R Cronograma detallado'!O81 -> 0.25925926
A12: ='PL Cronograma detallado'!A212 -> H5 | B12: ='PL Cronograma detallado'!B212 -> Entrega Avance N°4 y Defensa (Hito 5) | C12: ='PL Cronograma detallado'!C212 -> 46352 | D12: ='PL Cronograma detallado'!D212 -> 46352 | E12: ='PL Cronograma detallado'!E212 -> 1 | F12: ='PL Cronograma detallado'!F212 -> 0 | G12: ='PL Cronograma detallado'!I212 -> 0 | H12: ='PL Cronograma detallado'!J212 -> 2673 | I12: ='PL Cronograma detallado'!L212 -> 0 | J12: ='PL Cronograma detallado'!M212 -> 537.84 | K12: ='PL Cronograma detallado'!H212 -> 0.89750215 | L12: ='R Cronograma detallado'!O97 -> 0.30577089
A13: ='PL Cronograma detallado'!A213 -> 6 | B13: ='PL Cronograma detallado'!B213 -> Generación de Informes y Validación | C13: ='PL Cronograma detallado'!C213 -> 46353 | D13: ='PL Cronograma detallado'!D213 -> 46367 | E13: ='PL Cronograma detallado'!E213 -> 15 | F13: ='PL Cronograma detallado'!F213 -> 119 | G13: ='PL Cronograma detallado'!I213 -> 235 | H13: ='PL Cronograma detallado'!J213 -> 2908 | I13: ='PL Cronograma detallado'!L213 -> 51.68 | J13: ='PL Cronograma detallado'!M213 -> 589.52 | K13: ='PL Cronograma detallado'!H213 -> 1 | L13: ='R Cronograma detallado'!O98 -> 0.30921619
A14: ='PL Cronograma detallado'!A238 -> H6 | B14: ='PL Cronograma detallado'!B238 -> Entrega Informe Final (Hito 6) | C14: ='PL Cronograma detallado'!C238 -> 46367 | D14: ='PL Cronograma detallado'!D238 -> 46367 | E14: ='PL Cronograma detallado'!E238 -> 1 | F14: ='PL Cronograma detallado'!F238 -> 0 | G14: ='PL Cronograma detallado'!I238 -> 0 | H14: ='PL Cronograma detallado'!J238 -> 2908 | I14: ='PL Cronograma detallado'!L238 -> 0 | J14: ='PL Cronograma detallado'!M238 -> 589.52 | K14: ='PL Cronograma detallado'!H238 -> 1 | L14: ='R Cronograma detallado'!O113 -> 0.35228252

Sheet PL Cronograma detallado
A1: S | O1: Área
A2: N° | B2: Actividad | C2: Fecha | E2: Dias | F2: HH | G2: % Impacto | H2: % Avance PL | I2: Esfuerzo (HH) | L2: Costo (UF) | O2: Jefe de proyecto | T2: Documentación | Y2: Investigación | AD2: Desarrollo
C3: Inicio | D3: Termino | I3: Unit. | J3: Acum. | K3: % De uso | L3: Unit. | M3: Acum. | N3: % De uso | O3: % dedic | P3: HH esfuerzo | Q3: Rol | R3: Valor HH (UF) | S3: Costo (UF) | T3: % dedic | U3: HH esfuerzo | V3: Rol | W3: Valor HH (UF) | X3: Costo (UF) | Y3: % dedic | Z3: HH esfuerzo | AA3: Rol | AB3: Valor HH (UF) | AC3: Costo (UF) | AD3: % dedic | AE3: HH esfuerzo | AF3: Rol | AG3: Valor HH (UF) | AH3: Costo (UF)
A4: H0 | B4: Entrega Informe Propuesta inicial (Hito 0) | C4: 46268 | D4: 46268 | E4: =D4-C4+1 -> 1 | F4: 0 | G4: =F4/$F$239 -> 0 | H4: =G4 -> 0 | I4: =F4 -> 0 | J4: =I4 -> 0 | K4: =J4/$I$239 -> 0 | L4: 0 | M4: =L4 -> 0 | N4: =M4/$L$239 -> 0
A5: 1 | B5: Inicio proyecto | C5: 46268 | D5: 46274 | E5: =D5-C5+1 -> 7 | F5: =F6+F10+F23 -> 58 | G5: =F5/$F$239 -> 0.049956934 | H5: =H28 -> 0.049956934 | I5: =I6+I10+I23 -> 119.5 | J5: =J28 -> 119.5 | K5: =J5/$I$239 -> 0.045567207 | L5: =L6+L10+L23 -> 33.78 | M5: =M28 -> 33.78 | N5: =M5/$L$239 -> 0.075639849
A6: 1.1 | B6: Relevamiento inicial del Proyecto | C6: 46268 | D6: 46270 | E6: =D6-C6+1 -> 3 | F6: =SUM(F7:F9) -> 8 | G6: =F6/$F$239 -> 0.0068906115 | H6: =H9 -> 0.0068906115 | I6: =SUM(I7:I9) -> 15 | J6: =J9 -> 15 | K6: =J6/$I$239 -> 0.0057197331 | L6: =SUM(L7:L9) -> 3.21 | M6: =M9 -> 3.21 | N6: =M6/$L$239 -> 0.0071878009
A7: 1.1.1 | B7: Definición de Roles | C7: 46268 | D7: 46269 | E7: =D7-C7+1 -> 2 | F7: 1 | G7: =F7/$F$239 -> 0.00086132644 | H7: =H4+G7 -> 0.00086132644 | I7: =P7+U7+Z7+AE7 -> 1 | J7: =J4+I7 -> 1 | K7: =J7/$I$239 -> 0.00038131554 | L7: =S7+X7+AC7+AH7 -> 0.61 | M7: =M4+L7 -> 0.61 | N7: =M7/$L$239 -> 0.0013659061 | O7: =P7/$F7 -> 1 | P7: 1 | R7: =Roles!$D$2 -> 0.61 | S7: =R7*P7 -> 0.61 | T7: =U7/$F7 -> 0 | U7: 0 | W7: =Roles!$D$8 -> 0.09 | X7: =MIN(U7,1)*Roles!$D$5+MAX(U7-1,0)*W7 -> 0 | Y7: =Z7/$F7 -> 0 | Z7: 0 | AB7: =Roles!$D$7 -> 0.12 | AC7: =MIN(Z7,1)*Roles!$D$4+MAX(Z7-1,0)*AB7 -> 0 | AD7: =AE7/$F7 -> 0 | AE7: 0 | AG7: =Roles!$D$6 -> 0.1 | AH7: =MIN(AE7,1)*Roles!$D$3+MAX(AE7-1,0)*AG7 -> 0
A8: 1.1.2 | B8: Relevamiento inicial del problema y contexto One Health | C8: 46268 | D8: 46269 | E8: =D8-C8+1 -> 2 | F8: 4 | G8: =F8/$F$239 -> 0.0034453058 | H8: =H7+G8 -> 0.0043066322 | I8: =P8+U8+Z8+AE8 -> 8 | J8: =J7+I8 -> 9 | K8: =J8/$I$239 -> 0.0034318398 | L8: =S8+X8+AC8+AH8 -> 1.28 | M8: =M7+L8 -> 1.89 | N8: =M8/$L$239 -> 0.0042320697 | O8: =P8/$F8 -> 0 | P8: 0 | R8: =Roles!$D$2 -> 0.61 | S8: =R8*P8 -> 0 | T8: =U8/$F8 -> 0 | U8: 0 | W8: =Roles!$D$8 -> 0.09 | X8: =MIN(U8,1)*Roles!$D$5+MAX(U8-1,0)*W8 -> 0 | Y8: =Z8/$F8 -> 2 | Z8: 8 | AB8: =Roles!$D$7 -> 0.12 | AC8: =MIN(Z8,1)*Roles!$D$4+MAX(Z8-1,0)*AB8 -> 1.28 | AD8: =AE8/$F8 -> 0 | AE8: 0 | AG8: =Roles!$D$6 -> 0.1 | AH8: =MIN(AE8,1)*Roles!$D$3+MAX(AE8-1,0)*AG8 -> 0
A9: 1.1.3 | B9: Análisis de viabilidad técnica y metodológica del proyecto | C9: 46269 | D9: 46270 | E9: =D9-C9+1 -> 2 | F9: 3 | G9: =F9/$F$239 -> 0.0025839793 | H9: =H8+G9 -> 0.0068906115 | I9: =P9+U9+Z9+AE9 -> 6 | J9: =J8+I9 -> 15 | K9: =J9/$I$239 -> 0.0057197331 | L9: =S9+X9+AC9+AH9 -> 1.32 | M9: =M8+L9 -> 3.21 | N9: =M9/$L$239 -> 0.0071878009 | O9: =P9/$F9 -> 0 | P9: 0 | R9: =Roles!$D$2 -> 0.61 | S9: =R9*P9 -> 0 | T9: =U9/$F9 -> 0 | U9: 0 | W9: =Roles!$D$8 -> 0.09 | X9: =MIN(U9,1)*Roles!$D$5+MAX(U9-1,0)*W9 -> 0 | Y9: =Z9/$F9 -> 1 | Z9: 3 | AB9: =Roles!$D$7 -> 0.12 | AC9: =MIN(Z9,1)*Roles!$D$4+MAX(Z9-1,0)*AB9 -> 0.68 | AD9: =AE9/$F9 -> 1 | AE9: 3 | AG9: =Roles!$D$6 -> 0.1 | AH9: =MIN(AE9,1)*Roles!$D$3+MAX(AE9-1,0)*AG9 -> 0.64
A10: 1.2 | B10: Gestión del Alcance | C10: 46268 | D10: 46272 | E10: =D10-C10+1 -> 5 | F10: =SUM(F11:F22) -> 30 | G10: =F10/$F$239 -> 0.025839793 | H10: =H22 -> 0.032730405 | I10: =SUM(I11:I22) -> 67.5 | J10: =J22 -> 82.5 | K10: =J10/$I$239 -> 0.031458532 | L10: =SUM(L11:L22) -> 22.95 | M10: =M22 -> 26.16 | N10: =M10/$L$239 -> 0.058577218
A11: 1.2.1 | B11: Organización de grupos de Trabajo | C11: 46268 | D11: 46268 | E11: =D11-C11+1 -> 1 | F11: 1 | G11: =F11/$F$239 -> 0.00086132644 | H11: =H9+G11 -> 0.007751938 | I11: =P11+U11+Z11+AE11 -> 5 | J11: =J9+I11 -> 20 | K11: =J11/$I$239 -> 0.0076263108 | L11: =S11+X11+AC11+AH11 -> 1.73 | M11: =M9+L11 -> 4.94 | N11: =M11/$L$239 -> 0.0110616 | O11: =P11/$F11 -> 1 | P11: 1 | R11: =Roles!$D$2 -> 0.61 | S11: =R11*P11 -> 0.61 | T11: =U11/$F11 -> 1 | U11: 1 | W11: =Roles!$D$8 -> 0.09 | X11: =MIN(U11,1)*Roles!$D$5+MAX(U11-1,0)*W11 -> 0.44 | Y11: =Z11/$F11 -> 3 | Z11: 3 | AB11: =Roles!$D$7 -> 0.12 | AC11: =MIN(Z11,1)*Roles!$D$4+MAX(Z11-1,0)*AB11 -> 0.68 | AD11: =AE11/$F11 -> 0 | AE11: 0 | AG11: =Roles!$D$6 -> 0.1 | AH11: =MIN(AE11,1)*Roles!$D$3+MAX(AE11-1,0)*AG11 -> 0
A12: 1.2.2 | B12: Definir Metodologias | C12: 46268 | D12: 46268 | E12: =D12-C12+1 -> 1 | F12: 2 | G12: =F12/$F$239 -> 0.0017226529 | H12: =H11+G12 -> 0.0094745909 | I12: =P12+U12+Z12+AE12 -> 4 | J12: =J11+I12 -> 24 | K12: =J12/$I$239 -> 0.0091515729 | L12: =S12+X12+AC12+AH12 -> 1.61 | M12: =M11+L12 -> 6.55 | N12: =M12/$L$239 -> 0.014666697 | O12: =P12/$F12 -> 0.5 | P12: 1 | R12: =Roles!$D$2 -> 0.61 | S12: =R12*P12 -> 0.61 | T12: =U12/$F12 -> 0.5 | U12: 1 | W12: =Roles!$D$8 -> 0.09 | X12: =MIN(U12,1)*Roles!$D$5+MAX(U12-1,0)*W12 -> 0.44 | Y12: =Z12/$F12 -> 1 | Z12: 2 | AB12: =Roles!$D$7 -> 0.12 | AC12: =MIN(Z12,1)*Roles!$D$4+MAX(Z12-1,0)*AB12 -> 0.56 | AD12: =AE12/$F12 -> 0 | AE12: 0 | AG12: =Roles!$D$6 -> 0.1 | AH12: =MIN(AE12,1)*Roles!$D$3+MAX(AE12-1,0)*AG12 -> 0
A13: 1.2.3 | B13: Definir Plan de Hitos | C13: 46268 | D13: 46268 | E13: =D13-C13+1 -> 1 | F13: 1 | G13: =F13/$F$239 -> 0.00086132644 | H13: =H12+G13 -> 0.010335917 | I13: =P13+U13+Z13+AE13 -> 2.5 | J13: =J12+I13 -> 26.5 | K13: =J13/$I$239 -> 0.010104862 | L13: =S13+X13+AC13+AH13 -> 1.27 | M13: =M12+L13 -> 7.82 | N13: =M13/$L$239 -> 0.017510468 | O13: =P13/$F13 -> 1 | P13: 1 | R13: =Roles!$D$2 -> 0.61 | S13: =R13*P13 -> 0.61 | T13: =U13/$F13 -> 0.5 | U13: 0.5 | W13: =Roles!$D$8 -> 0.09 | X13: =MIN(U13,1)*Roles!$D$5+MAX(U13-1,0)*W13 -> 0.22 | Y13: =Z13/$F13 -> 1 | Z13: 1 | AB13: =Roles!$D$7 -> 0.12 | AC13: =MIN(Z13,1)*Roles!$D$4+MAX(Z13-1,0)*AB13 -> 0.44 | AD13: =AE13/$F13 -> 0 | AE13: 0 | AG13: =Roles!$D$6 -> 0.1 | AH13: =MIN(AE13,1)*Roles!$D$3+MAX(AE13-1,0)*AG13 -> 0
A14: 1.2.4 | B14: Definir Costos | C14: 46268 | D14: 46268 | E14: =D14-C14+1 -> 1 | F14: 1 | G14: =F14/$F$239 -> 0.00086132644 | H14: =H13+G14 -> 0.011197244 | I14: =P14+U14+Z14+AE14 -> 6 | J14: =J13+I14 -> 32.5 | K14: =J14/$I$239 -> 0.012392755 | L14: =S14+X14+AC14+AH14 -> 1.85 | M14: =M13+L14 -> 9.67 | N14: =M14/$L$239 -> 0.02165297 | O14: =P14/$F14 -> 1 | P14: 1 | R14: =Roles!$D$2 -> 0.61 | S14: =R14*P14 -> 0.61 | T14: =U14/$F14 -> 1 | U14: 1 | W14: =Roles!$D$8 -> 0.09 | X14: =MIN(U14,1)*Roles!$D$5+MAX(U14-1,0)*W14 -> 0.44 | Y14: =Z14/$F14 -> 4 | Z14: 4 | AB14: =Roles!$D$7 -> 0.12 | AC14: =MIN(Z14,1)*Roles!$D$4+MAX(Z14-1,0)*AB14 -> 0.8 | AD14: =AE14/$F14 -> 0 | AE14: 0 | AG14: =Roles!$D$6 -> 0.1 | AH14: =MIN(AE14,1)*Roles!$D$3+MAX(AE14-1,0)*AG14 -> 0
A15: 1.2.5 | B15: Definir Criterio de Evaluación de Integrantes | C15: 46268 | D15: 46268 | E15: =D15-C15+1 -> 1 | F15: 1 | G15: =F15/$F$239 -> 0.00086132644 | H15: =H14+G15 -> 0.01205857 | I15: =P15+U15+Z15+AE15 -> 5 | J15: =J14+I15 -> 37.5 | K15: =J15/$I$239 -> 0.014299333 | L15: =S15+X15+AC15+AH15 -> 1.73 | M15: =M14+L15 -> 11.4 | N15: =M15/$L$239 -> 0.02552677 | O15: =P15/$F15 -> 1 | P15: 1 | R15: =Roles!$D$2 -> 0.61 | S15: =R15*P15 -> 0.61 | T15: =U15/$F15 -> 1 | U15: 1 | W15: =Roles!$D$8 -> 0.09 | X15: =MIN(U15,1)*Roles!$D$5+MAX(U15-1,0)*W15 -> 0.44 | Y15: =Z15/$F15 -> 3 | Z15: 3 | AB15: =Roles!$D$7 -> 0.12 | AC15: =MIN(Z15,1)*Roles!$D$4+MAX(Z15-1,0)*AB15 -> 0.68 | AD15: =AE15/$F15 -> 0 | AE15: 0 | AG15: =Roles!$D$6 -> 0.1 | AH15: =MIN(AE15,1)*Roles!$D$3+MAX(AE15-1,0)*AG15 -> 0
A16: 1.2.6 | B16: Definición de Enfoques y Justificación | C16: 46268 | D16: 46269 | E16: =D16-C16+1 -> 2 | F16: 2 | G16: =F16/$F$239 -> 0.0017226529 | H16: =H15+G16 -> 0.013781223 | I16: =P16+U16+Z16+AE16 -> 6 | J16: =J15+I16 -> 43.5 | K16: =J16/$I$239 -> 0.016587226 | L16: =S16+X16+AC16+AH16 -> 2.31 | M16: =M15+L16 -> 13.71 | N16: =M16/$L$239 -> 0.030699299 | O16: =P16/$F16 -> 1 | P16: 2 | R16: =Roles!$D$2 -> 0.61 | S16: =R16*P16 -> 1.22 | T16: =U16/$F16 -> 1 | U16: 2 | W16: =Roles!$D$8 -> 0.09 | X16: =MIN(U16,1)*Roles!$D$5+MAX(U16-1,0)*W16 -> 0.53 | Y16: =Z16/$F16 -> 1 | Z16: 2 | AB16: =Roles!$D$7 -> 0.12 | AC16: =MIN(Z16,1)*Roles!$D$4+MAX(Z16-1,0)*AB16 -> 0.56 | AD16: =AE16/$F16 -> 0 | AE16: 0 | AG16: =Roles!$D$6 -> 0.1 | AH16: =MIN(AE16,1)*Roles!$D$3+MAX(AE16-1,0)*AG16 -> 0
A17: 1.2.7 | B17: Establecer Alcances y Limitaciones | C17: 46268 | D17: 46269 | E17: =D17-C17+1 -> 2 | F17: 2 | G17: =F17/$F$239 -> 0.0017226529 | H17: =H16+G17 -> 0.015503876 | I17: =P17+U17+Z17+AE17 -> 6 | J17: =J16+I17 -> 49.5 | K17: =J17/$I$239 -> 0.018875119 | L17: =S17+X17+AC17+AH17 -> 2.31 | M17: =M16+L17 -> 16.02 | N17: =M17/$L$239 -> 0.035871829 | O17: =P17/$F17 -> 1 | P17: 2 | R17: =Roles!$D$2 -> 0.61 | S17: =R17*P17 -> 1.22 | T17: =U17/$F17 -> 1 | U17: 2 | W17: =Roles!$D$8 -> 0.09 | X17: =MIN(U17,1)*Roles!$D$5+MAX(U17-1,0)*W17 -> 0.53 | Y17: =Z17/$F17 -> 1 | Z17: 2 | AB17: =Roles!$D$7 -> 0.12 | AC17: =MIN(Z17,1)*Roles!$D$4+MAX(Z17-1,0)*AB17 -> 0.56 | AD17: =AE17/$F17 -> 0 | AE17: 0 | AG17: =Roles!$D$6 -> 0.1 | AH17: =MIN(AE17,1)*Roles!$D$3+MAX(AE17-1,0)*AG17 -> 0
A18: 1.2.8 | B18: Elaborar Cronograma | C18: 46268 | D18: 46271 | E18: =D18-C18+1 -> 4 | F18: 5 | G18: =F18/$F$239 -> 0.0043066322 | H18: =H17+G18 -> 0.019810508 | I18: =P18+U18+Z18+AE18 -> 9 | J18: =J17+I18 -> 58.5 | K18: =J18/$I$239 -> 0.022306959 | L18: =S18+X18+AC18+AH18 -> 3.16 | M18: =M17+L18 -> 19.18 | N18: =M18/$L$239 -> 0.04294767 | O18: =P18/$F18 -> 0.6 | P18: 3 | R18: =Roles!$D$2 -> 0.61 | S18: =R18*P18 -> 1.83 | T18: =U18/$F18 -> 0.4 | U18: 2 | W18: =Roles!$D$8 -> 0.09 | X18: =MIN(U18,1)*Roles!$D$5+MAX(U18-1,0)*W18 -> 0.53 | Y18: =Z18/$F18 -> 0.8 | Z18: 4 | AB18: =Roles!$D$7 -> 0.12 | AC18: =MIN(Z18,1)*Roles!$D$4+MAX(Z18-1,0)*AB18 -> 0.8 | AD18: =AE18/$F18 -> 0 | AE18: 0 | AG18: =Roles!$D$6 -> 0.1 | AH18: =MIN(AE18,1)*Roles!$D$3+MAX(AE18-1,0)*AG18 -> 0
A19: 1.2.9 | B19: Elaboración presentación | C19: 46268 | D19: 46272 | E19: =D19-C19+1 -> 5 | F19: 5 | G19: =F19/$F$239 -> 0.0043066322 | H19: =H18+G19 -> 0.02411714 | I19: =P19+U19+Z19+AE19 -> 6 | J19: =J18+I19 -> 64.5 | K19: =J19/$I$239 -> 0.024594852 | L19: =S19+X19+AC19+AH19 -> 1.79 | M19: =M18+L19 -> 20.97 | N19: =M19/$L$239 -> 0.046955821 | O19: =P19/$F19 -> 0.2 | P19: 1 | R19: =Roles!$D$2 -> 0.61 | S19: =R19*P19 -> 0.61 | T19: =U19/$F19 -> 0.6 | U19: 3 | W19: =Roles!$D$8 -> 0.09 | X19: =MIN(U19,1)*Roles!$D$5+MAX(U19-1,0)*W19 -> 0.62 | Y19: =Z19/$F19 -> 0.4 | Z19: 2 | AB19: =Roles!$D$7 -> 0.12 | AC19: =MIN(Z19,1)*Roles!$D$4+MAX(Z19-1,0)*AB19 -> 0.56 | AD19: =AE19/$F19 -> 0 | AE19: 0 | AG19: =Roles!$D$6 -> 0.1 | AH19: =MIN(AE19,1)*Roles!$D$3+MAX(AE19-1,0)*AG19 -> 0
A20: 1.2.10 | B20: Distribución del Esfuerzo | C20: 46269 | D20: 46270 | E20: =D20-C20+1 -> 2 | F20: 4 | G20: =F20/$F$239 -> 0.0034453058 | H20: =H19+G20 -> 0.027562446 | I20: =P20+U20+Z20+AE20 -> 8 | J20: =J19+I20 -> 72.5 | K20: =J20/$I$239 -> 0.027645377 | L20: =S20+X20+AC20+AH20 -> 2.55 | M20: =M19+L20 -> 23.52 | N20: =M20/$L$239 -> 0.052665756 | O20: =P20/$F20 -> 0.5 | P20: 2 | R20: =Roles!$D$2 -> 0.61 | S20: =R20*P20 -> 1.22 | T20: =U20/$F20 -> 0.5 | U20: 2 | W20: =Roles!$D$8 -> 0.09 | X20: =MIN(U20,1)*Roles!$D$5+MAX(U20-1,0)*W20 -> 0.53 | Y20: =Z20/$F20 -> 1 | Z20: 4 | AB20: =Roles!$D$7 -> 0.12 | AC20: =MIN(Z20,1)*Roles!$D$4+MAX(Z20-1,0)*AB20 -> 0.8 | AD20: =AE20/$F20 -> 0 | AE20: 0 | AG20: =Roles!$D$6 -> 0.1 | AH20: =MIN(AE20,1)*Roles!$D$3+MAX(AE20-1,0)*AG20 -> 0
A21: 1.2.11 | B21: Definición de la WBS y la OBS del proyecto | C21: 46269 | D21: 46270 | E21: =D21-C21+1 -> 2 | F21: 3 | G21: =F21/$F$239 -> 0.0025839793 | H21: =H20+G21 -> 0.030146425 | I21: =P21+U21+Z21+AE21 -> 5 | J21: =J20+I21 -> 77.5 | K21: =J21/$I$239 -> 0.029551954 | L21: =S21+X21+AC21+AH21 -> 1.32 | M21: =M20+L21 -> 24.84 | N21: =M21/$L$239 -> 0.055621487 | O21: =P21/$F21 -> 0.33333333 | P21: 1 | R21: =Roles!$D$2 -> 0.61 | S21: =R21*P21 -> 0.61 | T21: =U21/$F21 -> 1.3333333 | U21: 4 | W21: =Roles!$D$8 -> 0.09 | X21: =MIN(U21,1)*Roles!$D$5+MAX(U21-1,0)*W21 -> 0.71 | Y21: =Z21/$F21 -> 0 | Z21: 0 | AB21: =Roles!$D$7 -> 0.12 | AC21: =MIN(Z21,1)*Roles!$D$4+MAX(Z21-1,0)*AB21 -> 0 | AD21: =AE21/$F21 -> 0 | AE21: 0 | AG21: =Roles!$D$6 -> 0.1 | AH21: =MIN(AE21,1)*Roles!$D$3+MAX(AE21-1,0)*AG21 -> 0
A22: 1.2.12 | B22: Grafo PERT/CPM, camino crítico y Curva S de planificación | C22: 46270 | D22: 46271 | E22: =D22-C22+1 -> 2 | F22: 3 | G22: =F22/$F$239 -> 0.0025839793 | H22: =H21+G22 -> 0.032730405 | I22: =P22+U22+Z22+AE22 -> 5 | J22: =J21+I22 -> 82.5 | K22: =J22/$I$239 -> 0.031458532 | L22: =S22+X22+AC22+AH22 -> 1.32 | M22: =M21+L22 -> 26.16 | N22: =M22/$L$239 -> 0.058577218 | O22: =P22/$F22 -> 0.33333333 | P22: 1 | R22: =Roles!$D$2 -> 0.61 | S22: =R22*P22 -> 0.61 | T22: =U22/$F22 -> 1.3333333 | U22: 4 | W22: =Roles!$D$8 -> 0.09 | X22: =MIN(U22,1)*Roles!$D$5+MAX(U22-1,0)*W22 -> 0.71 | Y22: =Z22/$F22 -> 0 | Z22: 0 | AB22: =Roles!$D$7 -> 0.12 | AC22: =MIN(Z22,1)*Roles!$D$4+MAX(Z22-1,0)*AB22 -> 0 | AD22: =AE22/$F22 -> 0 | AE22: 0 | AG22: =Roles!$D$6 -> 0.1 | AH22: =MIN(AE22,1)*Roles!$D$3+MAX(AE22-1,0)*AG22 -> 0
A23: 1.3 | B23: Elaboración Informe Propuesta | C23: 46268 | D23: 46274 | E23: =D23-C23+1 -> 7 | F23: =SUM(F24:F28) -> 20 | G23: =F23/$F$239 -> 0.017226529 | H23: =H28 -> 0.049956934 | I23: =SUM(I24:I28) -> 37 | J23: =J28 -> 119.5 | K23: =J23/$I$239 -> 0.045567207 | L23: =SUM(L24:L28) -> 7.62 | M23: =M28 -> 33.78 | N23: =M23/$L$239 -> 0.075639849
A24: 1.3.1 | B24: Elaboración informe de propuesta | C24: 46268 | D24: 46274 | E24: =D24-C24+1 -> 7 | F24: 8 | G24: =F24/$F$239 -> 0.0068906115 | H24: =H22+G24 -> 0.039621016 | I24: =P24+U24+Z24+AE24 -> 10 | J24: =J22+I24 -> 92.5 | K24: =J24/$I$239 -> 0.035271687 | L24: =S24+X24+AC24+AH24 -> 1.77 | M24: =M22+L24 -> 27.93 | N24: =M24/$L$239 -> 0.062540585 | O24: =P24/$F24 -> 0.125 | P24: 1 | R24: =Roles!$D$2 -> 0.61 | S24: =R24*P24 -> 0.61 | T24: =U24/$F24 -> 1.125 | U24: 9 | W24: =Roles!$D$8 -> 0.09 | X24: =MIN(U24,1)*Roles!$D$5+MAX(U24-1,0)*W24 -> 1.16 | Y24: =Z24/$F24 -> 0 | Z24: 0 | AB24: =Roles!$D$7 -> 0.12 | AC24: =MIN(Z24,1)*Roles!$D$4+MAX(Z24-1,0)*AB24 -> 0 | AD24: =AE24/$F24 -> 0 | AE24: 0 | AG24: =Roles!$D$6 -> 0.1 | AH24: =MIN(AE24,1)*Roles!$D$3+MAX(AE24-1,0)*AG24 -> 0
A25: 1.3.2 | B25: Formulación preliminar del problema, pregunta y objetivos de investigación | C25: 46269 | D25: 46271 | E25: =D25-C25+1 -> 3 | F25: 4 | G25: =F25/$F$239 -> 0.0034453058 | H25: =H24+G25 -> 0.043066322 | I25: =P25+U25+Z25+AE25 -> 8 | J25: =J24+I25 -> 100.5 | K25: =J25/$I$239 -> 0.038322212 | L25: =S25+X25+AC25+AH25 -> 1.28 | M25: =M24+L25 -> 29.21 | N25: =M25/$L$239 -> 0.065406749 | O25: =P25/$F25 -> 0 | P25: 0 | R25: =Roles!$D$2 -> 0.61 | S25: =R25*P25 -> 0 | T25: =U25/$F25 -> 0 | U25: 0 | W25: =Roles!$D$8 -> 0.09 | X25: =MIN(U25,1)*Roles!$D$5+MAX(U25-1,0)*W25 -> 0 | Y25: =Z25/$F25 -> 2 | Z25: 8 | AB25: =Roles!$D$7 -> 0.12 | AC25: =MIN(Z25,1)*Roles!$D$4+MAX(Z25-1,0)*AB25 -> 1.28 | AD25: =AE25/$F25 -> 0 | AE25: 0 | AG25: =Roles!$D$6 -> 0.1 | AH25: =MIN(AE25,1)*Roles!$D$3+MAX(AE25-1,0)*AG25 -> 0
A26: 1.3.3 | B26: Identificación preliminar de tecnologías de IA (LLM, RAG, multiagente) | C26: 46270 | D26: 46272 | E26: =D26-C26+1 -> 3 | F26: 4 | G26: =F26/$F$239 -> 0.0034453058 | H26: =H25+G26 -> 0.046511628 | I26: =P26+U26+Z26+AE26 -> 8 | J26: =J25+I26 -> 108.5 | K26: =J26/$I$239 -> 0.041372736 | L26: =S26+X26+AC26+AH26 -> 1.14 | M26: =M25+L26 -> 30.35 | N26: =M26/$L$239 -> 0.067959426 | O26: =P26/$F26 -> 0 | P26: 0 | R26: =Roles!$D$2 -> 0.61 | S26: =R26*P26 -> 0 | T26: =U26/$F26 -> 0 | U26: 0 | W26: =Roles!$D$8 -> 0.09 | X26: =MIN(U26,1)*Roles!$D$5+MAX(U26-1,0)*W26 -> 0 | Y26: =Z26/$F26 -> 0 | Z26: 0 | AB26: =Roles!$D$7 -> 0.12 | AC26: =MIN(Z26,1)*Roles!$D$4+MAX(Z26-1,0)*AB26 -> 0 | AD26: =AE26/$F26 -> 2 | AE26: 8 | AG26: =Roles!$D$6 -> 0.1 | AH26: =MIN(AE26,1)*Roles!$D$3+MAX(AE26-1,0)*AG26 -> 1.14
A27: 1.3.4 | B27: Reunión de Líderes 1 | C27: 46271 | D27: 46271 | E27: =D27-C27+1 -> 1 | F27: 1 | G27: =F27/$F$239 -> 0.00086132644 | H27: =H26+G27 -> 0.047372954 | I27: =P27+U27+Z27+AE27 -> 4 | J27: =J26+I27 -> 112.5 | K27: =J27/$I$239 -> 0.042897998 | L27: =S27+X27+AC27+AH27 -> 1.93 | M27: =M26+L27 -> 32.28 | N27: =M27/$L$239 -> 0.072281063 | O27: =P27/$F27 -> 1 | P27: 1 | R27: =Roles!$D$2 -> 0.61 | S27: =R27*P27 -> 0.61 | T27: =U27/$F27 -> 1 | U27: 1 | W27: =Roles!$D$5 -> 0.44 | X27: =U27*W27 -> 0.44 | Y27: =Z27/$F27 -> 1 | Z27: 1 | AB27: =Roles!$D$4 -> 0.44 | AC27: =Z27*AB27 -> 0.44 | AD27: =AE27/$F27 -> 1 | AE27: 1 | AG27: =Roles!$D$3 -> 0.44 | AH27: =AE27*AG27 -> 0.44
A28: 1.3.5 | B28: Revisión de redacción, formato y referencias del informe de propuesta | C28: 46273 | D28: 46274 | E28: =D28-C28+1 -> 2 | F28: 3 | G28: =F28/$F$239 -> 0.0025839793 | H28: =H27+G28 -> 0.049956934 | I28: =P28+U28+Z28+AE28 -> 7 | J28: =J27+I28 -> 119.5 | K28: =J28/$I$239 -> 0.045567207 | L28: =S28+X28+AC28+AH28 -> 1.5 | M28: =M27+L28 -> 33.78 | N28: =M28/$L$239 -> 0.075639849 | O28: =P28/$F28 -> 0.33333333 | P28: 1 | R28: =Roles!$D$2 -> 0.61 | S28: =R28*P28 -> 0.61 | T28: =U28/$F28 -> 2 | U28: 6 | W28: =Roles!$D$8 -> 0.09 | X28: =MIN(U28,1)*Roles!$D$5+MAX(U28-1,0)*W28 -> 0.89 | Y28: =Z28/$F28 -> 0 | Z28: 0 | AB28: =Roles!$D$7 -> 0.12 | AC28: =MIN(Z28,1)*Roles!$D$4+MAX(Z28-1,0)*AB28 -> 0 | AD28: =AE28/$F28 -> 0 | AE28: 0 | AG28: =Roles!$D$6 -> 0.1 | AH28: =MIN(AE28,1)*Roles!$D$3+MAX(AE28-1,0)*AG28 -> 0
